Workbook

Sheet PAINEL
A1: PAINEL – MAPA COMPARATIVO DE FALHAS, ERROS E OUTROS DO MQT
A2: Pavilhão gimnodesportivo escolar · MQT_CUSTO-VENDA.XLS · 14 capítulos, 833 artigos · todos os valores por fórmula a partir das restantes folhas
A3: PARECER: NÃO VALIDAR o MQT na versão atual – corrigir os achados CRÍTICOS e ALTOS e voltar a submeter.
A4: INDICADORES
A5: Achados ativos (verificados) | C5: =COUNTIFS('MAPA COMPARATIVO'!$V$5:$V$206,"<>REJEITADO") -> 202
A6: dos quais CRÍTICOS | C6: =COUNTIFS('MAPA COMPARATIVO'!$G$5:$G$206,"CRÍTICA",'MAPA COMPARATIVO'!$V$5:$V$206,"<>REJEITADO") -> 1
A7: dos quais ALTOS | C7: =COUNTIFS('MAPA COMPARATIVO'!$G$5:$G$206,"ALTA",'MAPA COMPARATIVO'!$V$5:$V$206,"<>REJEITADO") -> 34
A8: Rejeitados na verificação (fora do mapa) | C8: =COUNTA('REJEITADOS NA VERIFICAÇÃO'!A5:A500) -> 9
A9: Custo MQT (€) | C9: ='CUSTO vs VENDA'!C21 -> 4499642.1
A10: Venda MQT (€) | C10: ='CUSTO vs VENDA'!D21 -> 4499630
A11: Venda − Custo (€) | C11: ='CUSTO vs VENDA'!E21 -> -12.12
A12: Impacto líquido cenário A (€) | C12: =SUMIFS('MAPA COMPARATIVO'!$O$5:$O$206,'MAPA COMPARATIVO'!$V$5:$V$206,"<>REJEITADO") -> 115594.89
A13: Impacto líquido cenário B (€) | C13: =SUMIFS('MAPA COMPARATIVO'!$P$5:$P$206,'MAPA COMPARATIVO'!$V$5:$V$206,"<>REJEITADO") -> 399725.14
A14: Custo corrigido cenário A (€) | C14: ='CUSTO vs VENDA'!I21 -> 4615237
A15: Custo corrigido cenário B (€) | C15: ='CUSTO vs VENDA'!J21 -> 4899367.2
A16: Venda proposta com K – cenário A (€) | C16: ='CUSTO vs VENDA'!K21 -> 5538284.4
A17: Venda proposta com K – cenário B (€) | C17: ='CUSTO vs VENDA'!L21 -> 5879240.7
A18: K usado (editar em CUSTO vs VENDA!C3) | C18: ='CUSTO vs VENDA'!C3 -> 1.2
A20: COMPARAÇÃO POR TIPO × GRAVIDADE
A21: Tipo | C21: CRÍTICA | D21: ALTA | E21: MÉDIA | F21: BAIXA | G21: TOTAL | H21: Impacto A – mín (€) | I21: Impacto B – máx (€)
A22: ERRO | C22: =COUNTIFS('MAPA COMPARATIVO'!$F$5:$F$206,$A22,'MAPA COMPARATIVO'!$G$5:$G$206,"CRÍTICA",'MAPA COMPARATIVO'!$V$5:$V$206,"<>REJEITADO") -> 1 | D22: =COUNTIFS('MAPA COMPARATIVO'!$F$5:$F$206,$A22,'MAPA COMPARATIVO'!$G$5:$G$206,"ALTA",'MAPA COMPARATIVO'!$V$5:$V$206,"<>REJEITADO") -> 3 | E22: =COUNTIFS('MAPA COMPARATIVO'!$F$5:$F$206,$A22,'MAPA COMPARATIVO'!$G$5:$G$206,"MÉDIA",'MAPA COMPARATIVO'!$V$5:$V$206,"<>REJEITADO") -> 4 | F22: =COUNTIFS('MAPA COMPARATIVO'!$F$5:$F$206,$A22,'MAPA COMPARATIVO'!$G$5:$G$206,"BAIXA",'MAPA COMPARATIVO'!$V$5:$V$206,"<>REJEITADO") -> 14 | G22: =SUM(C22:F22) -> 22 | H22: =SUMIFS('MAPA COMPARATIVO'!$O$5:$O$206,'MAPA COMPARATIVO'!$F$5:$F$206,$A22,'MAPA COMPARATIVO'!$V$5:$V$206,"<>REJEITADO") -> -10430.43 | I22: =SUMIFS('MAPA COMPARATIVO'!$P$5:$P$206,'MAPA COMPARATIVO'!$F$5:$F$206,$A22,'MAPA COMPARATIVO'!$V$5:$V$206,"<>REJEITADO") -> -20500.23
A23: FALHA/OMISSÃO | C23: =COUNTIFS('MAPA COMPARATIVO'!$F$5:$F$206,$A23,'MAPA COMPARATIVO'!$G$5:$G$206,"CRÍTICA",'MAPA COMPARATIVO'!$V$5:$V$206,"<>REJEITADO") -> 0 | D23: =COUNTIFS('MAPA COMPARATIVO'!$F$5:$F$206,$A23,'MAPA COMPARATIVO'!$G$5:$G$206,"ALTA",'MAPA COMPARATIVO'!$V$5:$V$206,"<>REJEITADO") -> 12 | E23: =COUNTIFS('MAPA COMPARATIVO'!$F$5:$F$206,$A23,'MAPA COMPARATIVO'!$G$5:$G$206,"MÉDIA",'MAPA COMPARATIVO'!$V$5:$V$206,"<>REJEITADO") -> 15 | F23: =COUNTIFS('MAPA COMPARATIVO'!$F$5:$F$206,$A23,'MAPA COMPARATIVO'!$G$5:$G$206,"BAIXA",'MAPA COMPARATIVO'!$V$5:$V$206,"<>REJEITADO") -> 4 | G23: =SUM(C23:F23) -> 31 | H23: =SUMIFS('MAPA COMPARATIVO'!$O$5:$O$206,'MAPA COMPARATIVO'!$F$5:$F$206,$A23,'MAPA COMPARATIVO'!$V$5:$V$206,"<>REJEITADO") -> 83480 | I23: =SUMIFS('MAPA COMPARATIVO'!$P$5:$P$206,'MAPA COMPARATIVO'!$F$5:$F$206,$A23,'MAPA COMPARATIVO'!$V$5:$V$206,"<>REJEITADO") -> 327087.24
A24: DUPLICAÇÃO | C24: =COUNTIFS('MAPA COMPARATIVO'!$F$5:$F$206,$A24,'MAPA COMPARATIVO'!$G$5:$G$206,"CRÍTICA",'MAPA COMPARATIVO'!$V$5:$V$206,"<>REJEITADO") -> 0 | D24: =COUNTIFS('MAPA COMPARATIVO'!$F$5:$F$206,$A24,'MAPA COMPARATIVO'!$G$5:$G$206,"ALTA",'MAPA COMPARATIVO'!$V$5:$V$206,"<>REJEITADO") -> 5 | E24: =COUNTIFS('MAPA COMPARATIVO'!$F$5:$F$206,$A24,'MAPA COMPARATIVO'!$G$5:$G$206,"MÉDIA",'MAPA COMPARATIVO'!$V$5:$V$206,"<>REJEITADO") -> 3 | F24: =COUNTIFS('MAPA COMPARATIVO'!$F$5:$F$206,$A24,'MAPA COMPARATIVO'!$G$5:$G$206,"BAIXA",'MAPA COMPARATIVO'!$V$5:$V$206,"<>REJEITADO") -> 9 | G24: =SUM(C24:F24) -> 17 | H24: =SUMIFS('MAPA COMPARATIVO'!$O$5:$O$206,'MAPA COMPARATIVO'!$F$5:$F$206,$A24,'MAPA COMPARATIVO'!$V$5:$V$206,"<>REJEITADO") -> -25714.01 | I24: =SUMIFS('MAPA COMPARATIVO'!$P$5:$P$206,'MAPA COMPARATIVO'!$F$5:$F$206,$A24,'MAPA COMPARATIVO'!$V$5:$V$206,"<>REJEITADO") -> -58092.59
A25: PREÇO BAIXO | C25: =COUNTIFS('MAPA COMPARATIVO'!$F$5:$F$206,$A25,'MAPA COMPARATIVO'!$G$5:$G$206,"CRÍTICA",'MAPA COMPARATIVO'!$V$5:$V$206,"<>REJEITADO") -> 0 | D25: =COUNTIFS('MAPA COMPARATIVO'!$F$5:$F$206,$A25,'MAPA COMPARATIVO'!$G$5:$G$206,"ALTA",'MAPA COMPARATIVO'!$V$5:$V$206,"<>REJEITADO") -> 6 | E25: =COUNTIFS('MAPA COMPARATIVO'!$F$5:$F$206,$A25,'MAPA COMPARATIVO'!$G$5:$G$206,"MÉDIA",'MAPA COMPARATIVO'!$V$5:$V$206,"<>REJEITADO") -> 20 | F25: =COUNTIFS('MAPA COMPARATIVO'!$F$5:$F$206,$A25,'MAPA COMPARATIVO'!$G$5:$G$206,"BAIXA",'MAPA COMPARATIVO'!$V$5:$V$206,"<>REJEITADO") -> 13 | G25: =SUM(C25:F25) -> 39 | H25: =SUMIFS('MAPA COMPARATIVO'!$O$5:$O$206,'MAPA COMPARATIVO'!$F$5:$F$206,$A25,'MAPA COMPARATIVO'!$V$5:$V$206,"<>REJEITADO") -> 106965.34 | I25: =SUMIFS('MAPA COMPARATIVO'!$P$5:$P$206,'MAPA COMPARATIVO'!$F$5:$F$206,$A25,'MAPA COMPARATIVO'!$V$5:$V$206,"<>REJEITADO") -> 262194.09
A26: PREÇO ALTO | C26: =COUNTIFS('MAPA COMPARATIVO'!$F$5:$F$206,$A26,'MAPA COMPARATIVO'!$G$5:$G$206,"CRÍTICA",'MAPA COMPARATIVO'!$V$5:$V$206,"<>REJEITADO") -> 0 | D26: =COUNTIFS('MAPA COMPARATIVO'!$F$5:$F$206,$A26,'MAPA COMPARATIVO'!$G$5:$G$206,"ALTA",'MAPA COMPARATIVO'!$V$5:$V$206,"<>REJEITADO") -> 0 | E26: =COUNTIFS('MAPA COMPARATIVO'!$F$5:$F$206,$A26,'MAPA COMPARATIVO'!$G$5:$G$206,"MÉDIA",'MAPA COMPARATIVO'!$V$5:$V$206,"<>REJEITADO") -> 1 | F26: =COUNTIFS('MAPA COMPARATIVO'!$F$5:$F$206,$A26,'MAPA COMPARATIVO'!$G$5:$G$206,"BAIXA",'MAPA COMPARATIVO'!$V$5:$V$206,"<>REJEITADO") -> 1 | G26: =SUM(C26:F26) -> 2 | H26: =SUMIFS('MAPA COMPARATIVO'!$O$5:$O$206,'MAPA COMPARATIVO'!$F$5:$F$206,$A26,'MAPA COMPARATIVO'!$V$5:$V$206,"<>REJEITADO") -> -3478.58 | I26: =SUMIFS('MAPA COMPARATIVO'!$P$5:$P$206,'MAPA COMPARATIVO'!$F$5:$F$206,$A26,'MAPA COMPARATIVO'!$V$5:$V$206,"<>REJEITADO") -> -5037.68
A27: INCOERÊNCIA | C27: =COUNTIFS('MAPA COMPARATIVO'!$F$5:$F$206,$A27,'MAPA COMPARATIVO'!$G$5:$G$206,"CRÍTICA",'MAPA COMPARATIVO'!$V$5:$V$206,"<>REJEITADO") -> 0 | D27: =COUNTIFS('MAPA COMPARATIVO'!$F$5:$F$206,$A27,'MAPA COMPARATIVO'!$G$5:$G$206,"ALTA",'MAPA COMPARATIVO'!$V$5:$V$206,"<>REJEITADO") -> 2 | E27: =COUNTIFS('MAPA COMPARATIVO'!$F$5:$F$206,$A27,'MAPA COMPARATIVO'!$G$5:$G$206,"MÉDIA",'MAPA COMPARATIVO'!$V$5:$V$206,"<>REJEITADO") -> 9 | F27: =COUNTIFS('MAPA COMPARATIVO'!$F$5:$F$206,$A27,'MAPA COMPARATIVO'!$G$5:$G$206,"BAIXA",'MAPA COMPARATIVO'!$V$5:$V$206,"<>REJEITADO") -> 13 | G27: =SUM(C27:F27) -> 24 | H27: =SUMIFS('MAPA COMPARATIVO'!$O$5:$O$206,'MAPA COMPARATIVO'!$F$5:$F$206,$A27,'MAPA COMPARATIVO'!$V$5:$V$206,"<>REJEITADO") -> -38297.49 | I27: =SUMIFS('MAPA COMPARATIVO'!$P$5:$P$206,'MAPA COMPARATIVO'!$F$5:$F$206,$A27,'MAPA COMPARATIVO'!$V$5:$V$206,"<>REJEITADO") -> -35930.15
A28: DESCRIÇÃO | C28: =COUNTIFS('MAPA COMPARATIVO'!$F$5:$F$206,$A28,'MAPA COMPARATIVO'!$G$5:$G$206,"CRÍTICA",'MAPA COMPARATIVO'!$V$5:$V$206,"<>REJEITADO") -> 0 | D28: =COUNTIFS('MAPA COMPARATIVO'!$F$5:$F$206,$A28,'MAPA COMPARATIVO'!$G$5:$G$206,"ALTA",'MAPA COMPARATIVO'!$V$5:$V$206,"<>REJEITADO") -> 3 | E28: =COUNTIFS('MAPA COMPARATIVO'!$F$5:$F$206,$A28,'MAPA COMPARATIVO'!$G$5:$G$206,"MÉDIA",'MAPA COMPARATIVO'!$V$5:$V$206,"<>REJEITADO") -> 9 | F28: =COUNTIFS('MAPA COMPARATIVO'!$F$5:$F$206,$A28,'MAPA COMPARATIVO'!$G$5:$G$206,"BAIXA",'MAPA COMPARATIVO'!$V$5:$V$206,"<>REJEITADO") -> 11 | G28: =SUM(C28:F28) -> 23 | H28: =SUMIFS('MAPA COMPARATIVO'!$O$5:$O$206,'MAPA COMPARATIVO'!$F$5:$F$206,$A28,'MAPA COMPARATIVO'!$V$5:$V$206,"<>REJEITADO") -> -172.1 | I28: =SUMIFS('MAPA COMPARATIVO'!$P$5:$P$206,'MAPA COMPARATIVO'!$F$5:$F$206,$A28,'MAPA COMPARATIVO'!$V$5:$V$206,"<>REJEITADO") -> -3452.71
A29: NORMA | C29: =COUNTIFS('MAPA COMPARATIVO'!$F$5:$F$206,$A29,'MAPA COMPARATIVO'!$G$5:$G$206,"CRÍTICA",'MAPA COMPARATIVO'!$V$5:$V$206,"<>REJEITADO") -> 0 | D29: =COUNTIFS('MAPA COMPARATIVO'!$F$5:$F$206,$A29,'MAPA COMPARATIVO'!$G$5:$G$206,"ALTA",'MAPA COMPARATIVO'!$V$5:$V$206,"<>REJEITADO") -> 2 | E29: =COUNTIFS('MAPA COMPARATIVO'!$F$5:$F$206,$A29,'MAPA COMPARATIVO'!$G$5:$G$206,"MÉDIA",'MAPA COMPARATIVO'!$V$5:$V$206,"<>REJEITADO") -> 5 | F29: =COUNTIFS('MAPA COMPARATIVO'!$F$5:$F$206,$A29,'MAPA COMPARATIVO'!$G$5:$G$206,"BAIXA",'MAPA COMPARATIVO'!$V$5:$V$206,"<>REJEITADO") -> 3 | G29: =SUM(C29:F29) -> 10 | H29: =SUMIFS('MAPA COMPARATIVO'!$O$5:$O$206,'MAPA COMPARATIVO'!$F$5:$F$206,$A29,'MAPA COMPARATIVO'!$V$5:$V$206,"<>REJEITADO") -> 3700 | I29: =SUMIFS('MAPA COMPARATIVO'!$P$5:$P$206,'MAPA COMPARATIVO'!$F$5:$F$206,$A29,'MAPA COMPARATIVO'!$V$5:$V$206,"<>REJEITADO") -> -62784.92
A30: INCOMPATIBILIDADE | C30: =COUNTIFS('MAPA COMPARATIVO'!$F$5:$F$206,$A30,'MAPA COMPARATIVO'!$G$5:$G$206,"CRÍTICA",'MAPA COMPARATIVO'!$V$5:$V$206,"<>REJEITADO") -> 0 | D30: =COUNTIFS('MAPA COMPARATIVO'!$F$5:$F$206,$A30,'MAPA COMPARATIVO'!$G$5:$G$206,"ALTA",'MAPA COMPARATIVO'!$V$5:$V$206,"<>REJEITADO") -> 0 | E30: =COUNTIFS('MAPA COMPARATIVO'!$F$5:$F$206,$A30,'MAPA COMPARATIVO'!$G$5:$G$206,"MÉDIA",'MAPA COMPARATIVO'!$V$5:$V$206,"<>REJEITADO") -> 1 | F30: =COUNTIFS('MAPA COMPARATIVO'!$F$5:$F$206,$A30,'MAPA COMPARATIVO'!$G$5:$G$206,"BAIXA",'MAPA COMPARATIVO'!$V$5:$V$206,"<>REJEITADO") -> 0 | G30: =SUM(C30:F30) -> 1 | H30: =SUMIFS('MAPA COMPARATIVO'!$O$5:$O$206,'MAPA COMPARATIVO'!$F$5:$F$206,$A30,'MAPA COMPARATIVO'!$V$5:$V$206,"<>REJEITADO") -> 0 | I30: =SUMIFS('MAPA COMPARATIVO'!$P$5:$P$206,'MAPA COMPARATIVO'!$F$5:$F$206,$A30,'MAPA COMPARATIVO'!$V$5:$V$206,"<>REJEITADO") -> 5066.5
A31: EXTRA/FORA DE ÂMBITO | C31: =COUNTIFS('MAPA COMPARATIVO'!$F$5:$F$206,$A31,'MAPA COMPARATIVO'!$G$5:$G$206,"CRÍTICA",'MAPA COMPARATIVO'!$V$5:$V$206,"<>REJEITADO") -> 0 | D31: =COUNTIFS('MAPA COMPARATIVO'!$F$5:$F$206,$A31,'MAPA COMPARATIVO'!$G$5:$G$206,"ALTA",'MAPA COMPARATIVO'!$V$5:$V$206,"<>REJEITADO") -> 0 | E31: =COUNTIFS('MAPA COMPARATIVO'!$F$5:$F$206,$A31,'MAPA COMPARATIVO'!$G$5:$G$206,"MÉDIA",'MAPA COMPARATIVO'!$V$5:$V$206,"<>REJEITADO") -> 1 | F31: =COUNTIFS('MAPA COMPARATIVO'!$F$5:$F$206,$A31,'MAPA COMPARATIVO'!$G$5:$G$206,"BAIXA",'MAPA COMPARATIVO'!$V$5:$V$206,"<>REJEITADO") -> 0 | G31: =SUM(C31:F31) -> 1 | H31: =SUMIFS('MAPA COMPARATIVO'!$O$5:$O$206,'MAPA COMPARATIVO'!$F$5:$F$206,$A31,'MAPA COMPARATIVO'!$V$5:$V$206,"<>REJEITADO") -> -457.84 | I31: =SUMIFS('MAPA COMPARATIVO'!$P$5:$P$206,'MAPA COMPARATIVO'!$F$5:$F$206,$A31,'MAPA COMPARATIVO'!$V$5:$V$206,"<>REJEITADO") -> -4821.36
A32: VERIFICAR | C32: =COUNTIFS('MAPA COMPARATIVO'!$F$5:$F$206,$A32,'MAPA COMPARATIVO'!$G$5:$G$206,"CRÍTICA",'MAPA COMPARATIVO'!$V$5:$V$206,"<>REJEITADO") -> 0 | D32: =COUNTIFS('MAPA COMPARATIVO'!$F$5:$F$206,$A32,'MAPA COMPARATIVO'!$G$5:$G$206,"ALTA",'MAPA COMPARATIVO'!$V$5:$V$206,"<>REJEITADO") -> 1 | E32: =COUNTIFS('MAPA COMPARATIVO'!$F$5:$F$206,$A32,'MAPA COMPARATIVO'!$G$5:$G$206,"MÉDIA",'MAPA COMPARATIVO'!$V$5:$V$206,"<>REJEITADO") -> 14 | F32: =COUNTIFS('MAPA COMPARATIVO'!$F$5:$F$206,$A32,'MAPA COMPARATIVO'!$G$5:$G$206,"BAIXA",'MAPA COMPARATIVO'!$V$5:$V$206,"<>REJEITADO") -> 17 | G32: =SUM(C32:F32) -> 32 | H32: =SUMIFS('MAPA COMPARATIVO'!$O$5:$O$206,'MAPA COMPARATIVO'!$F$5:$F$206,$A32,'MAPA COMPARATIVO'!$V$5:$V$206,"<>REJEITADO") -> 0 | I32: =SUMIFS('MAPA COMPARATIVO'!$P$5:$P$206,'MAPA COMPARATIVO'!$F$5:$F$206,$A32,'MAPA COMPARATIVO'!$V$5:$V$206,"<>REJEITADO") -> -4003.05
A33: TOTAL | C33: =SUM(C22:C32) -> 1 | D33: =SUM(D22:D32) -> 34 | E33: =SUM(E22:E32) -> 82 | F33: =SUM(F22:F32) -> 85 | G33: =SUM(G22:G32) -> 202 | H33: =SUM(H22:H32) -> 115594.89 | I33: =SUM(I22:I32) -> 399725.14

Sheet LEGENDA
A1: LEGENDA E NOTAS
A3: Objetivo | B3: Comparar, artigo a artigo, O QUE ESTÁ NO MQT com O QUE DEVERIA ESTAR, classificando falhas, erros e outros problemas, com impacto estimado em €.
A4: Origem dos dados | B4: MQT_CUSTO-VENDA.XLS (folha única). Qtd/Un/PU/Total copiados do original (texto azul).
A5: Método | B5: 1) Leitura integral e verificação aritmética por script; 2) revisão + varrimento por 5 grupos de capítulos; 3) verificação adversarial independente de cada achado (coluna Verificação: MANTIDO / CORRIGIDO / REJEITADO).
A6: Tipos | B6: ERRO (cálculo, unidade, numeração, texto) · FALHA/OMISSÃO (trabalho em falta) · DUPLICAÇÃO (pago 2×) · PREÇO BAIXO/ALTO (vs mercado) · INCOERÊNCIA (mesmo trabalho com preços/quantidades diferentes) · DESCRIÇÃO (texto incompatível/omisso) · NORMA (norma/lei errada ou em falta) · INCOMPATIBILIDADE (técnica) · EXTRA/FORA DE ÂMBITO · VERIFICAR (precisa de desenhos).
A7: Gravidade | B7: CRÍTICA = invalida o MQT ou > ~10 k€ / risco legal · ALTA = erro relevante de custo/técnico · MÉDIA = corrigir antes da adjudicação · BAIXA = forma/texto.
A8: Impacto (€) | B8: Cenário A = a menor variação plausível de cada achado; cenário B = a maior (mesmo sinal). Ordem de grandeza, sem IVA, Portugal 2025-2026. Negativo = retirar ao custo (duplicações, sobrepreços); positivo = acrescentar (omissões, subavaliações). Não substitui consultas ao mercado.
A9: Cores | B9: Azul = dado copiado do MQT ou estimativa introduzida · Verde = ligação a outra folha · Preto = fórmula · Amarelo = preencher/alterar pelo revisor.
A10: O que editar | B10: MAPA COMPARATIVO: colunas 'Estado de resolução' (lista) e 'Observações do revisor'. CUSTO vs VENDA: célula C3 (K). Todos os totais, a matriz e o painel recalculam.
A11: Limitações | B11: Sem peças desenhadas, caderno de encargos nem memória descritiva: medições não confirmadas contra o projeto; achados 'VERIFICAR' dependem dessa conferência.
A12: Fontes de referência | B12: LNEC – Número mínimo de ensaios em ancoragens (repositorio.lnec.pt); EN 1537 / EN ISO 22477-5; DL 266/2007 e Portaria 40/2014 (amianto); DL 163/2006 (acessibilidades); RT-SCIE; CCP arts. 50.º, 70.º–71.º e 378.º; Habitissimo (remoção de fibrocimento); Obramat (preço de material GL24h).
A14: Exemplo de preenchimento | B14: Estado de resolução = 'Corrigido no MQT'; Observações do revisor = 'Projetista confirmou duplicação; 2.2.2 eliminado na rev. B (15/10/2026)'.

Sheet MAPA COMPARATIVO
A1: MAPA COMPARATIVO DE FALHAS, ERROS E OUTROS – MQT CUSTO/VENDA
A2: Cada linha compara O QUE ESTÁ NO MQT com O QUE DEVERIA ESTAR. Valores em € sem IVA. Impacto: negativo reduz o custo, positivo aumenta. Colunas a amarelo = preencher pelo revisor.
A4: Nº | B4: Cap. | C4: Artigo | D4: Artigos relacionados | E4: Designação no MQT | F4: Tipo | G4: Gravidade | H4: Problema | I4: O QUE ESTÁ NO MQT | J4: Qtd MQT | K4: Un | L4: PU MQT (€) | M4: Total MQT (€) | N4: O QUE DEVERIA ESTAR (referência) | O4: Impacto A – mín (€) | P4: Impacto B – máx (€) | Q4: Impacto médio (€) | R4: Fundamentação | S4: Ação corretiva | T4: Responsável | U4: Origem | V4: Verificação | W4: Nota de verificação | X4: Estado de resolução | Y4: Observações do revisor
A5: 1 | B5: GERAL | C5: GERAL | D5: Colunas G/H (todos os artigos) | E5: Estrutura CUSTO/VENDA | F5: ERRO | G5: CRÍTICA | H5: VENDA = CUSTO: sem margem; venda 12,12 € abaixo do custo | I5: PU de venda igual ao PU de custo nos 833 artigos. Total custo 4.499.642,08 €; total venda 4.499.629,96 €; K implícito = 0,999997. | N5: Preço de venda = custo × K (estrutura + risco + lucro; tipicamente 1,15–1,25, definido pela empresa) ou composição de preço por artigo. | O5: 0 | P5: 0 | Q5: =AVERAGE(O5:P5) -> 0 | R5: Comparação direta das colunas E/G e F/H do ficheiro (script). Efeito de K calculado na folha CUSTO vs VENDA. | S5: Definir K por capítulo e recalcular a VENDA com fórmulas. | T5: Orçamentista | U5: EXISTENTE | V5: MANTIDO | W5: Verificado por script sobre o ficheiro original. | X5: Pendente
A6: 2 | B6: GERAL | C6: GERAL | D6: Todo o ficheiro | E6: Construção do ficheiro | F6: ERRO | G6: ALTA | H6: Ficheiro sem fórmulas: totais colados como valores | I6: 0 fórmulas em toda a folha; somas de capítulos e totais são números fixos. | N6: Totais = Qtd × PU e SUBTOTAL por capítulo, por fórmula. | O6: 0 | P6: 0 | Q6: =AVERAGE(O6:P6) -> 0 | R6: Conversão para .xlsx e contagem de fórmulas (openpyxl): 0. | S6: Refazer o MQT com fórmulas. | T6: Orçamentista | U6: EXISTENTE | V6: MANTIDO | W6: Verificado por script. | X6: Pendente
A7: 3 | B7: GERAL | C7: GERAL | D7: Fim do MQT | E7: Quadro-resumo | F7: FALHA/OMISSÃO | G7: ALTA | H7: Sem total geral, resumo por capítulos nem linha de IVA | I7: O MQT termina na nota 08; não há total geral nem indicação de IVA. | N7: Quadro-resumo por capítulo, total geral, 'IVA não incluído' e taxa aplicável. | O7: 0 | P7: 0 | Q7: =AVERAGE(O7:P7) -> 0 | R7: Leitura integral do ficheiro. | S7: Acrescentar quadro-resumo. | T7: Orçamentista | U7: EXISTENTE | V7: MANTIDO | W7: Verificado por leitura. | X7: Pendente
A8: 4 | B8: 2 | C8: 2.2.1 | D8: 2.2.2; 2.3.1; 2.3.3 | E8: MICROESTACAS | F8: VERIFICAR | G8: ALTA | H8: Microestacas 'para fundação' na contenção: possível duplicação com 2.3.1 | I8: 2.2.1 (subcapítulo 2.2 CONTENÇÃO PERIFÉRICA): 'Execução de microestaca para fundação, com um comprimento médio de 8,50 m...', 599,85 ml × 90,03 € = 54.005,32 €, seguida de 2.2.2 MACIÇO DE ENCABEÇAMENTO de estacas 63,00 m3. Em 2.3 OBRA DE BETÃO repete-se o mesmo par: 2.3.1 'microestaca para fundação' (L média 12,15 m; 525,22 + 555,11 = 1.080,33 ml) + 2.3.3 maciços 63,11 m3. | J8: 599.85 | K8: ml | L8: 90.03 | M8: 54005.32 | N8: Uma contenção tipo Berlim tem os seus próprios elementos verticais (perfis selados 2.2.3–2.2.5, 899,98 ml) e viga de coroamento (2.2.7). Microestacas 'para fundação' com maciços de encabeçamento são fundações (2.3). Cada microestaca deve aparecer uma só vez, com a função indicada. | O8: 0 | P8: -54005.32 | Q8: =AVERAGE(O8:P8) -> -27002.66 | R8: O par 'microestaca para fundação + maciço de encabeçamento' aparece duas vezes, com comprimentos médios diferentes (8,50 m e 12,15 m) e cerca de 71 un e 89 un, mas com volumes de maciços quase iguais (63,00 e 63,11 m3). Isto aponta para uma versão anterior das fundações que ficou no subcapítulo 2.2. Se for o caso, 2.2.1 está a mais (−54.005,32 €). Se forem microestacas reais de outro elemento, a descrição tem de dizer qual. | S8: Confirmar nas peças desenhadas a que elementos correspondem as cerca de 71 microestacas de 2.2.1 e depois eliminar o artigo ou corrigir a descrição e o subcapítulo. | T8: Projetista | U8: NOVO | V8: MANTIDO | W8: Confirmado no dump (linhas Excel 37, 39, 87–91, 95): 2.2.1 599,85 ml × 90,03 = 54.005,32 € (CUSTO), texto 'microestaca para fundação' L 8,50 m; 2.3.1 L 12,15 m com 525,22 + 555,11 = 1.080,33 ml; 599,85/8,5 = 70,6 un e 1.080,33/12,15 = 88,9 un. A palavra 'microestaca' só existe em 2.2.1 e 2.3.1 em todo o MQT. Os volumes de maciços quase iguais (63,00/63,11 m3) reforçam a hipótese de versão duplicada. O impacto vai de 0 a −54.005,32 €, porque o achado é de verificação. Mantido apesar de ser NOVO, porque a incoerência textual é objetiva. | X8: Pendente
A9: 5 | B9: 2 | C9: 2.2.1 | D9: 2.3.1.1 | E9: MICROESTACAS | F9: INCOERÊNCIA | G9: ALTA | H9: Microestaca 101,6×6,5 a 90,03 €/ml e a 134,17 €/ml (+49%) | I9: 2.2.1: 599,85 ml × 90,03 € = 54.005,32 € (N80 101,6×6,5 mm, Ø200, IRS, L média 8,50 m). 2.3.1.1 '101.6x6.5': 525,22 ml × 134,17 € = 70.469,71 € (mesma especificação, L média 12,15 m). | J9: 599.85 | K9: ml | L9: 90.03 | M9: 54005.32 | N9: Um só PU para a mesma microestaca: 90–105 €/ml (o PU de 2.2.1 já é um valor de mercado). | O9: -15320.67 | P9: -23183.21 | Q9: =AVERAGE(O9:P9) -> -19251.94 | R9: Diferença de 44,14 €/ml (+49,0%). Alinhando 2.3.1.1 a 90,03 €/ml: (90,03−134,17)×525,22 = −23.183,21 €. A 105 €/ml: −15.320,67 €. A falta de ensaios de carga está tratada em 2.3.1 (OMISSÃO). | S9: Uniformizar o PU das microestacas 101,6×6,5 (2.2.1 e 2.3.1.1). | T9: Orçamentista | U9: EXISTENTE | V9: MANTIDO | W9: Conferido: 2.2.1 599,85 × 90,03, total 54.005,32; 2.3.1.1 525,22 × 134,17, total 70.469,71. 134,17/90,03 = 1,490. Impactos recomputados (−23.183,21 € e −15.320,67 €). Não há dupla contagem com o achado de duplicação de 2.2.1, porque este ajusta o PU de 2.3.1.1 e não o de 2.2.1. | X9: Pendente
A10: 6 | B10: 2 | C10: 2.2.2 | D10: 2.3.3; 2.2.1 | E10: MACIÇOS DE FUNDAÇÃO | F10: DUPLICAÇÃO | G10: ALTA | H10: Maciços de encabeçamento repetidos em 2.2.2 e 2.3.3 (63,00/63,11 m3) | I10: 2.2.2: 63,00 m3 × 317,40 € = 19.996,33 € (C30/37, XC2, Cl0.40, S3, Dinf 2mm, Dsup 20mm, hidrófugo). 2.3.3: 63,11 m3 × 318,79 € = 20.119,03 €, com texto igual palavra a palavra exceto 'S4'. | J10: 63 | K10: m3 | L10: 317.4 | M10: 19996.33 | N10: Um único artigo de maciços de encabeçamento com a quantidade do projeto (cerca de 63 m3), a não ser que os desenhos mostrem dois conjuntos distintos de maciços. | O10: 0 | P10: -19996.33 | Q10: =AVERAGE(O10:P10) -> -9998.165 | R10: Os volumes diferem 0,17% e as descrições são iguais exceto na consistência (S3/S4). Como há dois conjuntos de microestacas (2.2.1 e 2.3.1), dois conjuntos de maciços podem justificar-se. A duplicação é provável mas não está provada. Se se confirmar, o artigo a eliminar vale 19.996,33 €. | S10: Confirmar nos desenhos de estabilidade. Se for duplicação, eliminar 2.2.2. Se não for, explicar na descrição a que microestacas se refere cada artigo. | T10: Projetista | U10: EXISTENTE | V10: MANTIDO | W10: Valores conferidos em rows.json: 2.2.2 q=63,00, PU 317,40, total CUSTO 19.996,33 (VENDA 19.996,20); 2.3.3 q=63,11, PU 318,79, total 20.119,03. Comparação dos textos: iguais exceto S3/S4. 0,11/63 = 0,17%. Impacto e gravidade coerentes. | X10: Pendente
A11: 7 | B11: 2 | C11: 2.2.5 | D11: 2.3.1.2 | E11: PERFIS SELADOS TUBULARES | F11: INCOERÊNCIA | G11: ALTA | H11: Microestaca 88,9×6,5 a 74,57 €/ml e a 126,31 €/ml (+69%) | I11: 2.2.5: 275,28 ml × 74,57 € = 20.528,28 € (tubo N80 88,9×6,5 mm, Ø200, IRS, L 9–10 m). 2.3.1.2 '88.9x6.5': 555,11 ml × 126,31 € = 70.116,04 € (mesma especificação, L média 12,15 m). | J11: 275.28 | K11: ml | L11: 74.57 | M11: 20528.28 | N11: Um só PU para a mesma microestaca 88,9×6,5 N80 IRS: 75–90 €/ml. Um comprimento maior não encarece o metro. | O11: -20156.04 | P11: -28721.39 | Q11: =AVERAGE(O11:P11) -> -24438.715 | R11: Diferença de 51,74 €/ml (+69,4%). Alinhando 2.3.1.2 a 74,57 €/ml: (74,57−126,31)×555,11 = −28.721,39 €. A 90 €/ml: (90−126,31)×555,11 = −20.156,04 €. | S11: Uniformizar o PU (2.2.5 e 2.3.1.2) ou justificar a diferença por escrito. | T11: Orçamentista | U11: EXISTENTE | V11: MANTIDO | W11: Conferido: 2.2.5 q=275,28, PU 74,57, total 20.528,28; 2.3.1.2 q=555,11, PU 126,31, total 70.116,04. 126,31/74,57 = 1,694 (+69,4%). Cálculos recomputados: −28.721,39 € e −20.156,04 €. Os textos têm a mesma especificação (N80, Ø200, leitada CEM I 42,5N a/c 0,4, IRS). As microestacas de fundação podem ter custos de acesso um pouco maiores, mas não justificam +69%. | X11: Pendente
A12: 8 | B12: 2 | C12: 2.2.12 | D12: 2.2.12.1; 2.2.12.2; 2.2.12.3 | E12: ANCORAGENS | F12: NORMA | G12: ALTA | H12: Só 2 ancoragens ensaiadas em 13; falta destensionamento | I12: 2.2.12.1: 5 UN × 1.533,59 € (400 kN, Llivre 5,50 + Lbolbo 9,00). 2.2.12.2: 4 UN × 1.586,48 € (400 kN, 5,00 + 10,00). 2.2.12.3: 4 UN × 1.374,95 € (200 kN, 6,00 + 7,00). Total 19.513,67 €, 13 ancoragens, todas a 105,77 €/ml. Texto: 'ancoragens provisórias, com / capacidade de carga,' (valor em branco) e 'ensaio de 2 ancoragens'. | N12: NP EN 1537, EN ISO 22477-5 e NP EN 1997-1 (8.8) exigem ensaio de receção em TODAS as 13 ancoragens, mais ensaios de investigação/aptidão. É preciso também destensionar e desativar as provisórias no fim, e ter autorização dos confinantes se os bolbos entrarem em terreno alheio. | O12: 3500 | P12: 7050 | Q12: =AVERAGE(O12:P12) -> 5275 | R12: 11 ensaios de receção adicionais × 150–250 € + 2–3 ensaios de aptidão × 600–1.000 € + destensionamento de 13 un × 50–100 € = 3.500–7.050 €. O PU por metro é igual (105,77 €/ml) para 200 kN e 400 kN, sinal de preço paramétrico. | S12: Exigir ensaio de receção em todas as ancoragens e ensaios de aptidão, acrescentar o destensionamento e completar a capacidade de carga em falta no texto. | T12: Projetista | U12: EXISTENTE | V12: MANTIDO | W12: Conferido: totais 7.667,97 + 6.345,91 + 5.499,79 = 19.513,67 €. PU/ml: 1.533,59/14,5 = 105,765; 1.586,48/15 = 105,765; 1.374,95/13 = 105,765, todos iguais. Texto 'com / capacidade de carga' (em branco) e 'ensaio de 2 ancoragens' confirmados. Impacto recomputado: 11×150 + 2×600 + 13×50 = 3.500; 11×250 + 3×1.000 + 13×100 = 7.050. | X12: Pendente
A13: 9 | B13: 2 | C13: 2.2.13 | D13: 2.2.12 | E13: SISTEMA DE MONITORIZAÇÃO | F13: PREÇO BAIXO | G13: ALTA | H13: Monitorização de contenção ancorada e vistorias por 3.500 € | I13: 1 UN × 3.500,00 € = 3.500,00 €. Inclui 'plano de instrumentação e monitorização', 'vistorias aos edifícios envolventes', 'fornecimento, aplicação e manutenção dos equipamentos' e 'leitura de medições durante o decurso da Empreitada'. | J13: 1 | K13: UN | L13: 3500 | M13: 3500 | N13: 10.000–20.000 € para uma contenção ancorada com 13 ancoragens: vistorias prévias com relatório, alvos topográficos e outros instrumentos previstos, leituras periódicas e relatórios durante a escavação. | O13: 6500 | P13: 16500 | Q13: =AVERAGE(O13:P13) -> 11500 | R13: (10.000−3.500) = 6.500 € e (20.000−3.500) = 16.500 €. Só as vistorias com relatório aos edifícios confinantes absorvem a maior parte dos 3.500 €. | S13: Rever o PU para 10–20 k€, de acordo com o plano de instrumentação do projeto. | T13: Orçamentista | U13: EXISTENTE | V13: MANTIDO | W13: Texto e valor (1 UN × 3.500) confirmados. As únicas ocorrências de 'monitoriza' no MQT são 2.2.13 e 7.5.2 (especialidade), e 'vistoria' só aparece em 2.2.13, por isso não há outro artigo que pague isto. A referência é plausível para a obra (13 ancoragens, cerca de 900 ml de perfis) e os cálculos estão corretos. | X13: Pendente
A14: 10 | B14: 2 | C14: 2.3.1 (OMISSÃO) | D14: 2.2.1; 2.2.5; 2.3.1; 2.2.12; 2.1.4 | E14: Ensaios de carga e controlo de qualidade | F14: FALHA/OMISSÃO | G14: ALTA | H14: Sem ensaios de carga de microestacas nem controlo de betão, aço ou aterros | I14: Nenhum artigo de ensaios de carga para 1.955,46 ml de microestacas (2.2.1: 599,85; 2.2.5: 275,28; 2.3.1: 1.080,33), nem de controlo de receção de cerca de 1.383 m3 de betão (2.2–2.3), do aço ou da compactação. Nos caps. 1–2 só 2.1.4 (Proctor) e 2.2.12 ('ensaio de 2 ancoragens') falam em ensaios. | N14: NP EN 14199 e NP EN 1997-1 (7.5): ensaios de carga estáticos de microestacas (pelo menos 2 un) e/ou ensaios de integridade. DL 90/2021 com NP EN 13670/NP EN 206: controlo de receção do betão (ensaios de identidade) e do aço. Ensaios de placa ou de densidade nos aterros. | O14: 8000 | P14: 18000 | Q14: =AVERAGE(O14:P14) -> 13000 | R14: 2 ensaios estáticos × 3.000–6.000 € = 6.000–12.000 €, mais 2.000–6.000 € de controlo de betão, aço e compactação = 8.000–18.000 €. | S14: Criar artigos de ensaios de carga de microestacas e de plano de controlo de qualidade (betão, aço, aterros). | T14: Projetista | U14: EXISTENTE | V14: MANTIDO | W14: Pesquisa de 'ensaio' em todas as 833 linhas: 2.1.4, 2.2.12 e depois apenas especialidades (4.5.7, 5.4.5, 6.3.4, 7.9.9, 7.12, 10.5.2, 11.15, 12.2), todas de redes, instalações ou condutas. Não há ensaios de estacas, betão ou aço. Somas conferidas: 599,85 + 275,28 + 525,22 + 555,11 = 1.955,46 ml; m3 de betão em 2.2–2.3 = 1.383,34. | X14: Pendente
A15: 11 | B15: 2 | C15: 2.3.1 | D15: 2.3.1 (OMISSÃO); 2.2.1; 2.2.5 | E15: MICROESTACAS | F15: FALHA/OMISSÃO | G15: ALTA | H15: Microestacas de fundação sem ensaios de carga | I15: 2.3.1.1: 525,22 ml × 134,17 € = 70.469,71 €. 2.3.1.2: 555,11 ml × 126,31 € = 70.116,04 €. O texto não inclui ensaios e nenhum outro artigo os prevê. | N15: Ensaios de carga estáticos (pelo menos 1–2 un) e/ou ensaios de integridade segundo a NP EN 14199 e a NP EN 1997-1 (7.5), de acordo com o caderno de encargos. | O15: 0 | P15: 0 | Q15: =AVERAGE(O15:P15) -> 0 | R15: Nos caps. 1–2 só 2.1.4 e 2.2.12 falam em ensaios. O impacto está quantificado em '2.3.1 (OMISSÃO)', para não contar duas vezes. | S15: Ver 2.3.1 (OMISSÃO). | T15: Projetista | U15: EXISTENTE | V15: MANTIDO | W15: Valores confirmados. A pesquisa de 'ensaio' no MQT inteiro não encontra ensaios de estacas. O impacto nulo evita a dupla contagem com '2.3.1 (OMISSÃO)'. | X15: Pendente
A16: 12 | B16: 2 | C16: 2.3.3 | D16: 2.2.2 | E16: MACIÇOS DE FUNDAÇÃO | F16: DUPLICAÇÃO | G16: ALTA | H16: Par de 2.2.2 (63,11 vs 63,00 m3), com S4 em vez de S3 | I16: 2.3.3: 63,11 m3 × 318,79 € = 20.119,03 € (C30/37, XC2, Cl0.40, S4). 2.2.2: 63,00 m3 × 317,40 € (S3), com texto igual. | J16: 63.11 | K16: m3 | L16: 318.79 | M16: 20119.03 | N16: Um só artigo. Se os dois forem reais, uniformizar a consistência (S3/S4) e o PU. | O16: 0 | P16: 0 | Q16: =AVERAGE(O16:P16) -> 0 | R16: É o mesmo par de 2.2.2. O impacto (até −19.996,33 €) está em 2.2.2, para não contar duas vezes. | S16: Ver 2.2.2. | T16: Projetista | U16: EXISTENTE | V16: MANTIDO | W16: Valores confirmados (linha Excel 95). O impacto nulo evita a dupla contagem com 2.2.2. | X16: Pendente
A17: 13 | B17: 2 | C17: 2.3.11 | D17: 2.3.9; 2.3.10; 2.3.12 | E17: VIGAS | F17: DESCRIÇÃO | G17: ALTA | H17: Vigas sem especificação do betão | I17: 101,63 m3 × 566,23 € = 57.546,06 €. Texto: '...compactação e cura de betão; transporte, montagem...', sem classe de resistência, exposição, cloretos, consistência nem Dsup. | J17: 101.63 | K17: m3 | L17: 566.23 | M17: 57546.06 | N17: Especificação completa segundo a NP EN 206, como nos artigos vizinhos (2.3.9/2.3.10: C30/37, XC1, Cl 0,40, S3, Dmáx 20 mm), de acordo com o projeto. | O17: 0 | P17: 0 | Q17: =AVERAGE(O17:P17) -> 0 | R17: Todos os outros artigos de betão do subcapítulo 2.3 têm especificação. Este é o único sem nenhuma. | S17: Completar a especificação do betão das vigas. | T17: Projetista | U17: EXISTENTE | V17: MANTIDO | W17: Linha Excel 112: texto sem classe de betão, confirmado. q=101,63, PU 566,23, total CUSTO 57.546,06. 2.3.9 e 2.3.10 com C30/37, XC1, Cl 0.40, S3, Dmáx 20 mm, confirmado. | X17: Pendente
A18: 14 | B18: 2 | C18: 2.5.1 | D18: 2.5.1.1 a 2.5.1.9 | E18: COBERTURA MADEIRA | F18: NORMA | G18: ALTA | H18: Classe de madeira ME-1 + GL24h contraditória, sem tratamento nem fogo; PU elevado | I18: 9 subartigos com 133,50 m3 de madeira, num total de 308.931,74 € (média de 2.314 €/m3; 2.304–2.361 €/m3 em todos exceto 2.5.1.8). Texto: 'COBERTURA EM MADEIRA em Pinho Silvestre da classe ME-1; GL24-h incluindo ligação entre vigas, ripas e barrotes'. Não indica classe de uso, tratamento preservador nem resistência ao fogo. | N18: Uma só especificação: madeira lamelada colada GL24h (EN 14080) ou madeira maciça C24/C27 (EN 338). A ME-1 é uma classe visual de madeira serrada de resinosas (UNE 56544). Falta a classe de uso (EN 335) com o respetivo tratamento e a resistência ao fogo (EN 1995-1-2). Referência de GL24h montado, com ligações e ripado incluídos: cerca de 1.760–2.200 €/m3. | O18: 0 | P18: -73963.92 | Q18: =AVERAGE(O18:P18) -> -36981.96 | R18: Madeira maciça classificada visualmente (ME-1) e lamelado colado (GL24h) são produtos diferentes. No retalho espanhol (Obramat) o GL24h custa cerca de 610–1.260 €/m3 com IVA (cerca de 500–1.040 €/m3 sem IVA). Somando fabrico, ligações, tratamento, transporte, grua e montagem (cerca de 700–900 €/m3) e uns 10% de ripas e barrotes incluídos no PU, a referência fica em 1.760–2.200 €/m3: (2.200−2.314)×133,50 = −15.221,96 € e (1.760−2.314)×133,50 = −73.963,92 €. Como o PU também paga ripas e barrotes (volume não medido) e falta prever tratamento e proteção ao fogo, que acrescentam custo, o PU atual pode estar correto. Por isso o cenário mínimo é 0. | S18: Corrigir a especificação (GL24h, EN 14080), acrescentar a classe de uso, o tratamento e a resistência ao fogo, e validar o PU com 2–3 propostas de fabricantes de lamelado. | T18: Projetista | U18: EXISTENTE | V18: CORRIGIDO | W18: Volume recalculado secção × comprimento: 133,504 m3. Soma 308.931,74 € e média 2.314,02 €/m3 confirmadas. €/m3 por linha: 2.304–2.361, e 1.743 em 2.5.1.8. Texto ME-1 + GL24-h confirmado. O problema normativo é real. A redução de preço não é demonstrável, porque o PU inclui ripas, barrotes e ligações não medidos em m3 e o tratamento e a proteção ao fogo em falta aumentariam o custo. impacto_min corrigido de −15.221,96 para 0; o máximo (−73.963,92 €) foi mantido. | X18: Pendente
A19: 15 | B19: 3 | C19: 3.1.1 | D19: 3.1.3; 3.1.4; 3.1.5; 3.1.7; 1.6 | E19: DEMOLIÇÃO DE PAVILHÃO EXISTENTE | F19: FALHA/OMISSÃO | G19: ALTA | H19: Demolição sem fundações, laje térrea nem transporte/destino final dos RCD | I19: 3.1.1 | m3 | Qtd 9 000 | PU 4,55 € | Total 40 950,00 €. Texto: «Demolição completa, elemento a elemento ... de edifício de cerca de 1200 m² ... e carga mecânica para camião ou contentor». Não refere fundações, laje térrea, transporte nem destino final. | J19: 9000 | K19: m3 | L19: 4.55 | M19: 40950 | N19: Demolição completa, incluindo fundações e pavimento térreo, e transporte e deposição dos RCD em operador licenciado com e-GAR (DL 102-D/2020). É a formulação dos art. 3.1.3, 3.1.4, 3.1.5 e 3.1.7 («transporte e descarga em vazadouro conforme o especificado no PGR»). O PU de 40 950 € / 1 200 m² ≈ 34 €/m² só é plausível para a demolição propriamente dita. | O19: 0 | P19: 30000 | Q19: =AVERAGE(O19:P19) -> 15000 | R19: Os restantes artigos de demolição do capítulo incluem expressamente transporte e vazadouro, mas o 3.1.1 termina na carga. RCD estimados: 1 200 m² × 1,0–1,5 t/m² = 1 200–1 800 t. A 8–15 €/t de transporte e deposição dá ≈10–27 k€. Fundações e laje térrea: ≈260 m³ × 25–40 €/m³ ≈ 6,5–10 k€. Mínimo de 0 € se o art. 1.6 (PGR, 25 000 €) cobrir o transporte e a deposição e se 'demolição completa' abranger as fundações. | S19: Completar a descrição do 3.1.1 com a demolição de fundações e laje térrea e com o transporte e deposição em operador licenciado, ou criar subartigos próprios, e clarificar a fronteira com o art. 1.6. | T19: Projetista | U19: EXISTENTE | V19: MANTIDO | W19: Confirmado em rows.json: m3, 9 000 × 4,55 = 40 950,00 €. O texto termina em «carga mecânica para camião ou contentor», enquanto 3.1.3, 3.1.4, 3.1.5 e 3.1.7 dizem «transporte e descarga em vazadouro» e o 3.1.7 refere fundações. O art. 1.6 é genérico («Implementação do PGR ... todos os trabalhos necessários»), pelo que o mínimo de 0 € está corretamente previsto. A ordem de grandeza do máximo é razoável. | X19: Pendente
A20: 16 | B20: 3 | C20: 3.1.2 | D20: 1.6; 3.1.1 | E20: DEMOLIÇÃO DE COBERTURA COM AMIANTO EM PAV. EXISTENTE | F20: FALHA/OMISSÃO | G20: ALTA | H20: Amianto sem transporte nem deposição licenciada | I20: 3.1.2 | m2 | Qtd 1 000 | PU 14,00 € | Total 14 000,00 €. Texto: «... por empresa qualificada ... superfície média a desmontar de cerca de 1000 m² ... e carga mecânica sobre camião. O preço inclui ... as medições da concentração de amianto (ambientais e pessoais)». | J20: 1000 | K20: m2 | L20: 14 | M20: 14000 | N20: Preço global de 20–30 €/m² (remoção, encapsulamento e embalagem, transporte com e-GAR e deposição em aterro licenciado para RCD com amianto), conforme a Portaria 40/2014 e a Portaria 145/2017 (e-GAR). Plano de trabalhos comunicado à ACT nos termos do DL 266/2007 (obrigação legal do executante). Área a confirmar com levantamento prévio de MCA, num edifício de ≈1 200 m². | O20: 0 | P20: 22000 | Q20: =AVERAGE(O20:P20) -> 11000 | R20: A descrição termina na carga sobre camião, sem transporte nem deposição. O PU de 14 €/m² é plausível só para a remoção (referência indicativa de ≈10 €/m² sem transporte e ≈20 €/m² com transporte a destino certificado). Diferença de preço: (20−14)×1 000 = 6 000 € a (30−14)×1 000 = 16 000 €. A eventual diferença de área (até +200 m² × 30 €) acrescenta até 6 000 €. Mínimo de 0 € se o art. 1.6 (PGR, 25 000 €) cobrir o transporte e a deposição, critério igual ao do achado 3.1.1. | S20: Reformular o 3.1.2 para incluir o embalamento, o transporte com e-GAR e a deposição em destino licenciado (ou remeter expressamente para o 1.6). Confirmar a área com levantamento de MCA e rever o PU para 20–30 €/m², se o transporte e a deposição ficarem neste artigo. | T20: Projetista | U20: EXISTENTE | V20: CORRIGIDO | W20: Números confirmados (1 000 × 14,00 = 14 000,00 €). Problema real (o texto acaba na carga), mas: (i) o mínimo passa a 0 €, porque o art. 1.6 (PGR) pode cobrir o transporte e a deposição, como se admitiu no 3.1.1; (ii) o plano de trabalhos ACT é obrigação legal do executante e não constitui omissão de custo, pelo que sai do título; (iii) a gravidade passa de CRÍTICA para ALTA, porque o artigo já prevê empresa qualificada e medições de amianto e a exposição é de 6–22 k€. A referência Habitissimo não é verificável nos dados e fica apenas como indicativa. | X20: Pendente
A21: 17 | B21: 3 | C21: 3.1.4 | D21: 3.1.4.1; 3.1.4.2; 3.1.4.3 | E21: DEMOLIÇÃO DE MUROS E MURETES | F21: PREÇO BAIXO | G21: ALTA | H21: 6,5 €/m3 para demolição manual de muros com vazadouro | I21: 3.1.4.1 | m3 | 74 | 6,50 € | 481,00 €; 3.1.4.2 | m3 | 10 | 6,50 € | 65,00 €; 3.1.4.3 | m3 | 40 | 6,50 € | 260,00 €. Total de 124 m³ = 806,00 €. Texto: «com meios manuais, e carga manual ... transporte e descarga em vazadouro». | N21: 45–80 €/m³ para demolição de alvenaria, betão armado ou granito com meios manuais ou martelo, com carga, transporte e vazadouro (mercado PT 2025-2026). | O21: 4774 | P21: 9114 | Q21: =AVERAGE(O21:P21) -> 6944 | R21: (45−6,5)×124 = 4 774 €; (80−6,5)×124 = 9 114 €. O PU de 6,5 €/m³ fica abaixo do da simples escavação com transporte do próprio MQT (art. 2.1.1 + 2.1.5 = 11 €/m³) e não cobre a demolição de betão armado e granito com meios manuais. | S21: Rever o PU dos três subartigos para 45–80 €/m³, diferenciando o betão armado e granito da alvenaria de bloco. | T21: Orçamentista | U21: EXISTENTE | V21: MANTIDO | W21: Quantidades 74/10/40 m³ a 6,50 € e totais 481/65/260 € confirmados (soma de 806 €). 2.1.1 e 2.1.5 estão ambos a 5,50 €/m³. Cálculo de impacto correto. Intervalo de referência plausível para demolição manual de muros com vazadouro. | X21: Pendente
A22: 18 | B22: 3 | C22: 3.3 (OMISSÃO) | D22: 3.13.6; 11.11 | E22: Linha de vida / sistema anti-queda na cobertura (omisso) | F22: FALHA/OMISSÃO | G22: ALTA | H22: Cobertura com acesso de manutenção sem linha de vida | I22: Nenhum artigo de linha de vida ou ancoragem (pesquisa sem resultados). Há ≈1 851 m² de cobertura em painel sandwich (3.3.1 e 3.3.2), 8 exutores em cobertura (11.11) e 3 escadas de acesso «de modo a aceder e manter todas as coberturas» (3.13.6). | N22: Sistema anti-queda permanente EN 795 (tipo C, cabo, e tipo A, pontos), certificado, para manutenção de coberturas leves não transitáveis, previsto na compilação técnica (DL 273/2003). | O22: 8000 | P22: 18000 | Q22: =AVERAGE(O22:P22) -> 13000 | R22: ≈140–200 ml de linha × 60–90 €/ml, mais pontos de ancoragem e certificação, dá ≈8–18 k€. O MQT prevê o acesso (3.13.6) e equipamentos a manter (exutores), mas não a proteção. | S22: Acrescentar um artigo de linha de vida com o traçado e a certificação. | T22: Projetista | U22: EXISTENTE | V22: MANTIDO | W22: Pesquisa sem resultados para 'linha de vida' e 'anti-queda'. 'ancoragem' só aparece no 2.2.12 (contenção) e no 13.6.4 (manta). 1 230 + 454 + 128 + 39 = 1 851 m². Confirmado o texto do 3.13.6 (3 UN, «aceder e manter todas as coberturas»). | X22: Pendente
A23: 19 | B23: 3 | C23: 3.9.2.3 | D23: 3.9.2.3.1; 3.9.2.3.2; 3.11.2.2 a 3.11.2.15 | E23: SOLEIRAS EXT. (betão polimérico tipo Tubani) | F23: DUPLICAÇÃO | G23: ALTA | H23: Soleiras exteriores pagas em 3.9.2.3 e nos artigos dos vãos | I23: 3.9.2.3.1 400 mm | ml | 112 | 85,00 € | 9 520,00 €; 3.9.2.3.2 200 mm | ml | 6 | 70,00 € | 420,00 €. Total 118 ml = 9 940 €. Os art. 3.11.2.2, 3.11.2.3, 3.11.2.4, 3.11.2.5, 3.11.2.6 a 3.11.2.13 e 3.11.2.15 dizem todos «Inclui soleira pré-fabricada de betão tipo TUBANI». O texto do 3.9.2.3 diz ainda «a aplicar em vãos interiores». | N23: Soleira paga uma só vez: no artigo do vão ou no 3.9.2.3. | O23: -9940 | P23: -9940 | Q23: =AVERAGE(O23:P23) -> -9940 | R23: Soma das larguras dos vãos exteriores cuja descrição inclui soleira Tubani: VE1.01 4,63 + VE1.02 2,50 + VE2.04 2,90 + VE1.03 1,20 + VE1.04/1.09/1.10 3×1,50 + VE2.08 1,40 + VE1.06 3,00 + VE2.01 3×5,33 + VE2.02 7×5,33 + VE2.03 3×5,33 + VE2.05 5,43 + VE2.05.01 2,17 + VE2.06 3,30 + VE2.07 2×6,10 + VE2.14 2,64 + VE1.05 2,61 = 117,77 ml. Isto coincide com os 118 ml do 3.9.2.3, que mede as mesmas soleiras. | S23: Retirar a soleira dos artigos de caixilharia (e reduzir os PU) ou anular o 3.9.2.3. Corrigir 'vãos interiores' para 'exteriores'. | T23: Projetista | U23: NOVO | V23: MANTIDO | W23: Soma recalculada: 117,77 ml, contra 112 + 6 = 118 ml. Os textos com «soleira pré-fabricada de betão tipo TUBANI» foram confirmados em todos os artigos listados (e também no 3.11.2.14, de vãos circulares, bem excluído da soma). O 3.9.2.3 diz «vãos interiores» apesar do título EXT. Valores de 9 520 € + 420 € = 9 940 € confirmados. Prova forte. | X23: Pendente
A24: 20 | B24: 3 | C24: 3.11.2.13.2 | D24: 3.11.2.13; 3.11.2.13.1; 3.11.2.24; 3.11.2.25 | E24: VE.2.14.1 com diâmetro 45cm | F24: ERRO | G24: ALTA | H24: Vão Ø45 cm a 5 174,40 €/un, já incluído no artigo-mãe | I24: 3.11.2.13.2 | UN | 2 | 5 174,40 € | 10 348,80 €. O artigo-mãe 3.11.2.13 (porta metálica TRIA TSN2 de 2 folhas) diz «Incluí 2 vãos de ventilação fixos tipo Navarra série 12000». A porta VE.2.14 (2,64x2,40) custa 4 840,00 €. | J24: 2 | K24: UN | L24: 5174.4 | M24: 10348.8 | N24: Um vão de ventilação circular custa 119,58 € (3.11.2.25, Ø300) a 438,64 € (3.11.2.24). Se VE.2.14.1 forem os 2 vãos de ventilação, já estão incluídos no artigo-mãe. | O24: 0 | P24: -10348.8 | Q24: =AVERAGE(O24:P24) -> -5174.4 | R24: Com descrição de vão Ø45 cm, o PU é 12 a 43 vezes o de vãos circulares semelhantes do MQT e superior ao da própria porta. Se for duplicação dos vãos incluídos no artigo-mãe: −10 348,80 €. Se o texto estiver errado e for outra porta: 0 €. | S24: Confirmar no mapa de vãos o que é VE.2.14.1. Corrigir a descrição ou o PU, ou eliminar o subartigo. | T24: Projetista | U24: EXISTENTE | V24: MANTIDO | W24: Confirmado em rows.json: 2 × 5 174,40 = 10 348,80 €. O artigo-mãe inclui textualmente «2 vãos de ventilação fixos tipo Navarra série 12000 com lâminas de ventilação». Rácios: 5 174,40/438,64 = 11,8× e /119,58 = 43,3× (≈12–43×). O achado é sólido. | X24: Pendente
A25: 21 | B25: 3 | C25: 3.11.2.26 | D25: 3.11.2.26.1; 3.11.2.26.2; 3.11.2.26 (OMISSÃO) | E25: SOLEIRAS EM CHAPA QUINADA (VE.C.01 / VE.1.11) | F25: FALHA/OMISSÃO | G25: ALTA | H25: Soleiras para 16 vãos sem artigo de caixilharia | I25: 3.11.2.26.1 VE.C.01 | UN | 8 | 51,60 € | 412,80 €; 3.11.2.26.2 VE.1.11 | UN | 8 | 51,60 € | 412,80 €. VE.C.01 e VE.1.11 não aparecem em nenhum outro artigo do MQT. | N25: Cada vão com soleira deve ter o artigo da caixilharia (dimensões, sistema e vidro), como os restantes VE. | O25: 0 | P25: 0 | Q25: =AVERAGE(O25:P25) -> 0 | R25: A pesquisa no MQT só encontra estas linhas para VE.C.01 e VE.1.11. O impacto está quantificado no achado 3.11.2.26 (OMISSÃO), para não contar duas vezes. | S25: Confirmar no mapa de vãos e acrescentar os artigos de caixilharia. | T25: Projetista | U25: EXISTENTE | V25: MANTIDO | W25: Pesquisa em rows.json: 'C.01' só aparece no 3.11.2.26.1. '1.11' só aparece no 3.11.2.26.2, na nota 05 (VI 1.11, que é outro vão) e no 3.15.4.3 (compartimento A.1.11). Os VE.1.11 não constam da lista de inexistentes da nota 05. Valores confirmados. | X25: Pendente
A26: 22 | B26: 3 | C26: 3.11.2.26 (OMISSÃO) | D26: 3.11.2.26.1; 3.11.2.26.2 | E26: Caixilharia dos vãos VE.C.01 e VE.1.11 (omissa) | F26: FALHA/OMISSÃO | G26: ALTA | H26: 16 vãos com soleira e sem caixilharia orçada | I26: VE.C.01 (8 UN) e VE.1.11 (8 UN) só existem nas soleiras 3.11.2.26, a 51,60 €. | N26: Artigos de caixilharia para os 16 vãos, a ≈0–1 500 €/vão consoante a dimensão (o VE.C.02 semelhante custa 471,36 €; vãos de ventilação 119–439 €). | O26: 0 | P26: 24000 | Q26: =AVERAGE(O26:P26) -> 12000 | R26: 16 × até 1 500 € = 24 000 €. Mínimo de 0 € se os vãos não levarem caixilho (por exemplo, aberturas livres). | S26: Confirmar no mapa de vãos e orçar. | T26: Projetista | U26: EXISTENTE | V26: MANTIDO | W26: Pesquisa confirma que não há outras ocorrências. Referências internas corretas (VE.C.02 a 471,36 €; 3.11.2.25 a 119,58 €; 3.11.2.24 a 438,64 €). O intervalo 0–24 000 € é coerente. | X26: Pendente
A27: 23 | B27: 3 | C27: 3.15.9 (OMISSÃO) | D27: 3.9.2.8; 3.15.9.1 | E27: Marcações do campo exterior PAV E 02 (omisso) | F27: FALHA/OMISSÃO | G27: ALTA | H27: Campo exterior sem linhas de jogo | I27: O 3.15.9 só tem marcações interiores: 3.15.9.1 (1 100 m²) e 3.15.9.2 (380 m²) a 2,50 €/m². O 3.9.2.8 (2 538 m²) não inclui linhas. | N27: Marcações multidesportivas em tinta compatível com o Sikafloor Colorsport. Pelo próprio PU do MQT (2,50 €/m²): 2 538 × 2,50 = 6 345 €. | O27: 1500 | P27: 6345 | Q27: =AVERAGE(O27:P27) -> 3922.5 | R27: ≈600–1 000 ml de linhas a 1,5–3 €/ml dá ≈1 500–3 000 €. Aplicando o critério do MQT por m², o máximo é 6 345 €. | S27: Acrescentar o subartigo 3.15.9.3 (campo exterior). | T27: Projetista | U27: EXISTENTE | V27: MANTIDO | W27: Confirmado que o 3.15.9 só tem os subartigos .1 e .2 (setores interiores) e que 'marcaç' não aparece noutro artigo. 2 538 × 2,50 = 6 345 € correto. | X27: Pendente
A28: 24 | B28: 3 | C28: 3.17 (OMISSÃO) | D28: 3.9.1.1; 3.9.2.8; 3.17.2 | E28: Equipamento desportivo (omisso) | F28: FALHA/OMISSÃO | G28: ALTA | H28: Sem balizas, tabelas, postes nem equipamento de ginásio | I28: Nenhum artigo do MQT inclui balizas, tabelas de basquetebol, postes ou redes de voleibol e badminton, ou equipamento de ginástica (pesquisa sem resultados). Só há redes de proteção (3.17.2), cortinas (3.17.7) e bancadas. | N28: Equipamento conforme o DL 100/2003 (balizas e equipamentos de basquetebol), a NP EN 749, a EN 1270, a EN 1271 e a EN 913, para o polidesportivo (1 100 m²), o ginásio (396 m²), a sala de ginástica e o campo exterior (2 538 m²). | O28: 35000 | P28: 70000 | Q28: =AVERAGE(O28:P28) -> 52500 | R28: Balizas: 4–6 × 1,5–3 k€. Tabelas principais e laterais: 15–35 k€. Voleibol e badminton: 2–4 k€. Ginásio: 10–20 k€. Total ≈35–70 k€. Impacto 0 € se o Dono de Obra fornecer o equipamento fora da empreitada. | S28: Decidir se o equipamento entra na empreitada e, nesse caso, criar os artigos com referências normativas. | T28: Dono de Obra | U28: EXISTENTE | V28: MANTIDO | W28: Pesquisa em todo o rows.json sem resultados para baliza, tabela, basquet, voleibol, badminton e espaldar. 'poste' só aparece em contextos não desportivos. O intervalo é plausível. A eventual exclusão pelo Dono de Obra está referida (responsável Dono de Obra). | X28: Pendente
A29: 25 | B29: 5 | C29: 5.3.7 | D29: 3.16.1.18; 6.2.16 | E29: CANAL COM GRELHA CHUVEIROS | F29: DUPLICAÇÃO | G29: ALTA | H29: Drenagem linear dos balneários paga em 5.3.7 e 3.16.1.18 | I29: 5.3.7: 25,60 m × 220,00 € = 5.632,00 €, 'caleiras de pavimento em ferro fundido ... aplicar nas cozinhas, e instalações sanitárias'. 3.16.1.18 'DRENAGEM LINEAR EM BALNEÁRIOS ... tipo ACO 64 em Aço Inox': 28,00 ml × 269,61 € = 7.549,08 €. | J29: 25.6 | K29: m | L29: 220 | M29: 5632 | N29: Uma só medição da drenagem linear dos balneários (3.16.1.18, inox, conforme arquitetura). O programa não tem cozinhas: a pesquisa de 'cozinha' no MQT só encontra 5.3.7. | O29: 0 | P29: 0 | Q29: =AVERAGE(O29:P29) -> 0 | R29: Mesma função (caleira de duche nos balneários) com comprimentos semelhantes (25,6 m vs 28 m) e materiais incompatíveis entre si (ferro fundido vs inox). Retirando o artigo duplicado, poupam-se 5.632 €. | S29: Eliminar 5.3.7, ou reduzi-lo à ligação à rede, e corrigir a referência a cozinhas. | T29: Projetista | U29: EXISTENTE | V29: MANTIDO | W29: Confirmei 25,6 × 220 = 5.632 € e 28 × 269,61 = 7.549,08 €, bem como os dois textos. 'cozinha' só aparece em 5.3.7. O 6.2.16 (ACO inox, 87,4 m) é drenagem pluvial exterior, não balneários, e não entra na duplicação. A duplicação entre especialidades é consistente. [Consolidação: impacto contabilizado em 3.16.1.18 para não contar duas vezes.] | X29: Pendente
A30: 26 | B30: 6 | C30: 6.1.1 | D30: 6.1.3; 2.1.2; 2.1.5 | E30: ESCAVAÇÃO | F30: PREÇO BAIXO | G30: ALTA | H30: Vala com entivação por estacas-prancha/painéis a 5,50 €/m3 | I30: 6.1.1: 708,21 m3 × 5,50 €/m3 = 3.895,16 €. Texto: 'entivações e escoramento das valas com estacas prancha ou painéis metálicos ... montagem e desmontagem'. | J30: 708.21 | K30: m3 | L30: 5.5 | M30: 3895.16 | N30: 12–18 €/m3; com painéis de entivação pode passar dos 20 €/m3. Só a escavação e o transporte custam 16,50 €/m3 no próprio MQT (2.1.2 + 2.1.5). | O30: 4603.37 | P30: 8852.63 | Q30: =AVERAGE(O30:P30) -> 6728 | R30: (12 − 5,50) × 708,21 = 4.603,37 €; (18 − 5,50) × 708,21 = 8.852,63 €. Atenuante: a regularização 6.1.2 está a 46,66 €/m3 (170,53 m3 = 7.957,05 €), o que eleva o custo global da vala para cerca de 20,9 €/m3 escavado. Mesmo assim, fica abaixo de um orçamento de mercado completo (≈ 28 €/m3). | S30: Rever o PU (≥ 12–18 €/m3) ou medir a entivação à parte (m2). | T30: Orçamentista | U30: EXISTENTE | V30: MANTIDO | W30: Confirmei 708,21 × 5,50 = 3.895,16 € e o texto (estacas-prancha/painéis, montagem e desmontagem). As contas estão certas: 4.603,37 € e 8.852,63 €. Acrescentei à fundamentação a compensação parcial pelo PU elevado da areia (6.1.2). O achado mantém-se, porque o conjunto da vala continua abaixo do mercado. | X30: Pendente
A31: 27 | B31: 6 | C31: 6.2.8 | D31: 6.2.8.1; 6.2.8.2; 6.2.8.3; 2.6.5 | E31: GEODRENO | F31: PREÇO BAIXO | G31: ALTA | H31: Geodreno com brita, geotêxtil, vala e pavimentos a 3,56–10,60 €/m | I31: 6.2.8.1 DN100: 29,40 m × 3,56 €; 6.2.8.2 DN160: 420,00 m × 7,65 €; 6.2.8.3 DN200: 183,75 m × 10,60 €. Total 633,15 m / 5.265,41 €. Inclui 'brita 25/40 envolvida em geotêxtil ... levantamento e reposição de pavimentos, abertura e tapamento de vala'. | N31: 2.6.5 (dreno DN160 + brita 25/40 + geotêxtil em secção 0,40 × 0,40, sem vala nem pavimentos) = 20,32 €/ml. Mercado com vala: DN100 16–25, DN160 20–32, DN200 24–38 €/m. | O31: 8149 | P31: 15892 | Q31: =AVERAGE(O31:P31) -> 12020.5 | R31: Mínimo: (16 − 3,56) × 29,4 + (20,32 − 7,65) × 420 + (24 − 10,60) × 183,75 = 8.149 €. Máximo: (25 − 3,56) × 29,4 + (32 − 7,65) × 420 + (38 − 10,60) × 183,75 = 15.892 €. O PU do DN160 é 38% do dreno equivalente 2.6.5, que nem tem vala. | S31: Rever os PU (DN160 ≥ 20,32 €/m, em linha com 2.6.5). | T31: Orçamentista | U31: EXISTENTE | V31: MANTIDO | W31: Confirmei quantidades, PU e totais (104,66 + 3.213 + 1.947,75 = 5.265,41 €; 633,15 m). O 2.6.5 está a 20,32 €/ml, com a descrição citada. Recalculei: mínimo 8.149,39 € e máximo 15.892,09 €. 7,65 / 20,32 = 37,6%. | X31: Pendente
A32: 28 | B32: 6 | C32: 6.2.13 | D32: 6.2.13.1; 6.2.12.3; 6.2.5.7 | E32: CÂMARA DE VISITA NA LIGAÇÃO À TUBAGEM DE 500mm | F32: PREÇO BAIXO | G32: ALTA | H32: CV especial com caixa BA 1,5×1,5 e D400 a 545,62 € | I32: 6.2.13.1 'DN 1.25 e 1,50x1,50mm': 1 UN × 545,62 €. Inclui anéis DN1,25 até 3,00 m, caixa em BA 1,50 × 1,50 m com e = 0,20 m, tampa D400, escavação e envolvimento em C35/45 XA3. O título refere 'TUBAGEM DE 500mm', mas o maior DN no MQT é 400 (6.2.5.7). | N32: Tem de custar mais do que 6.2.12.3 (CV DN1,25 simples com h > 2,50 m = 644,83 €). Mercado: 2.500–5.000 €. Corrigir '1,50x1,50mm' para '1,50 × 1,50 m' e o DN da tubagem. | O32: 1954.38 | P32: 4454.38 | Q32: =AVERAGE(O32:P32) -> 3204.38 | R32: (2.500 − 545,62) = 1.954,38 €; (5.000 − 545,62) = 4.454,38 €. Incoerência interna: a câmara especial (545,62 €) sai mais barata do que a câmara simples DN1,25 (644,83 €). | S32: Rever o PU (decompor anéis, caixa BA, betão C35/45 e tampa D400) e corrigir o texto (DN500 inexistente, unidade 'mm'). | T32: Orçamentista | U32: EXISTENTE | V32: MANTIDO | W32: Confirmei o texto e o PU (1 × 545,62 €). As pesquisas de '500 mm' e 'DN 500' só encontram 6.2.13, e o maior coletor medido é o DN400 (6.2.5.7). As contas estão certas. | X32: Pendente
A33: 29 | B33: 6 | C33: 6.2.18 | D33: 6.2.18.1; 3.3.1; 3.3.2; 3.3.5; nota 02 | E33: CALEIRA – 200x100 mm | F33: DUPLICAÇÃO | G33: ALTA | H33: Caleiras de zinco já incluídas nos artigos de cobertura | I33: 6.2.18.1: 196,60 m × 40,00 € = 7.864,00 € ('caleiras ... em folha de zinco nº 12'). 3.3.1, 3.3.2 e 3.3.5 incluem 'caleira de drenagem de A.P.s ... tipo FTB'. A nota 02 diz: 'encontram-se incluídos ... rufos, ... caleiros ... Optou-se por não fazer a sua medição individualizada'. | N33: 0 € no cap. 6, porque as caleiras estão pagas nas coberturas (1.886 m2). Se o projeto exigir uma caleira de zinco diferente da do sistema FTB, tem de ser expressamente excluída de 3.3.x e da nota 02. | O33: -7864 | P33: -7864 | Q33: =AVERAGE(O33:P33) -> -7864 | R33: Os artigos de cobertura e a nota 02 incluem expressamente as caleiras, logo o 6.2.18 paga o mesmo trabalho pela segunda vez. | S33: Eliminar 6.2.18, ou excluir as caleiras de 3.3.x e da nota 02 e confirmar a compatibilidade do zinco com o sistema FTB. | T33: Projetista | U33: EXISTENTE | V33: MANTIDO | W33: Confirmei 196,6 × 40 = 7.864 €. Os textos de 3.3.1, 3.3.2 e 3.3.5 incluem 'caleira de drenagem de A.P.s ... tipo FTB', e a nota 02 (linha 256) inclui 'caleiros' em todos os artigos de cobertura. Áreas: 1.230 + 454 + 128 + 39 + 35 = 1.886 m2. As coberturas 3.3.3/3.3.4 são planas e também estão abrangidas pela nota 02. A duplicação está bem suportada. | X33: Pendente
A34: 30 | B34: 7 | C34: 7 | D34: 7.4.1–7.4.5; 7.5.1; 7.5.3; 7.7.3.1.1–7.7.3.1.8; 7.7.3.2.1/2/4; 7.9.1; 7.9.5; 7.9.7 | E34: INSTALAÇÕES ELÉTRICAS | F34: DESCRIÇÃO | G34: ALTA | H34: Equipamentos principais do Cap. 7 sem especificação técnica | I34: Designações sem características: 7.4.1 'Q.G.P.' 1 UN × 2.648,86 €; 7.4.2 'Q.P.C.I.G.' 9.541,74 €; 7.5.1 'Inversor Solar' 3 UN × 1.699,55 €; 7.5.3 'Paineis Solares' 192 UN × 132,84 € = 25.505,28 €; 7.7.3.1.1–8 '.Tipo L1'…'.Tipo P3' = 62.857,82 €; 7.7.3.2.x '. Tipo S1/S2/S3' = 7.393,08 €; 7.9.1 'Consola', 7.9.5 'Switch dedicado', 7.9.7 'Servidor'. Soma = 124.345,57 € (46,7 % do Cap. 7 = 265.980,37 €) | M34: 265980.37 | N34: Cada artigo deve definir as características mínimas ou remeter expressamente para a ficha do C.E./peças desenhadas: QGP (In do corte geral, Icc, forma, IP/IK), inversor (kW AC), painel (Wp, tecnologia, garantia), luminária (lm, W, IP/IK, UGR, Ra). Ver Portaria 701-H/2008 (conteúdo das medições e do mapa de quantidades do projeto de execução) | O34: 0 | P34: 0 | Q34: =AVERAGE(O34:P34) -> 0 | R34: Soma calculada no rows.json: 18.364,21 (7.4) + 5.098,65 + 25.505,28 + 62.857,82 + 7.393,08 + 1.670,80 + 773,69 + 2.682,04 = 124.345,57 €. Ao contrário destes, os artigos do Cap. 10 (ex.: 10.1.1) remetem para 'peças escritas e desenhadas'. Sem esta definição não é possível validar preços nem exigir conformidade, e abre-se a porta a substituições por equipamento inferior. | S34: Pedir ao projetista as fichas técnicas e completar as descrições no MQT (ou incluir remissão explícita para o C.E.). Usá-las como base nas consultas a subempreiteiros. | T34: Projetista | U34: EXISTENTE | V34: MANTIDO | W34: Conferidos todos os PU/totais no rows.json: soma dos 8 L/P = 62.857,82 €; S1+S2+S3 = 1.734,48+3.814,00+1.844,60 = 7.393,08 €; soma global 124.345,57 € = 46,75 % de 265.980,37 €. As designações são de facto só códigos ('.Tipo L1', 'Q.G.P.'), sem remissão para o C.E. (ao contrário de 10.1.1/10.1.2/10.3.1 e 11.14.1). | X34: Pendente
A35: 31 | B35: 7 | C35: 7 (OMISSÃO) | D35: 7.3; 7.4.1; 7.5 | E35: SPDA – proteção contra descargas atmosféricas | F35: FALHA/OMISSÃO | G35: ALTA | H35: Sem SPDA nem descarregadores de sobretensões | I35: Nenhum artigo de captores, descidas, ligadores de medição ou elétrodos de SPDA, nem de descarregadores. 7.3 'Rede Terra' = 5.271,03 € | N35: Análise de risco segundo a NP EN 62305-2 e, se exigido, SPDA segundo a NP EN 62305-3 (cobertura de grande área com 192 módulos FV). SPD tipo 1/2 no QGP (RTIEBT secções 443/534) | O35: 1000 | P35: 20000 | Q35: =AVERAGE(O35:P35) -> 10500 | R35: Pesquisa em todo o MQT ('raio', 'descarreg', 'SPDA', 'sobretens', 'captor') sem resultados relevantes. O edifício é de grande dimensão, de uso escolar/desportivo e tem gerador FV na cobertura. Mínimo: só SPD tipo 1+2 no QGP e tipo 2 nos quadros parciais/FV (≈ 1.000 €) se a análise de risco dispensar SPDA externo; máximo com SPDA completo ≈ 20.000 €. | S35: Pedir a análise de risco e o projeto de SPDA e criar os artigos. | T35: Projetista | U35: EXISTENTE | V35: CORRIGIDO | W35: Pesquisa refeita em todo o rows.json: 'raio' só aparece em 13.1.1 (árvores); 'descarreg', 'spda', 'sobretens', 'captor' com 0 resultados. Omissão real. Corrigido o impacto_min de 8.000 € para 1.000 €: a NP EN 62305-2 pode dispensar SPDA externo, ficando só os SPD (que também podem estar dentro do PU dos quadros). | X35: Pendente
A36: 32 | B36: 7 | C36: 7.5.3 | D36: 7.5.4; 7.5.5; 7.4.5 | E36: Paineis Solares | F36: DESCRIÇÃO | G36: ALTA | H36: UPAC sem potência definida, proteções DC/AC nem registo | I36: 7.5.3 'Paineis Solares' 192 UN × 132,84 €; 7.5.4 'Estrutura de suporte dos painéis' 1 UN × 10.161,49 €; 7.5.5 'Instalação Elétrica, parametrização e configuração do sistema, testes e colocação em serviço.' 1 UN × 5.281,80 €. Não há artigo de caixas de proteção de strings, descarregadores DC/AC, registo nem certificado de exploração | J36: 192 | K36: UN | L36: 132.84 | M36: 25505.28 | N36: DL 15/2022: uma UPAC entre 30 kW e 1 MW exige registo prévio e certificado de exploração. Proteções DC (seccionamento/fusíveis por string) e SPD tipo 2 DC/AC segundo a RTIEBT secção 712 / IEC 60364-7-712. Verificação estrutural da cobertura para a sobrecarga dos painéis | O36: 0 | P36: 2500 | Q36: =AVERAGE(O36:P36) -> 1250 | R36: A potência e a tecnologia não estão definidas, pelo que o preço não pode ser validado. Muitos inversores string já integram seccionador e SPD DC; as proteções AC podem estar no Q.PV.AC (2.683,37 €) e a colocação em serviço em 7.5.5. Parte possivelmente em falta: caixas DC externas 3 × 300–500 € + SPD adicional 0–300 € + registo/inspeção da UPAC 300–600 € ≈ 0–2.500 € (0 se tudo estiver integrado/incluído). | S36: Completar a descrição (Wp, tecnologia, garantias) e criar artigos para as proteções DC/AC e para o registo/certificado da UPAC. Pedir a verificação estrutural da cobertura. | T36: Projetista | U36: EXISTENTE | V36: CORRIGIDO | W36: Valores conferidos (192 × 132,84 = 25.505,28; 10.161,49; 5.281,80; Q.PV.AC 2.683,37). Pesquisa por 'descarreg', 'sobretens', 'registo', 'certific' sem artigos elétricos. Regime DL 15/2022 (30 kW–1 MW: registo prévio + certificado de exploração) correto. Corrigida a fundamentação: a decomposição original somava até 3.000 € e não tinha em conta que os inversores string costumam integrar proteções DC; o máximo de 2.500 € fica agora coerente com a decomposição. | X36: Pendente
A37: 33 | B37: 7 | C37: 7.7.3.1.9 | D37: 7.7.3.1.8; 7.7.3.1.10; 7.3.4 | E37: .Postes 12m para luminárias P3 | F37: PREÇO BAIXO | G37: ALTA | H37: Poste de 12 m a 570,65 € sem maciço de fundação | I37: 7.7.3.1.9 '.Postes 12m para luminárias P3' 4 UN × 570,65 € = 2.282,60 €, sem maciço. Para comparação, 7.7.3.1.10 '.Tipo E1 (incluindo poste de 3,5m)' custa 604,55 €/un com luminária incluída | J37: 4 | K37: UN | L37: 570.65 | M37: 2282.6 | N37: Coluna troncocónica de 12 m em aço galvanizado ≈ 360 kg (ficha Thorn 'COL 12M STEEL TAPER') ≈ 1.000–1.400 € só a coluna; maciço em betão armado com chumbadouros M20–M22 ≈ 300–700 €; montagem com grua ≈ 200–400 €. Total ≈ 1.500–2.500 €/un | O37: 3717.4 | P37: 7717.4 | Q37: =AVERAGE(O37:P37) -> 5717.4 | R37: Um poste de 12 m sai mais barato do que um balizador de 3,5 m com luminária (604,55 €). (1.500 − 570,65) × 4 = 3.717,40 €; (2.500 − 570,65) × 4 = 7.717,40 €. Fonte: thornlighting.co.uk (Steel Tapered Columns, 12 m, ~360 kg). | S37: Rever o PU e criar um artigo para o maciço de fundação, com dimensionamento ao vento (EN 40). | T37: Orçamentista | U37: EXISTENTE | V37: MANTIDO | W37: Valores conferidos (4 × 570,65 = 2.282,60; E1 604,55). Pesquisa por 'maciço' no MQT só encontra artigos de estruturas (2.x), águas e cobertura — nenhum maciço de poste. Aritmética do impacto correta. A fonte Thorn (peso) não foi verificável offline, mas a ordem de grandeza é plausível. | X37: Pendente
A38: 34 | B38: 13 | C38: 13 (OMISSÃO) | D38: 4.3.10, 4.5.2, 13.6.3, 13.5.1, 13.5.2, 13.3.1–13.3.8 | E38: Rede de rega (~3.550 m2 de áreas plantadas) | F38: FALHA/OMISSÃO | G38: ALTA | H38: Rede de rega inexistente apesar de contador e ramal de rega | I38: Não há nenhum artigo de rede de rega em todo o MQT: a pesquisa por «rega», «aspers» e «gota» só devolve 4.3.10 «CONTADOR REDE DE REGA» (1 × 900,00 €) e 4.5.2 «LIGAÇÃO À REDE REGA» (1 × 700,00 €). Áreas: 13.5.1 prado em hidrossementeira 622 m2; 13.5.2 prado florido 2.568 m2; arbustos ≈368 m2 (13.6.4 manta); 80 árvores (13.3); 13.1.4 = 3.552 m2. 13.6.3 diz que os drenos servem «para facilitar o fornecimento directo da água de rega». | N38: Rega automática, mercado PT: aspersão em prados 4–7 €/m2; gota-a-gota em canteiros 6–10 €/m2; anel/borbulhador por árvore 25–40 €/un; programador, eletroválvulas, caixas e sensor de chuva 1.500–3.000 €. | O38: 8000 | P38: 32000 | Q38: =AVERAGE(O38:P38) -> 20000 | R38: Máximo: 3.190 m2 × 7 + 368 × 10 + 80 × 40 + 3.000 ≈ 32.000 €. Mínimo (prado florido P2 de sequeiro): 622 × 4 + 368 × 6 + 80 × 25 + 1.500 ≈ 8.200 €. Ter contador e ramal de rega sem rede a jusante é incoerente. A «primeira rega» incluída nas plantações não substitui a instalação. | S38: Incluir um subcapítulo de rede de rega (tubagens PEAD, aspersores/pulverizadores, gota-a-gota, eletroválvulas, programador e sensor de chuva) de acordo com o projeto de paisagismo. | T38: Projetista | U38: EXISTENTE | V38: MANTIDO | W38: Pesquisei todo o dump: «rega» só aparece em 4.3.10 (900 €), 4.5.2 (700 €), na «primeira rega» de 13.3.x e em 13.6.3; «aspers» e «gota» não dão resultados. As áreas estão certas (622 + 2.568 + 368 ≈ 3.558 m2, coerente com 13.1.4 = 3.552 m2 e com 13.2.1 = 888 m3 / 0,25 m). Cálculos: 32.210 € (máx.) e 8.196 € (mín.). | X38: Pendente
A39: 35 | B39: 14 | C39: 14.4.4 | D39: 14.4.2, 14.4.3 | E39: LIHCH 6x2x0.75 | F39: ERRO | G39: ALTA | H39: Cabo LIHCH 6x2x0,75 a 120,76 €/m (≈50× o mercado) | I39: 14.4.4 «LIHCH 6x2x0.75» – Un m, Qtd 110, PU 120,76 €/m, Total 13.283,60 € (84 % do subcapítulo 14.4 = 15.725,96 €). | J39: 110 | K39: m | L39: 120.76 | M39: 13283.6 | N39: Pela progressão interna (14.4.2 LIHCH 2x2x0.75 a 1,86 €/m; 14.4.3 LIHCH 4x2x0.75 a 2,12 €/m) o 6x2x0.75 ficaria a ≈2,38 €/m; mercado PT 2025-26 (fornecimento e enfiamento): 2,40–3,50 €/m. | O39: -12898.6 | P39: -13019.6 | Q39: =AVERAGE(O39:P39) -> -12959.1 | R39: Cada 2 pares adicionais acrescentam ≈0,26 €/m (1,86 → 2,12); 120,76 €/m é ≈50 vezes a referência, o que indica erro de digitação ou de unidade. Impacto = (PU_ref − PU_mqt) × Qtd: (3,50 − 120,76) × 110 = −12.898,60 €; (2,40 − 120,76) × 110 = −13.019,60 €. | S39: Corrigir o PU para ≈2,4–3,5 €/m e rever o subtotal 14.4 e o total do capítulo 14. | T39: Orçamentista | U39: EXISTENTE | V39: MANTIDO | W39: Confirmado no rows.json: 14.4.4 m, 110 × 120,76 = 13.283,60 €; 14.4 = 15.725,96 € (84,5 %); 14.4.2 a 1,86 €/m e 14.4.3 a 2,12 €/m. O total geral é 4.499.642 €. Os cálculos de impacto estão certos (−12.898,60 / −13.019,60). A convenção de sinal (mín. = menor redução) é a mesma dos outros achados de redução. | X39: Pendente
A40: 36 | B40: GERAL | C40: GERAL | D40: 82 artigos (ver folha VERIF. ARITMÉTICA do MQT anotado) | E40: Aritmética | F40: ERRO | G40: MÉDIA | H40: Total de custo ≠ Qtd × PU em 82 artigos; venda < custo em 49 | I40: Diferenças até 6,35 € por artigo (ex.: 3.9.2.8: 2.538 × 50,18 = 127.356,84 € mas o total de custo é 127.363,19 €). | N40: Total = Qtd × PU arredondado a 2 casas, igual nas duas colunas. | O40: -12.12 | P40: -12.12 | Q40: =AVERAGE(O40:P40) -> -12.12 | R40: PU de custo com mais casas decimais na origem, colados como valores. | S40: Arredondar PU e recalcular. | T40: Orçamentista | U40: EXISTENTE | V40: MANTIDO | W40: Verificado por script. | X40: Pendente
A41: 37 | B41: GERAL | C41: GERAL | D41: Capítulo 3 (121 de 236 artigos) | E41: Medições | F41: VERIFICAR | G41: MÉDIA | H41: Quantidades redondas: estimativas e não medições | I41: 121 de 236 quantidades da Arquitetura são números inteiros redondos (9.000 m3, 1.000 m2, 2.500 m3, 1.550 m2, 850 m2…); na Estabilidade só 3 de 69. | N41: Medições com memória de cálculo a partir das peças desenhadas. | O41: 0 | P41: 0 | Q41: =AVERAGE(O41:P41) -> 0 | R41: Contagem por script das quantidades inteiras (excl. UN/VG). | S41: Pedir memória de medições e conferir os 20 maiores artigos (39,3% do custo). | T41: Projetista | U41: EXISTENTE | V41: MANTIDO | W41: Verificado por script. | X41: Pendente
A42: 38 | B42: 1 | C42: 1.2 | D42: 1.1 | E42: IMPLEMENTAÇÃO DO PLANO DE QUALIDADE, PLANEAMENTO E GESTÃO DE OBRA | F42: PREÇO BAIXO | G42: MÉDIA | H42: Faseamento com pavilhão em funcionamento por 2.000 € | I42: 1 UN × 2.000,00 € = 2.000,00 €. Inclui as 'fases de obra de modo a garantir que o Pavilhão Existente se possa manter em funcionamento', o acesso à obra e a circulação na escola 'através da implementação limites físicos devidamente sinalizados'. 1.1 já inclui 'delimitações/vedações' e 'Todos os trabalhos necessários à implementação do Plano de Qualidade, Planeamento e Gestão de Obra'. | J42: 1 | K42: UN | L42: 2000 | M42: 2000 | N42: 7.000–17.000 € para um faseamento em 2 fases (separações físicas móveis, percursos protegidos e sinalização durante toda a obra), descontando o que 1.1 já paga (vedações e Plano de Qualidade). Ou 0 € se 1.1 declarar expressamente que inclui as vedações de faseamento. | O42: 0 | P42: 15000 | Q42: =AVERAGE(O42:P42) -> 7500 | R42: Só a mudança de separações entre fases (cerca de 150–250 ml de tapume a 15–25 €/ml ≈ 2.250–6.250 € por fase), mais percursos protegidos e sinalização, ultrapassa os 2.000 €. Mas 1.1 (265.185 €) já inclui 'delimitações/vedações' e 'sinalização', por isso as separações físicas podem já estar pagas: o impacto líquido vai de 0 a 15.000 €. | S42: Rever o PU para 7–17 k€, ou indicar em 1.1 que as vedações de faseamento estão lá incluídas e limitar 1.2 ao plano de faseamento. | T42: Orçamentista | U42: EXISTENTE | V42: CORRIGIDO | W42: Textos de 1.1 e 1.2 confirmados. O próprio achado admite uma solução sem custo (declarar em 1.1 a inclusão das vedações de faseamento), por isso o mínimo de 5.000 € não é sustentado: impacto_min corrigido de 5.000 para 0. O máximo (15.000 €) foi mantido. | X42: Pendente
A43: 39 | B43: 1 | C43: 1.5 | D43: 2.2.1; 2.3.1; 2.2.13 | E43: IMPLANTAÇÃO DE OBRA | F43: PREÇO BAIXO | G43: MÉDIA | H43: Implantação e apoio topográfico de toda a obra por 3.000 € | I43: 1 UN × 3.000,00 € = 3.000,00 €: 'implantação e piquetagem de toda a obra, incluindo apoio topográfico'. | J43: 1 | K43: UN | L43: 3000 | M43: 3000 | N43: 5.000–8.000 € para implantação e apoio topográfico contínuo numa obra com cerca de 160 microestacas, 900 ml de perfis selados, 13 ancoragens e duas fases. | O43: 2000 | P43: 5000 | Q43: =AVERAGE(O43:P43) -> 3500 | R43: 2.2.1: 599,85 ml / 8,5 m ≈ 71 un. 2.3.1: 1.080,33 ml / 12,15 m ≈ 89 un. Perfis 2.2.3–2.2.5: 899,98 ml. A diferença para a referência é de 2.000–5.000 €. | S43: Rever o PU para 5–8 k€. | T43: Orçamentista | U43: EXISTENTE | V43: MANTIDO | W43: Valor e texto confirmados. 'topogr' só aparece em 1.5 em todo o MQT. Contagens recomputadas: 70,6 un, 88,9 un e 291,50 + 333,20 + 275,28 = 899,98 ml. A referência é plausível (10–15 dias de topógrafo ao longo da obra). | X43: Pendente
A44: 40 | B44: 1 | C44: 1.7 | D44: 3.1.3; 5.4.3; 6.3.3 | E44: DESATIVAÇÕES | F44: DESCRIÇÃO | G44: MÉDIA | H44: Verba global sem âmbito e sobreposta a 3.1.3 | I44: 1 UN × 2.000,00 € = 2.000,00 €: 'Fornecimento e execução de desativação demolição e remoção de infraestruturas existentes.' 3.1.3 inclui '.Demolição e desativação de infraestruturas existentes' (pago em 3.1.3.1–3.1.3.3, 47.520 €). | J44: 1 | K44: UN | L44: 2000 | M44: 2000 | N44: Um artigo com âmbito definido (que redes e onde), sem sobreposição: ou 1.7 com a lista de infraestruturas e sem a menção em 3.1.3, ou eliminar 1.7. | O44: 0 | P44: -2000 | Q44: =AVERAGE(O44:P44) -> -1000 | R44: Os mesmos trabalhos estão descritos em 1.7 e em 3.1.3. Há também desativações de desvios de rede em 5.4.3 e 6.3.3. Se houver duplicação, o artigo a eliminar vale 2.000 €. | S44: Definir o âmbito de 1.7 ou eliminá-lo. | T44: Projetista | U44: EXISTENTE | V44: MANTIDO | W44: Conferido: 3.1.3 (linha Excel 206) inclui '.Demolição e desativação de infraestruturas existentes'; 3.1.3.1–3.1.3.3 = 20.480 + 26.000 + 1.040 = 47.520 €. 5.4.3 e 6.3.3 (750 € cada) são desativações do desvio provisório da rede, que é outro âmbito, como o achado indica. Impacto coerente. | X44: Pendente
A45: 41 | B45: 2 | C45: 2.1.1 | D45: 2.1.5 | E45: ESCAVAÇÃO GERAL | F45: DUPLICAÇÃO | G45: MÉDIA | H45: 'Carga e transporte' pagos em 2.1.1 e outra vez em 2.1.5 | I45: 9.861,90 m3 × 5,50 € = 54.240,45 €: 'Escavação em terreno de qualquer natureza ... incluindo carga e transporte de material'. 2.1.5: 8.171,56 m3 × 5,50 € = 44.943,58 €: 'Carga, transporte, descarga e colocação de terras ... à distância média de 20km'. | J45: 9861.9 | K45: m3 | L45: 5.5 | M45: 54240.45 | N45: A carga e o transporte das terras sobrantes devem ser pagos uma só vez (em 2.1.5). 2.1.1 deve ficar limitado à escavação e à movimentação interna para depósito provisório. 'Terreno de qualquer natureza' obriga o PU a incluir rocha: 5,50 €/m3 só chega para solos escaváveis com meios correntes (a escavação em rocha com martelo custa normalmente mais de 15 €/m3). | O45: 0 | P45: -8171.56 | Q45: =AVERAGE(O45:P45) -> -4085.78 | R45: Os dois artigos descrevem a 'carga e transporte' do mesmo volume (2.1.5 = 2.1.1 + 2.1.2 − 2.1.3). Uma carga mecânica custa cerca de 1 €/m3, por isso até 8.171,56 € podem estar pagos duas vezes. O MQT não caracteriza o terreno nem tem artigo de rocha. | S45: Retirar 'carga e transporte' de 2.1.1 e confirmar a natureza do terreno com o estudo geotécnico. Se houver rocha, criar um subartigo próprio. | T45: Projetista | U45: EXISTENTE | V45: MANTIDO | W45: Textos e valores confirmados (linhas Excel 24 e 33). A sobreposição textual é real. É coerente com o achado 2.1.5 (a referência de 7–9 €/m3 de 2.1.5 inclui a carga que sairia de 2.1.1), por isso não há dupla contagem. Impacto até −8.171,56 € a 1 €/m3, plausível. | X45: Pendente
A46: 42 | B46: 2 | C46: 2.1.5 | D46: 2.1.1; 2.1.2; 2.1.3; 3.2.1 | E46: TRANSPORTE A VAZADOURO | F46: PREÇO BAIXO | G46: MÉDIA | H46: Vazadouro a 20 km com taxa de depósito a 5,50 €/m3; 3.2.1 sem destino | I46: 8.171,56 m3 × 5,50 € = 44.943,58 €. A quantidade é 2.1.1 (9.861,90) + 2.1.2 (698,28) − 2.1.3 (2.388,61) = 8.171,57 m3. Texto: 'à distância média de 20km ... e eventual indemnização por depósito'. 3.2.1: 2.500 m3 × 5,50 € = 13.750 €, só com 'carga e transporte de material', sem vazadouro. | J46: 8171.56 | K46: m3 | L46: 5.5 | M46: 44943.58 | N46: 7–9 €/m3 (medido no perfil) para carga, transporte a 20 km e taxa de deposição de solos (LER 17 05 04) em operador licenciado. O empolamento (20–30%) entra no PU, porque a medição é feita no perfil. Os 2.500 m3 de 3.2.1 precisam de destino (vazadouro ou reutilização). | O46: 12257.34 | P46: 28600.46 | Q46: =AVERAGE(O46:P46) -> 20428.9 | R46: (7−5,5)×8.171,56 = 12.257,34 €; (9−5,5)×8.171,56 = 28.600,46 €. Se os 2.500 m3 de 3.2.1 forem também a vazadouro ao PU atual: +13.750 €, máximo 42.350,46 €. A quantidade está correta pelo critério de medição no perfil; o problema é o PU. | S46: Rever o PU para 7–9 €/m3 e acrescentar o destino final dos 2.500 m3 de 3.2.1 (vazadouro ou reutilização declarada). | T46: Orçamentista | U46: EXISTENTE | V46: MANTIDO | W46: Conferido: 2.1.5 q=8.171,56, PU 5,50, total 44.943,58; 9.861,90 + 698,28 − 2.388,61 = 8.171,57. 3.2.1: 2.500 m3 × 5,50 = 13.750, texto 'incluindo carga e transporte de material', sem vazadouro, e nenhum outro artigo de terras a vazadouro no cap. 3 (os 3.1.x são demolições). Cálculos recomputados. É coerente com o achado 2.1.1: a referência de 7–9 €/m3 já inclui a carga, que sairia de 2.1.1. [Consolidação: máximo reduzido para 28.600,46 € porque o destino dos 2.500 m3 de 3.2.1 está quantificado no achado 3.2.1.] | X46: Pendente
A47: 43 | B47: 2 | C47: 2.2.3 | D47: 2.2.1; 2.2.4 | E47: PERFIS SELADOS HEA120 | F47: DESCRIÇÃO | G47: MÉDIA | H47: Perfil HEA com selagem 'pelo interior da armadura' (texto copiado) | I47: 291,50 ml × 88,89 € = 25.912,71 €. Texto: 'perfis selados, 200 mm de diâmetro nominal, ... perfis classe S275, e leitada ... derramada pelo interior da armadura através de sistema de injecção repetitiva seletiva (IRS)'. | J47: 291.5 | K47: ml | L47: 88.89 | M47: 25912.71 | N47: Perfil HEA120 S275 colocado em furo Ø200 mm e selado com calda de cimento injetada pelo fundo do furo, com o comprimento de selagem e as cotas definidos no projeto. | O47: 0 | P47: 0 | Q47: =AVERAGE(O47:P47) -> 0 | R47: Um perfil H não tem interior: o texto foi copiado da microestaca tubular (2.2.1). O diâmetro do furo (200 mm) está indicado; faltam o comprimento e a cota de selagem. | S47: Reescrever a descrição do método de selagem e indicar o comprimento. | T47: Projetista | U47: EXISTENTE | V47: MANTIDO | W47: Texto confirmado na linha Excel 41. q=291,50, PU 88,89, total CUSTO 25.912,71 (Qtd × PU = 25.911,44; a diferença de arredondamento é tratada no achado global de totais). | X47: Pendente
A48: 44 | B48: 2 | C48: 2.2.4 | D48: 2.2.3; 2.2.1 | E48: PERFIS SELADOS HEB140 | F48: DESCRIÇÃO | G48: MÉDIA | H48: Perfil HEB com selagem 'pelo interior da armadura' (texto copiado) | I48: 333,20 ml × 100,61 € = 33.521,71 €. Texto igual ao de 2.2.3: '...leitada ... derramada pelo interior da armadura através de sistema de injecção repetitiva seletiva (IRS)'. | J48: 333.2 | K48: ml | L48: 100.61 | M48: 33521.71 | N48: Perfil HEB140 S275 em furo Ø200 mm selado com calda injetada pelo fundo do furo, com o comprimento de selagem definido. | O48: 0 | P48: 0 | Q48: =AVERAGE(O48:P48) -> 0 | R48: O mesmo erro de cópia de 2.2.3: um perfil HEB não tem interior para injeção IRS. | S48: Reescrever a descrição, como em 2.2.3. | T48: Projetista | U48: EXISTENTE | V48: MANTIDO | W48: Texto confirmado igual ao de 2.2.3 (linha Excel 43). q=333,20, PU 100,61, total CUSTO 33.521,71. | X48: Pendente
A49: 45 | B49: 2 | C49: 2.2.10 | D49: 2.2.11 | E49: ESCORAS | F49: FALHA/OMISSÃO | G49: MÉDIA | H49: Escoras provisórias sem desmontagem e mais caras que o aço definitivo | I49: 2.2.10.1 HEA160: 2.842,40 kg × 3,12 € = 8.868,29 €. 2.2.10.2 HEA140: 1.004,20 kg × 3,12 € = 3.133,10 €. Total 12.001,39 €. Texto: só 'Fornecimento e colocação'. PU de 3,12 €/kg, acima dos perfis de 2.2.11 (2,84–2,95 €/kg). | N49: Incluir desmontagem, corte de ligações e remoção das escoras provisórias (0,40–1,00 €/kg). Se o aço for recuperado, o PU deve ser de aluguer/valor residual, abaixo do aço definitivo. | O49: 1538.64 | P49: 3846.6 | Q49: =AVERAGE(O49:P49) -> 2692.62 | R49: 3.846,60 kg × 0,40–1,00 €/kg = 1.538,64–3.846,60 €. Uma escora provisória com PU acima do aço definitivo (2.2.11) não é coerente se o aço for recuperado. | S49: Acrescentar ao texto a desmontagem e remoção e rever o PU conforme o aço seja recuperável ou perdido. | T49: Projetista | U49: EXISTENTE | V49: MANTIDO | W49: Conferido: 2.842,40 + 1.004,20 = 3.846,60 kg; totais 8.868,29 + 3.133,10 = 12.001,39 €. PU de 2.2.11 entre 2,84 e 2,95 €/kg, confirmado. 'Destensio' e 'desmont' de escoras não aparecem noutro artigo. Cálculo correto. | X49: Pendente
A50: 46 | B50: 2 | C50: 2.2.11 | D50: 2.2.10 | E50: PERFIS METÁLICOS | F50: VERIFICAR | G50: MÉDIA | H50: Perfis da contenção sem função (provisória ou definitiva) nem proteção | I50: 2.2.11.1 HEA220: 4.568,43 kg. 2.2.11.2 UNP100: 24,49 kg. 2.2.11.3 HEA180: 168,31 kg. 2.2.11.4 IPE220: 618,96 kg. 2.2.11.5 IPE270: 3.316,58 kg. Total 8.696,77 kg a 2,84–2,95 €/kg = 25.564,51 €. O texto é igual ao de 2.2.10 e não diz se os perfis são provisórios ou definitivos nem que proteção anticorrosiva levam. | N50: Indicar a função (longarinas ou vigas de distribuição, provisórias ou definitivas). Se forem definitivas: esquema de proteção (galvanização ou pintura segundo a EN ISO 12944), cerca de +0,6–1,0 €/kg. Se forem provisórias: desmontagem. | O50: 0 | P50: 0 | Q50: =AVERAGE(O50:P50) -> 0 | R50: O texto é copiado de 2.2.10 e não é possível quantificar sem desenhos. | S50: Completar a descrição com a função, a proteção e a desmontagem. | T50: Projetista | U50: EXISTENTE | V50: MANTIDO | W50: Conferido: soma 8.696,77 kg e total 25.564,51 € (13.476,87 + 69,55 + 493,15 + 1.807,36 + 9.717,58). O texto de 2.2.11 é idêntico ao de 2.2.10. Fica como verificação, sem impacto. | X50: Pendente
A51: 47 | B51: 2 | C51: 2.3.7 | D51: 2.3.8; 2.2.6 | E51: MURO DE SUPORTE | F51: NORMA | G51: MÉDIA | H51: Classe de exposição 'XC' incompleta no maior artigo de betão | I51: 262,53 m3 × 657,49 € = 172.610,32 € (10,45% do cap. 2). Texto: 'C30/37, XC, Cl 0.40, S4, Dinf 2mm, Dsup 20mm'. | J51: 262.53 | K51: m3 | L51: 657.49 | M51: 172610.32 | N51: Classe de exposição completa segundo a NP EN 206 e a LNEC E 464 (muro em contacto com o terreno: XC2, ou XC4 na face exposta). Os outros elementos usam XC2 (2.2.x) e XC4 (2.3.8). Validar a medição. | O51: 0 | P51: 0 | Q51: =AVERAGE(O51:P51) -> 0 | R51: 'XC' sem algarismo não é uma classe válida e define o recobrimento e a durabilidade de 172,6 k€ de betão. | S51: Completar a classe de exposição e validar a quantidade com os desenhos. | T51: Projetista | U51: EXISTENTE | V51: MANTIDO | W51: Texto 'XC,' confirmado (linha Excel 103). 172.610,32/1.651.924,53 = 10,45%, confirmado. 2.3.8 com XC4 e 2.2.x com XC2, confirmado. | X51: Pendente
A52: 48 | B52: 2 | C52: 2.3.12 | D52: 2.3.13 | E52: LAJE MACIÇA | F52: VERIFICAR | G52: MÉDIA | H52: Escoramento limitado a 4,0 m e betão C25/30 diferente do resto | I52: 243,09 m3 × 435,21 € = 105.794,23 €. Texto: 'C25/30, XC1, Cl 0.40, S3, Dmáx 20 mm ... escoramento até 4.0 m'. 2.3.13 também é C25/30; os outros elementos são C30/37. | J52: 243.09 | K52: m3 | L52: 435.21 | M52: 105794.23 | N52: Escoramento para a altura real das lajes (se houver pés-direitos acima de 4 m, por exemplo em bancadas ou átrios, prever um subartigo próprio) e classe de betão confirmada no projeto (C25/30 é o mínimo admissível para XC1 na LNEC E 464). | O52: 0 | P52: 0 | Q52: =AVERAGE(O52:P52) -> 0 | R52: O MQT não indica os pés-direitos. Sem desenhos não é possível quantificar escoramento acima de 4 m. | S52: Confirmar no projeto as alturas de escoramento e a classe do betão. | T52: Projetista | U52: EXISTENTE | V52: MANTIDO | W52: Texto e valores confirmados (linhas Excel 114 e 116). Qtd × PU = 105.795,20 e total CUSTO 105.794,23 (citado corretamente). Está bem classificado como verificação, sem impacto. | X52: Pendente
A53: 49 | B53: 2 | C53: 2.3.14 | D53: 2.3.14.1; 2.3.14.2; 2.3.14.3 | E53: PAVIMENTO TÉRREO | F53: DESCRIÇÃO | G53: MÉDIA | H53: Título diz '15 cm' mas as camadas não coincidem | I53: Título: 'PAVIMENTO TÉRREO com 15 cm de espessura'. 2.3.14.1 P.T.1 brita 0,22 m: 419,56 m2 × 51,52 €. 2.3.14.2 P.T.2 brita 0,15 m: 1.602,90 m2 × 48,91 €. 2.3.14.3 P.T.3 brita 0,17 m: 262,82 m2 × 49,66 €. Laje de 0,12 m e regularização de 0,05 m. | N53: Retirar os '15 cm' do título ou indicar as espessuras por tipo (brita 0,22/0,15/0,17 m; regularização 0,05 m; laje 0,12 m). | O53: 0 | P53: 0 | Q53: =AVERAGE(O53:P53) -> 0 | R53: Os 15 cm não correspondem à laje (0,12 m), nem à laje com regularização (0,17 m), nem a 2 das 3 caixas de brita. Os PU são coerentes entre si (cerca de 37 €/m3 de brita adicional). | S53: Corrigir o título. | T53: Projetista | U53: EXISTENTE | V53: MANTIDO | W53: Texto e valores confirmados (linhas Excel 118–125). (51,52−48,91)/0,07 = 37,3 €/m3 e (49,66−48,91)/0,02 = 37,5 €/m3. Os 15 cm coincidem só com a brita de P.T.2, como o achado diz. | X53: Pendente
A54: 50 | B54: 2 | C54: 2.4.2 | D54: 2.4.1; 2.2.11.2 | E54: ESTRUTURA METÁLICA INTERIOR | F54: PREÇO BAIXO | G54: MÉDIA | H54: Aço com C3 + intumescente R60 mais barato que aço exterior só com C3 | I54: Texto: 'pintura anticorrosiva da classe C3 e proteção intumescente para 60''. 2.4.2.1 IPE 80: 103,95 kg × 6,94 €. 2.4.2.2 LNP35x4: 53,55 kg × 2,84 €. 2.4.2.3 SHS120x6,3: 78,79 kg × 4,84 €. 2.4.2.4 SHS100x4: 869,65 kg × 3,13 €. Total 3.976,83 €. No exterior (2.4.1, só C3) o PU é 3,91–4,31 €/kg. | N54: 4,50–5,50 €/kg para aço S275 montado com C3 e intumescente R60 em perfis leves (fator de massividade alto). Nunca abaixo do PU do aço exterior sem intumescente. | O54: 1280.31 | P54: 2203.51 | Q54: =AVERAGE(O54:P54) -> 1741.91 | R54: A 4,50 €/kg: (4,50−3,13)×869,65 + (4,50−2,84)×53,55 = 1.280,31 €. A 5,50 €/kg: 2.203,51 €. O LNP35x4 com C3 e R60 tem o mesmo PU (2,84 €/kg) que o UNP100 da contenção sem pintura (2.2.11.2). | S54: Rever os PU de 2.4.2.2 e 2.4.2.4 e uniformizar dentro do artigo. | T54: Orçamentista | U54: EXISTENTE | V54: MANTIDO | W54: Quantidades, PU e total (3.976,83 €) conferidos. 2.4.1.1 a 3,91 €/kg e 2.4.1.2 a 4,31 €/kg; 2.2.11.2 UNP100 a 2,84 €/kg. Impactos recomputados: 1.280,31 € e 2.203,51 €. O IPE 80 a 6,94 €/kg mostra que o PU com intumescente foi aplicado só nalgumas linhas. | X54: Pendente
A55: 51 | B55: 2 | C55: 2.4.4 | E55: GRADIL | F55: ERRO | G55: MÉDIA | H55: Gradil com '0.30 m' de espessura e aço 'ST 37.2' | I55: 17,18 m2 × 156,22 € = 2.683,86 €. Texto: 'gradil para pavimento com 0.30 [m] de espessura, com dimensões 0.030x0.030 [m x m] com 27 kg/m2 ... ST 37.2'. | J55: 17.18 | K55: m2 | L55: 156.22 | M55: 2683.86 | N55: Altura de 0,030 m (30 mm), coerente com 27 kg/m2 e malha 30×30. Aço S235JR (NP EN 10025-2). Galvanização por imersão a quente (EN ISO 1461) se for exterior. | O55: 0 | P55: 0 | Q55: =AVERAGE(O55:P55) -> 0 | R55: Um gradil de 300 mm pesaria muito mais que 27 kg/m2. ST 37-2 é a designação DIN 17100, já anulada. | S55: Corrigir a espessura e a designação do aço e indicar o acabamento. | T55: Projetista | U55: EXISTENTE | V55: MANTIDO | W55: Texto confirmado na linha Excel 147. 17,18 × 156,22 = 2.683,86. A designação ST 37-2 (DIN 17100) foi substituída pela S235JR. | X55: Pendente
A56: 52 | B56: 2 | C56: 2.5.1.8 | D56: 2.5.1.2; 2.5.1.6; 2.5.1.9 | E56: PM 0.20x0.20 | F56: ERRO | G56: MÉDIA | H56: PM 0,20×0,20 com o PU da secção 0,15×0,20 | I56: 98,64 ml × 69,73 € = 6.878,45 € (1.743 €/m3). VM 0.15x0.20 (2.5.1.2) também a 69,73 €/ml. VM 0.20x0.20 (2.5.1.6) a 93,70 €/ml (2.342 €/m3). PM 0.20x0.40 e VM 0.20x0.40 têm ambos 184,36 €/ml. | J56: 98.64 | K56: ml | L56: 69.73 | M56: 6878.45 | N56: 93,70 €/ml, o PU de VM 0.20x0.20 (mesma secção). | O56: 2364.4 | P56: 2364.4 | Q56: =AVERAGE(O56:P56) -> 2364.4 | R56: (93,70−69,73)×98,64 = 2.364,40 €. O par PM/VM 0.20x0.40 tem o mesmo PU, o que confirma que o PU de PM 0.20x0.20 foi copiado da linha errada. | S56: Corrigir o PU para 93,70 €/ml. | T56: Orçamentista | U56: EXISTENTE | V56: MANTIDO | W56: Conferido: 2.5.1.8 q=98,64, PU 69,73, total CUSTO 6.878,45; 69,73/0,04 = 1.743,2 €/m3; 2.5.1.6 93,70/0,04 = 2.342,5 €/m3; 2.5.1.7 e 2.5.1.9 ambos a 184,36. Impacto 2.364,40 € recomputado. | X56: Pendente
A57: 53 | B57: 2 | C57: 2.6.1 | D57: 2.6.6; 3.4.4; 3.4.2 | E57: IMPERMEABILIZAÇÃO COM PINTURA DE BASE BETUMINOSA | F57: VERIFICAR | G57: MÉDIA | H57: Pintura betuminosa em 2.017 m2 pode sobrepor-se ao sistema de 2.6.6 | I57: 2.017,13 m2 × 2,64 € = 5.329,66 € ('elementos em contacto com o terreno', duas camadas cruzadas, primários). 2.6.6: 1.085,80 m2 × 17,65 € (sistema completo no tardoz, com primário). 3.4.4: 464 m2 × 2,64 € (emulsão betuminosa em paredes exteriores). 3.4.2: 637 m2 de XPS em muros. | J57: 2017.13 | K57: m2 | L57: 2.64 | M57: 5329.66 | N57: Um mapa de superfícies que separe fundações (2.6.1), tardoz de muros e contenções (2.6.6) e paredes exteriores (3.4.4), sem áreas repetidas. Para uma pintura betuminosa de 2 demãos, cerca de 3,5–4,5 €/m2. | O57: 0 | P57: -2866.51 | Q57: =AVERAGE(O57:P57) -> -1433.255 | R57: Se os 1.085,80 m2 de 2.6.6 estiverem também em 2.6.1: 1.085,80 × 2,64 = −2.866,51 €. As fundações enterradas (2.2.2, 2.2.8, 2.3.3–2.3.6) somam cerca de 385 m3 (401 m3 com a viga de coroamento 2.2.7). Com esse volume, 2.017 m2 de superfície parece elevado para fundações apenas, o que sugere que 2.6.1 inclui paramentos de muros. Esta é uma estimativa indicativa e não substitui o mapa de superfícies. Em sentido contrário, o PU de 2,64 €/m2 é baixo: +1.734,73 a +3.751,86 € (valor não somado ao impacto). | S57: Pedir o mapa de superfícies, eliminar as áreas repetidas e rever o PU. | T57: Projetista | U57: EXISTENTE | V57: CORRIGIDO | W57: Valores conferidos: 2.6.1 total CUSTO 5.329,66 (Qtd × PU = 5.325,22); 3.4.4 464 × 2,64 = 1.225,98; 3.4.2 637 m2. O volume de 'cerca de 415 m3 de fundações' não se reproduz: a soma de 2.2.2 + 2.2.8 + 2.3.3 + 2.3.4 + 2.3.5 + 2.3.6 dá 385,34 m3 (401,34 com 2.2.7), e a fundamentação foi corrigida. Os dados não provam a duplicação, por isso o tipo passa a VERIFICAR e o estado a AJUSTADO. Impactos recomputados corretamente. | X57: Pendente
A58: 54 | B58: 2 | C58: 2.6.3 | D58: 2.3.14.1; 3.9.1.2 | E58: ENDURECEDOR DE SUPERFÍCIE | F58: VERIFICAR | G58: MÉDIA | H58: Endurecedor na área de P.T.1 que pode levar também Unipiso | I58: 419,56 m2 × 4,31 € = 1.806,63 € (igual à área de P.T.1, 2.3.14.1). 3.9.1.2 PAV I 02 Unipiso 10 cm: Piso 01 com 280 m2 × 35 € e Piso 02 com 339 m2 × 35 €. | J58: 419.56 | K58: m2 | L58: 4.31 | M58: 1806.63 | N58: Endurecedor só onde a laje térrea fica à vista, sem Unipiso nem outro revestimento. | O58: 0 | P58: -1206.8 | Q58: =AVERAGE(O58:P58) -> -603.4 | R58: Se os 280 m2 de Unipiso do Piso 01 assentarem sobre P.T.1: 280 × 4,31 = −1.206,80 €. | S58: Confirmar no mapa de acabamentos. | T58: Projetista | U58: EXISTENTE | V58: MANTIDO | W58: Conferido: 2.6.3 q=419,56 = 2.3.14.1 q=419,56; total CUSTO 1.806,63 (Qtd × PU = 1.808,30). 3.9.1.2.1 Piso 01 280 m2 × 35 e 3.9.1.2.2 Piso 02 339 m2 × 35, confirmado. 280 × 4,31 = 1.206,80. | X58: Pendente
A59: 55 | B59: 2 | C59: 2.6.4.3 | D59: 3.9.1.5; 3.9.2.2; 3.9.1.4.1; 3.9.2.1.1 | E59: Degraus (BANCADAS) | F59: VERIFICAR | G59: MÉDIA | H59: Degraus de bancada em 3 artigos com PU diferentes | I59: 2.6.4.3 Degraus: 92 UN × 106,00 € = 9.752,00 €. 3.9.1.5 Degraus de escada de bancada int. (pré-fabricados 110×30×19 cm): 14 UN × 100,00 € = 1.400 €. 3.9.2.2 Degraus de escada de bancada ext.: 6 UN × 100,00 € = 600 €. Há ainda 3.9.1.4.1 e 3.9.2.1.1 'degrau de remate em bancadas' (20 + 18 m2 × 145 €). | J59: 92 | K59: UN | L59: 106 | M59: 9752 | N59: Um só artigo por elemento. Se for o mesmo degrau pré-fabricado, um só PU. | O59: 0 | P59: -2000 | Q59: =AVERAGE(O59:P59) -> -1000 | R59: O mesmo tipo de peça (degrau de bancada) aparece em 3 artigos, a 106 € e a 100 €, e há ainda os remates de degrau em 3.9.1.4.1 e 3.9.2.1.1. Se 3.9.1.5 e 3.9.2.2 estiverem contidos nos 92 de 2.6.4.3, há −2.000 €. Também pode tratar-se de elementos distintos (degraus estruturais pré-fabricados da bancada em 2.6.4 e degraus das escadas de acesso em 3.9). | S59: Confirmar nas peças desenhadas e eliminar ou uniformizar. | T59: Projetista | U59: EXISTENTE | V59: CORRIGIDO | W59: Valores confirmados. A pesquisa de 'degrau' encontrou também 3.9.1.4.1 e 3.9.2.1.1 (degrau de remate em bancadas, m2 a 145 €), que foram acrescentados aos artigos relacionados e ao no_mqt. Ficou registada a hipótese de serem elementos diferentes. O impacto (0 a −2.000 €) mantém-se. | X59: Pendente
A60: 56 | B60: 2 | C60: 2.6.5 | D60: 6.2.8.2 | E60: DRENO TARDOZ PAREDES DE CONTENÇÃO E MUROS DE SUPORTE | F60: INCOERÊNCIA | G60: MÉDIA | H60: O mesmo dreno DN160 a 20,32 €/ml (2.6.5) e a 7,65 €/m (6.2.8.2) | I60: 2.6.5: PVC corrugado perfurado de dupla parede Ø160, brita 25/40 envolvida em geotêxtil (secção 0,40×0,40), 244,57 ml × 20,32 € = 4.969,17 €. 6.2.8.2 GEODRENO DN 160: PVC corrugado perfurado de dupla parede, brita 25/40 em geotêxtil, 'incluindo levantamento e reposição de pavimentos, abertura e tapamento de vala', 420,00 m × 7,65 € = 3.213,00 €. | J60: 244.57 | K60: ml | L60: 20.32 | M60: 4969.17 | N60: Um PU coerente para o mesmo produto (cerca de 15–22 €/ml com secção drenante de 0,40×0,40) e a confirmação de que os 420 m de 6.2.8.2 não incluem os 244,57 ml do tardoz. | O60: 0 | P60: -4969.17 | Q60: =AVERAGE(O60:P60) -> -2484.585 | R60: 20,32 / 7,65 = 2,66 vezes (+165,6%) para o mesmo tubo e o mesmo material drenante, e 6.2.8.2 ainda inclui vala e reposição. Se o dreno de tardoz também estiver medido em 6.2.8.2, 2.6.5 duplica-o (−4.969,17 €). Se não estiver, o PU de 6.2.8.2 está subavaliado (a tratar no cap. 6). | S60: Confirmar a separação das medições entre 2.6.5 e 6.2.8.2 e uniformizar o critério de preço. | T60: Orçamentista | U60: NOVO | V60: MANTIDO | W60: Conferido em rows.json: 6.2.8 (linha Excel 1260), texto com PVC corrugado de dupla parede EN 13476-1, brita 25/40 em geotêxtil, vala e reposição; 6.2.8.2 DN 160 com 420 m × 7,65 = 3.213. Também 6.2.9.1 (geodreno bancos DN160, 78,75 m a 7,65). Razão 20,32/7,65 = 2,656. A incoerência de PU é factual, por isso o achado fica apesar de ser NOVO. A hipótese de duplicação mantém-se só como verificação (mínimo 0). | X60: Pendente
A61: 57 | B61: 3 | C61: 3 (OMISSÃO) | D61: 3.5.1; 3.7; 3.9.1.1 | E61: Proteções anti-impacto de paredes nas salas desportivas (omisso) | F61: FALHA/OMISSÃO | G61: MÉDIA | H61: Sem proteção de paredes junto a zonas de jogo | I61: Não há nenhum artigo de proteção almofadada ou anti-impacto. As paredes interiores do pavilhão são de painel sandwich com chapa interior microperfurada (3.5.1) e de bloco face à vista (3.7). | N61: Proteção almofadada ou anti-impacto até ≈2 m atrás das balizas e tabelas e junto a obstáculos, quando as zonas livres das normas de equipamento (NP EN 749 / EN 1270) e dos regulamentos federativos não são garantidas. Chapa microperfurada sem proteção fica exposta a bolas. | O61: 0 | P61: 10000 | Q61: =AVERAGE(O61:P61) -> 5000 | R61: Só zonas de topo: ≈80 m² × 40–60 €/m² ≈ 3–5 k€. Perímetro parcial: até ≈10 k€. A necessidade depende do mapa de acabamentos e das zonas de segurança, pelo que o mínimo é 0 € e a gravidade baixa para MÉDIA. | S61: Verificar o mapa de acabamentos e as zonas de segurança e incluir a proteção onde for necessária. | T61: Projetista | U61: EXISTENTE | V61: CORRIGIDO | W61: Pesquisa confirma que não há artigo de proteção de paredes ('almofad' só aparece nos cap. 4 e 5, noutro contexto). Como o próprio achado diz que a exigência depende do projeto e não é obrigatória em todos os casos, o impacto mínimo passa de 3 000 € para 0 €. | X61: Pendente
A62: 58 | B62: 3 | C62: 3.2.1 | D62: 2.1.1; 2.1.5 | E62: ESCAVAÇÃO COTAS DE PAV. EXTERIORES E/OU SOLO VEGETAL | F62: FALHA/OMISSÃO | G62: MÉDIA | H62: 2 500 m3 de escavação sem artigo de transporte a vazadouro | I62: 3.2.1 | m3 | Qtd 2 500 | PU 5,50 € | Total 13 750,00 €. Texto: «... incluindo carga e transporte de material». Sem destino nem distância definidos. O 2.1.1 (escavação geral, 5,50 €/m³) tem a mesma frase e o transporte a vazadouro é pago à parte no 2.1.5 (8 171,56 m³ a 5,50 €/m³, 20 km). | J62: 2500 | K62: m3 | L62: 5.5 | M62: 13750 | N62: Critério igual ao do cap. 2: escavação com 'carga e transporte de material' a 5,50 €/m³ (2.1.1) mais transporte a vazadouro a 20 km a 5,50 €/m³ (2.1.5). Para os 2 500 m³ do 3.2.1 não há artigo equivalente ao 2.1.5. Quantidade a justificar pela área e profundidade das caixas. | O62: 0 | P62: 13750 | Q62: =AVERAGE(O62:P62) -> 6875 | R62: O texto e o PU do 3.2.1 são iguais aos do 2.1.1, que também diz «incluindo carga e transporte de material». O que muda é que, no cap. 2, o destino final a vazadouro é pago no 2.1.5, cuja quantidade (8 171,56 m³) é inferior à do 2.1.1 (9 861,9 m³) e não abrange o cap. 3. Se as terras do 3.2.1 não forem reutilizadas em obra, falta o vazadouro: 2 500 × 5,50 = 13 750 €. Mínimo de 0 € se forem reutilizadas. A quantidade de 2 500 m³ é redonda e não tem medição justificativa. | S62: Definir o destino (reutilização em obra ou vazadouro) e a distância. Se for vazadouro, acrescentar o transporte (como no 2.1.5) e justificar a medição. | T62: Orçamentista | U62: EXISTENTE | V62: CORRIGIDO | W62: Números confirmados (2 500 × 5,50 = 13 750 €). A fundamentação estava errada: o 2.1.1 NÃO é 'escavação sem transporte' e o seu texto inclui «carga e transporte de material», igual ao do 3.2.1. O que está pago à parte no cap. 2 é o transporte a vazadouro a 20 km (2.1.5), que não tem correspondente no cap. 3. Tipo devolvido a FALHA/OMISSÃO. Título, referência e fundamentação reescritos. O impacto de 0–13 750 € mantém-se. | X62: Pendente
A63: 59 | B63: 3 | C63: 3.3.1 | D63: 3.3.1.1; 3.3.1.2; nota 02; 6.2.18; 11.11 | E63: COB. TIPO 01 (painel sandwich FTB PC 1000 acústico 100 mm) | F63: DESCRIÇÃO | G63: MÉDIA | H63: Painel sem núcleo nem classe de fogo; caleiras também em 6.2.18 | I63: 3.3.1.1 | m2 | 1 230 | 71,83 € | 88 348,00 €; 3.3.1.2 | m2 | 454 | 71,83 € | 32 609,75 €. Texto: «painel sandwich tipo FTB PC 1000 acústico com 100mm ... Rufos, chapas de remate com a platibanda, caleira de drenagem de A.P.s». A nota 02 inclui também «caleiros». O art. 6.2.18.1 mede à parte uma caleira de zinco 200x100: m | 196,6 | 40,00 € | 7 864,00 €. | N63: Especificar o núcleo (lã de rocha ou PIR) e a classe de reação ao fogo e de comportamento ao fogo exterior exigidas pelo RT-SCIE (Portaria 1532/2008, na redação da Portaria 135/2020). Referir os remates dos exutores do art. 11.11 (8 RD2 em cobertura). Caleiras orçadas num só artigo. | O63: 0 | P63: 0 | Q63: =AVERAGE(O63:P63) -> 0 | R63: As caleiras de A.P. estão incluídas no 3.3.1, no 3.3.2 e na nota 02 e são medidas de novo no 6.2.18 (196,6 m). O impacto de −7 864 € corresponde à duplicação total. Sem núcleo definido, o preço não é comparável (painel PIR ≠ painel em lã de rocha). A linha de vida é tratada no achado 3.3 (OMISSÃO). | S63: Completar a descrição com o núcleo, a classe de fogo e os remates dos exutores. Retirar as caleiras de 3.3.x/nota 02 ou anular o 6.2.18. | T63: Projetista | U63: EXISTENTE | V63: MANTIDO | W63: Valores confirmados na coluna de custo (88 348,00 € e 32 609,75 €; Qtd × PU visível dá 88 350,90 € e 32 610,82 €, por causa do arredondamento tratado no achado '3'). O texto inclui caleira de A.P. e a nota 02 inclui caleiros. O 6.2.18 mede 196,6 m de caleira de zinco a 40 €. Os materiais são diferentes (sistema FTB vs zinco), o que justifica o intervalo até 0 €. Os 8 RD2 do 11.11 (6 + 2) foram confirmados. [Consolidação: impacto contabilizado em 6.2.18 para não contar duas vezes.] | X63: Pendente
A64: 60 | B64: 3 | C64: 3.3.3 | D64: 3.3.4; 3.9.2.4 | E64: COB. TIPO 03 (cobertura plana com lajetas sobre apoios) | F64: PREÇO BAIXO | G64: MÉDIA | H64: Cobertura plana completa com lajetas sobre plots a 63,44 €/m2 | I64: 3.3.3 | m2 | 256 | 63,44 € | 16 240,08 €. Inclui emulsão, barreira pára-vapor, XPS 80, Impersep, betão leve de 21 a 5 cm, sistema bicapa Imperalum, lajetas 60x40 com suportes reguláveis e maciços para equipamentos. | J64: 256 | K64: m2 | L64: 63.44 | M64: 16240.08 | N64: 85–95 €/m², pela composição do próprio MQT: o 3.3.4 (70,13 €, com Unipiso 12 cm ≈27 €) dá ≈43 € para betão leve, bicapa, XPS e Impersep. Somam-se ≈3–5 € de pára-vapor e emulsão e ≈38–45 € de lajetas (30,50 € no 3.9.2.4) sobre apoios reguláveis. | O64: 5519.36 | P64: 8079.36 | Q64: =AVERAGE(O64:P64) -> 6799.36 | R64: (85−63,44)×256 = 5 519,36 €; (95−63,44)×256 = 8 079,36 €. A cobertura tipo 03 tem mais camadas do que a tipo 04 e custa menos. | S64: Rever o PU com uma decomposição por camadas. | T64: Orçamentista | U64: NOVO | V64: MANTIDO | W64: Texto e valores confirmados (256 m² a 63,44 €; 16 240,08 € de custo). O 3.3.4 (265 m² a 70,13 €) tem as mesmas camadas base com Unipiso em vez de pára-vapor, emulsão e lajetas sobre apoios. Incoerência interna real. Cálculo correto. | X64: Pendente
A65: 61 | B65: 3 | C65: 3.6.1.1 | D65: 3.6.1; 3.10.5 | E65: Chapa ondulada 0,7 mm tipo FTB (fachada) | F65: DESCRIÇÃO | G65: MÉDIA | H65: Título diz alumínio, subartigo aponta chapa de aço tipo FTB | I65: 3.6.1 «Fornecimento de fachada de alumínio ondulada»; 3.6.1.1 «chapa ondulada de 0.7mm de espessura tipo FTB ou equiv.» | m2 | 1 550 | 25,44 € | 39 432,00 €. | J65: 1550 | K65: m2 | L65: 25.44 | M65: 39432 | N65: Definir o material (alumínio lacado ou aço pré-lacado). Em alumínio 0,7 mm lacado, montado, a referência é 28–35 €/m². O PU de 25,44 €/m² só é compatível com aço pré-lacado. | O65: 0 | P65: 14818 | Q65: =AVERAGE(O65:P65) -> 7409 | R65: Se for alumínio: (28−25,44)×1 550 = 3 968 € a (35−25,44)×1 550 = 14 818 €. Se for aço, o impacto é 0 € e só há que corrigir o título. | S65: Uniformizar o material no título e no subartigo e ajustar o PU em conformidade. | T65: Projetista | U65: EXISTENTE | V65: MANTIDO | W65: Confirmado: o título do 3.6.1 diz «alumínio ondulada» e o 3.6.1.1 diz «chapa ondulada de 0.7mm ... tipo FTB». Valores 1 550 × 25,44 = 39 432 € corretos. Cálculo de impacto correto (14 818 €). | X65: Pendente
A66: 62 | B66: 3 | C66: 3.6.1.2 | D66: 3.6.1.1; 3.10.5; 3.5.1 | E66: Sub-estrutura em perfis de aço galvanizado para a chapa ondulada | F66: INCOERÊNCIA | G66: MÉDIA | H66: Subestrutura de 320 m2 para 1 550 m2 de chapa ondulada | I66: 3.6.1.2 | m2 | 320 | 12,50 € | 4 000,00 € contra 3.6.1.1 chapa | m2 | 1 550. Em 3.10.5 (teto em chapa ondulada) o PU de 93,32 € = 25,44 (chapa) + 12,50 (subestrutura) + 55,38 (painel 3.5.1), ou seja, subestrutura em 100 % da área. | J66: 320 | K66: m2 | L66: 12.5 | M66: 4000 | N66: Subestrutura medida na mesma área da chapa (1 550 m²), como o próprio MQT faz em 3.10.5, ou justificação das zonas onde a chapa não a precisa (por exemplo, sobre o painel sandwich do 3.5.1, que já inclui subestrutura). | O66: 0 | P66: 15375 | Q66: =AVERAGE(O66:P66) -> 7687.5 | R66: (1 550−320)×12,50 = 15 375 €. A decomposição exata do PU do 3.10.5 mostra que o orçamentista considera chapa + subestrutura + painel na mesma área. Na fachada a subestrutura cobre apenas 20,6 % da chapa. Mínimo de 0 € se a chapa for fixada sobre o painel sandwich (1 309 m² no 3.5.1, com subestrutura própria) e só os 320 m² sobre alvenaria ou betão precisarem de perfis. | S66: Rever a medição da subestrutura com base nos alçados ou justificar a diferença. | T66: Projetista | U66: EXISTENTE | V66: CORRIGIDO | W66: Números confirmados (320 m² × 12,50 = 4 000 €; chapa 1 550 m²; 25,44 + 12,50 + 55,38 = 93,32 exatos). Não se prova que seja um erro: o 3.5.1 (1 309 m²) já inclui «sub-estrutura em aço galvanizado», e a chapa pode estar sobreposta ao painel, precisando de perfis próprios só noutras zonas. Tipo passa de ERRO para INCOERÊNCIA e gravidade de ALTA para MÉDIA. O intervalo 0–15 375 € mantém-se. | X66: Pendente
A67: 63 | B67: 3 | C67: 3.8.3 | D67: 3.10.1; 3.4.3 | E67: REV. ACU EM ZONAS TÉCNICAS PA I.09 (lã de vidro 40 mm) | F67: PREÇO ALTO | G67: MÉDIA | H67: Painel de lã mineral 40 mm a 54,05 €/m2 | I67: 3.8.3 | m2 | 76 | 54,05 € | 4 107,80 €; 3.10.1 | m2 | 42 | 54,05 € | 2 270,10 €. Só o painel ISOVER TECH Slab 40 mm com véu preto; o acabamento e a subestrutura são pagos à parte (3.8.5 / 3.10.2). | J67: 76 | K67: m2 | L67: 54.05 | M67: 4107.8 | N67: 20–30 €/m², colocado. No próprio MQT, a lã de rocha de 80 mm a 75 kg/m³ custa 10,66 €/m² (3.4.3). | O67: -2837.9 | P67: -4017.9 | Q67: =AVERAGE(O67:P67) -> -3427.9 | R67: (20−54,05)×118 = −4 017,90 €; (30−54,05)×118 = −2 837,90 €. Um painel com metade da espessura custa cinco vezes mais do que o isolamento de 80 mm. | S67: Rever o PU ou justificar o que inclui. | T67: Orçamentista | U67: NOVO | V67: MANTIDO | W67: Confirmados os textos (apenas painel TECH Slab 3.0 40 mm) e os valores (76 + 42 = 118 m² a 54,05 €; 3.4.3 a 10,66 €). As mesmas áreas (76 e 42 m²) estão no 3.8.5 e no 3.10.2, o que confirma que o acabamento é pago à parte. Cálculo correto (ambos negativos, min ≤ max). | X67: Pendente
A68: 64 | B68: 3 | C68: 3.9.1.2 | D68: 3.9.1.2.1; 3.9.1.2.2; 3.9.2.5; 3.3.4 | E68: PAV I 02 – Betão armado tipo SECIL UNIPISO (10 cm) | F68: INCOERÊNCIA | G68: MÉDIA | H68: Unipiso interior 10 cm mais caro que exterior 12 cm com brita | I68: 3.9.1.2.1 | m2 | 280 | 35,00 € | 9 800,00 €; 3.9.1.2.2 | m2 | 339 | 35,00 € | 11 865,00 € (Unipiso 10 cm + betão leve). 3.9.2.5 | m2 | 1 086 | 34,13 € (Unipiso 12 cm + brita 20 cm + manta). | N68: O sistema exterior (12 cm + caixa de brita 20 cm + manta) deve ser mais caro do que o interior (10 cm + betão leve), com uma referência de 39–46 €/m². | O68: 0 | P68: 0 | Q68: =AVERAGE(O68:P68) -> 0 | R68: Incoerência entre PU confirmada. A correção recai sobre o PU exterior e está quantificada no achado 3.9.2.5, para não contar o impacto duas vezes. | S68: Rever em conjunto os PU de 3.9.1.2 e 3.9.2.5, decompondo betão, malha, acabamento e camadas. | T68: Orçamentista | U68: EXISTENTE | V68: MANTIDO | W68: Valores confirmados nas três linhas. O interior de 10 cm (com betão leve) a 35,00 € contra o exterior de 12 cm (com brita e manta) a 34,13 € é incoerente. Impacto a 0 € para não duplicar. | X68: Pendente
A69: 65 | B69: 3 | C69: 3.9.2.5 | D69: 3.9.1.2; 3.3.4 | E69: PAV E 01 – Unipiso 12 cm s/ caixa de brita 20 cm e manta | F69: PREÇO BAIXO | G69: MÉDIA | H69: Unipiso 12 cm com brita e manta a 34,13 €/m2 | I69: 3.9.2.5 | m2 | 1 086 | 34,13 € | 37 070,00 € (Qtd × PU visível = 37 065,18 €). | J69: 1086 | K69: m2 | L69: 34.13 | M69: 37070 | N69: 39–46 €/m²: betão 12 cm com malha e acabamento afagado ≈27–31 €, caixa de brita 20 cm ≈5–8 € e manta separadora ≈1,5–2 €. | O69: 5288.82 | P69: 12890.82 | Q69: =AVERAGE(O69:P69) -> 9089.82 | R69: (39−34,13)×1 086 = 5 288,82 €; (46−34,13)×1 086 = 12 890,82 €. O PU é inferior ao do Unipiso interior de 10 cm (35 €) e ao do 3.3.4 (70,13 € com impermeabilização e XPS). | S69: Rever o PU com uma decomposição por camadas. | T69: Orçamentista | U69: EXISTENTE | V69: CORRIGIDO | W69: Qtd, PU e total de custo confirmados (37 070,00 €). O cálculo de impacto usava 39,13 € e 46,13 € em vez do intervalo de referência declarado (39–46 €/m²). Recalculado: (39−34,13)×1 086 = 5 288,82 € e (46−34,13)×1 086 = 12 890,82 €. | X69: Pendente
A70: 66 | B70: 3 | C70: 3.9.2.6 | D70: 3.9.2.7 | E70: GUIA E 01 (chapa corten 10 mm, h=20 cm) | F70: PREÇO BAIXO | G70: MÉDIA | H70: Guia corten 10 mm a 46,44 €/ml; caldeira igual a 75 €/ml | I70: 3.9.2.6 | ml | 210 | 46,44 € | 9 752,40 €. O 3.9.2.7 (caldeira com a mesma chapa corten de 10 mm, h=20 cm e fundação incluída) custa 75,00 €/ml. | J70: 210 | K70: ml | L70: 46.44 | M70: 9752.4 | N70: 65–80 €/ml: chapa de 15,7 kg/ml × ≈3 €/kg transformada ≈47 €, mais fundação ≈9 € e montagem ≈10 €. | O70: 3897.6 | P70: 7047.6 | Q70: =AVERAGE(O70:P70) -> 5472.6 | R70: 0,010×0,20×7 850 = 15,7 kg/ml. Só o aço transformado já esgota o PU. (65−46,44)×210 = 3 897,60 €; (80−46,44)×210 = 7 047,60 €. | S70: Rever o PU e harmonizá-lo com o 3.9.2.7. | T70: Orçamentista | U70: NOVO | V70: MANTIDO | W70: Textos do 3.9.2.6 e do 3.9.2.7 confirmados como equivalentes (corten 10 mm, h 20 cm, fundação incluída), a 46,44 € e 75,00 €. Peso de 15,7 kg/ml e cálculos corretos. | X70: Pendente
A71: 67 | B71: 3 | C71: 3.9.2.8 | D71: 3.15.9 (OMISSÃO); 3.17 (OMISSÃO); 3.1.3.1 | E71: PAV E 02 – Pavimento desportivo betuminoso c/ Sikafloor Colorsport | F71: FALHA/OMISSÃO | G71: MÉDIA | H71: Campo exterior de 2 538 m2 sem marcações nem equipamento | I71: 3.9.2.8 | m2 | 2 538 | 50,18 € | 127 363,19 €. Texto: base e desgaste betuminosos com agregado calcário, resina Sikafloor Colorsport e caixa de brita 20 cm. Sem linhas de jogo nem equipamento. | J71: 2538 | K71: m2 | L71: 50.18 | M71: 127363.19 | N71: Campo desportivo com marcações (NP EN 14877 / regulamentos federativos) e balizas e tabelas conformes com o DL 100/2003. | O71: 0 | P71: 0 | Q71: =AVERAGE(O71:P71) -> 0 | R71: Omissão confirmada. O impacto está quantificado nos achados 3.15.9 (OMISSÃO), para as marcações, e 3.17 (OMISSÃO), para o equipamento, e aqui fica a 0 € para não contar duas vezes. | S71: Acrescentar marcações e equipamento do campo exterior (ver achados relacionados). | T71: Projetista | U71: EXISTENTE | V71: MANTIDO | W71: Valores confirmados (custo de 127 363,19 €). Pesquisa em todo o MQT: 'marcaç' só aparece no 3.15.9 (interior), e 'baliza', 'tabela' e 'basquet' não dão resultados. Impacto a 0 € correto para evitar dupla contagem. | X71: Pendente
A72: 68 | B72: 3 | C72: 3.9.2.11 | D72: 3.9.2.4; 3.9.2.13 | E72: PAV E 05 (elementos pré-fabricados em betão armado ou GRC) | F72: PREÇO BAIXO | G72: MÉDIA | H72: Peças GRC por medida a 35 €/m2, quase o preço de lajeta | I72: 3.9.2.11 | m2 | 210 | 35,00 € | 7 350,00 €. Texto: «elementos préfabricados de dimensões variadas de betão armado ou reforçado com fibras GRC ... Não se considera possível a sua pré-fabricação em obra». A lajeta corrente 60x40 custa 30,50 € (3.9.2.4). | J72: 210 | K72: m2 | L72: 35 | M72: 7350 | N72: 60–90 €/m² para peças pré-fabricadas por medida em betão armado ou GRC, assentes. | O72: 5250 | P72: 11550 | Q72: =AVERAGE(O72:P72) -> 8400 | R72: (60−35)×210 = 5 250 €; (90−35)×210 = 11 550 €. Peças por medida em GRC não podem custar quase o mesmo que lajetas de série. | S72: Rever o PU e definir as dimensões e espessuras das peças. | T72: Orçamentista | U72: NOVO | V72: MANTIDO | W72: Texto e valores confirmados (210 m² × 35 € = 7 350 €; 3.9.2.4 a 30,50 €). Cálculo correto. Intervalo de mercado plausível. | X72: Pendente
A73: 69 | B73: 3 | C73: 3.10.5 | D73: 3.5.1; 3.6.1.1; 3.6.1.2 | E73: TETOS EXT. EM CHAPA ONDULADA | F73: DESCRIÇÃO | G73: MÉDIA | H73: Teto exterior junta chapa, subestrutura e painel; PU é soma exata | I73: 3.10.5 | m2 | 105 | 93,32 € | 9 798,54 €. Texto: «Fornecimento de teto em fachada de alumínio ondulada ... sub-estrutura ... em paredes exteriores ... painel sandwich em fachada». 93,32 = 25,44 (3.6.1.1) + 12,50 (3.6.1.2) + 55,38 (3.5.1). | J73: 105 | K73: m2 | L73: 93.32 | M73: 9798.54 | N73: Descrição própria de teto exterior (soffit), sem remissões a 'fachada' e 'paredes', e garantia de que estas áreas não estão também medidas em 3.5.1 e 3.6.1. | O73: 0 | P73: -9798.54 | Q73: =AVERAGE(O73:P73) -> -4899.27 | R73: O PU é exatamente a soma dos três artigos de fachada, o que prova que o artigo é uma composição dos mesmos trabalhos. Se os 105 m² também estiverem nas medições de fachada (1 309 m² e 1 550 m²), há duplicação até −9 798,54 €. | S73: Reescrever a descrição e confirmar nas medições que as áreas não se sobrepõem. | T73: Projetista | U73: EXISTENTE | V73: MANTIDO | W73: Confirmado: 25,44 + 12,50 + 55,38 = 93,32 €. O texto copia as descrições de fachada («paredes exteriores», «painel sandwich em fachada»). Total de 9 798,54 € (custo) confirmado. O intervalo até 0 € reconhece que a duplicação não está provada. | X73: Pendente
A74: 70 | B74: 3 | C74: 3.11.2.9.1 | D74: 3.11.2.8; 3.11.2.7 | E74: VE.2.03 com 5,33x2,40 (3 folhas fixas) | F74: INCOERÊNCIA | G74: MÉDIA | H74: Vão só com fixos mais caro que vãos iguais com basculante | I74: 3.11.2.9.1 VE.2.03 (3 folhas fixas, mesmo vidro) | UN | 3 | 7 024,85 € | 21 074,55 €. 3.11.2.8 VE.2.02 (3 fixas + 1 basculante) | 5 547,92 €. 3.11.2.7 VE.2.01 (correr elevável + fixa + basculante) | 6 007,90 €. Todos com 5,33x2,40. | J74: 3 | K74: UN | L74: 7024.85 | M74: 21074.55 | N74: Um vão só com folhas fixas não deve custar mais do que vãos iguais com folhas móveis. Referência: ≤5 547,92 € (VE.2.02). | O74: 0 | P74: -4430.79 | Q74: =AVERAGE(O74:P74) -> -2215.395 | R74: (5 547,92−7 024,85)×3 = −4 430,79 €. VE.2.03 sai a 549 €/m², contra 434 €/m² do VE.2.02, que tem mais funcionalidade e o mesmo vidro. | S74: Rever a composição de preço do VE.2.03. | T74: Orçamentista | U74: NOVO | V74: MANTIDO | W74: Confirmado: mesmo vidro (SunGuard SN 70S HT 8 + 12 mm + 66.4), mesma série 15200 e mesma dimensão. 7 024,85/12,792 = 549,2 €/m²; 5 547,92/12,792 = 433,7 €/m². Cálculo de −4 430,79 € correto. | X74: Pendente
A75: 71 | B75: 3 | C75: 3.11.2.18 | D75: 3.11.2.18.1; 3.11.2.18.2; 3.11.2.13 | E75: Porta CF metálica 2 folhas TRIA SISAF ES2 | F75: NORMA | G75: MÉDIA | H75: Porta CF de 2 folhas sem classe EI/C nem seletor | I75: 3.11.2.18.1 VI.CF.1.01 | UN | 1 | 2 297,60 €; 3.11.2.18.2 VI.CF.1.06 | UN | 1 | 2 302,40 €. Texto: «porta CF metálica de 2 folhas ... Folha lateral com contrafechadura ... mola embutida». Sem classe de resistência e sem seletor de fecho (a porta não CF 3.11.2.13 tem «selector de fecho»). | N75: Classe EI 30/EI 60 com 'C' (fecho automático), conforme o RT-SCIE (Portaria 1532/2008) e o projeto SCIE. Seletor ou coordenador de fecho EN 1158, obrigatório em portas CF de 2 folhas com batente sobreposto. | O75: 200 | P75: 500 | Q75: =AVERAGE(O75:P75) -> 350 | R75: Sem classe não é verificável a conformidade com o projeto SCIE. Sem coordenador de fecho, a folha ativa pode fechar antes da passiva e a porta deixa de garantir a compartimentação. Seletor ≈100–250 €/porta × 2 portas. | S75: Indicar a classe (EI xx C) por vão e acrescentar o seletor de fecho EN 1158. | T75: Projetista | U75: EXISTENTE | V75: MANTIDO | W75: Texto e valores confirmados (2 297,60 € e 2 302,40 €). Não há referência à classe EI nem ao seletor. O 3.11.2.13 tem «selector de fecho». Pesquisa por 'seletor' em todo o MQT sem resultados. O impacto de 200–500 € é plausível. | X75: Pendente
A76: 72 | B76: 3 | C76: 3.11.2.20 | E76: VI.CF.2.01 – Caixilharia CF TRIA FogoFil E30 | F76: NORMA | G76: MÉDIA | H76: Envidraçado E30 onde a compartimentação exige normalmente EI | I76: 3.11.2.20 | UN | 2 | 3 232,80 € | 6 465,60 €. Texto: «classificação de resistência ao fogo E30 (PYROGUARD-FIRESAFE-T-E30-8mm)». | J76: 2 | K76: UN | L76: 3232.8 | M76: 6465.6 | N76: Envidraçados integrados em paredes de compartimentação ou de proteção de vias exigem em regra classe EI (EI 30/EI 60) segundo o RT-SCIE (Portaria 1532/2008). A classe E só é aceitável onde o projeto SCIE o admita. | O76: 0 | P76: 6264 | Q76: =AVERAGE(O76:P76) -> 3132 | R76: Área: 1,45×2,40×2 = 6,96 m². O sobrecusto de vidro e caixilho EI face a E é ≈600–900 €/m², ou seja ≈4 176–6 264 €. Impacto 0 € se o projeto SCIE admitir E30. | S76: Confirmar a classe no projeto SCIE e, se for EI, corrigir a especificação e o PU. | T76: Projetista | U76: EXISTENTE | V76: CORRIGIDO | W76: Texto E30 e valores (2 × 3 232,80 = 6 465,60 €) confirmados. O cálculo de área e de impacto está correto. Sem o projeto SCIE não se pode afirmar que haja não conformidade (o próprio achado admite 0 €), por isso a gravidade passa de ALTA para MÉDIA. | X76: Pendente
A77: 73 | B77: 3 | C77: 3.11.2.21 | D77: 3.11.2.21.1 | E77: Cortina CF TRIA Megafire (VI.CF.2.02) | F77: NORMA | G77: MÉDIA | H77: Cortina corta-fogo sem classe nem duração | I77: 3.11.2.21.1 VI.CF.2.02 3,60x2,40 | UN | 1 | 7 493,60 € | 7 493,60 €. Texto sem classificação (E/EW/EI) nem tempo. | N77: Classe e duração exigidas pelo projeto SCIE (ex.: E 60 / EW 60 / EI 60), conforme a EN 13501-2 e a EN 1634-1. | O77: 0 | P77: 0 | Q77: =AVERAGE(O77:P77) -> 0 | R77: Sem classe definida não é possível verificar a conformidade nem comparar propostas. Impacto não quantificável. | S77: Indicar a classe e a duração da cortina. | T77: Projetista | U77: EXISTENTE | V77: MANTIDO | W77: Texto do 3.11.2.21 verificado: refere acionamento automático ligado à central, mas nenhuma classe nem duração. Valor de 7 493,60 € confirmado. | X77: Pendente
A78: 74 | B78: 3 | C78: 3.12.4 | D78: 3.12.3 | E78: BANCO PARA VESTIÁRIOS | F78: ERRO | G78: MÉDIA | H78: Banco de vestiário com a descrição dos cacifos copiada | I78: 3.12.4 | ml | 52 | 144,00 € | 7 488,00 €. Texto: «Fornecimento e colocação de cacifos tipo Kemmlit modelo Ixos L à cor Branco, com 30x50x215cm» (igual ao 3.12.3). | J78: 52 | K78: ml | L78: 144 | M78: 7488 | N78: Descrição de banco de vestiário (estrutura, assento em HPL ou madeira, fixação, eventual cabideiro) medido em ml. | O78: 0 | P78: 0 | Q78: =AVERAGE(O78:P78) -> 0 | R78: O texto é idêntico ao do 3.12.3, mas a unidade (ml) e o PU são de banco. É um erro de texto e não é quantificável. | S78: Substituir a descrição pela do banco. | T78: Projetista | U78: EXISTENTE | V78: MANTIDO | W78: Confirmado em rows.json: o texto do 3.12.4 é o dos cacifos Kemmlit Ixos L, com 52 ml × 144 = 7 488 €. | X78: Pendente
A79: 75 | B79: 3 | C79: 3.13.1 | D79: 3.13.2; 3.13.3 | E79: GUARDA CORPOS TIPO GU 01 INT (malha inox Webnet) | F79: PREÇO BAIXO | G79: MÉDIA | H79: Guarda com malha inox Webnet custa só mais 5 €/ml | I79: 3.13.1 | ml | 122 | 150,00 € | 18 300,00 €; 3.13.2 | ml | 42 | 150,00 € | 6 300,00 € (tubos de 35 e 20 mm + malha inox Jakob Webnet tensionada). O 3.13.3, guarda de 1,10 m sem malha, custa 145,00 €/ml. | J79: 122 | K79: ml | L79: 150 | M79: 18300 | N79: 200–260 €/ml: só a malha inox tensionada custa ≈60–120 €/m², ou seja ≈66–130 €/ml para 1,10 m, e a estrutura ≈100–145 €/ml (o 3.13.3). | O79: 8200 | P79: 18040 | Q79: =AVERAGE(O79:P79) -> 13120 | R79: Pela comparação interna, a malha valeria apenas 5 €/ml. (200−150)×164 = 8 200 €; (260−150)×164 = 18 040 €. | S79: Rever o PU dos art. 3.13.1 e 3.13.2. | T79: Orçamentista | U79: NOVO | V79: MANTIDO | W79: Textos e valores confirmados (122 + 42 = 164 ml a 150 €; 3.13.3 com 21 ml a 145 €, sem malha). Cálculo correto. | X79: Pendente
A80: 76 | B80: 3 | C80: 3.13.4 | D80: 3.13.3; 3.13.5 | E80: CORRIMÃO EM ESCADAS GU 04 | F80: NORMA | G80: MÉDIA | H80: Corrimão de escada descrito como guarda de 1,10 m | I80: 3.13.4 | ml | 31 | 145,00 € | 4 495,00 €. Texto: «Fornecimento e aplicação de guarda corpos com 1,10m de altura» (igual ao 3.13.3). | J80: 31 | K80: ml | L80: 145 | M80: 4495 | N80: DL 163/2006, anexo, secção 2.4 (escadas): corrimãos em ambos os lados, contínuos, à altura de 0,85–0,90 m (medida no focinho do degrau), com prolongamento de 0,30 m. Corrimão simples ≈60–90 €/ml (o 3.13.5 do MQT custa 60 €). | O80: 0 | P80: -2635 | Q80: =AVERAGE(O80:P80) -> -1317.5 | R80: Descrição e PU de guarda num artigo de corrimão. Se for só corrimão: (60−145)×31 = −2 635 €. O valor mantém-se se for de facto uma guarda. | S80: Reescrever a descrição (altura 0,85–0,90 m, Ø, suportes, prolongamentos) e ajustar o PU. | T80: Projetista | U80: EXISTENTE | V80: CORRIGIDO | W80: Texto e valores confirmados (31 × 145 = 4 495 €; cálculo de −2 635 € correto). Problema real. A citação exata dos números 2.4.8/2.4.9 não é verificável nos dados e foi generalizada para «secção 2.4 (escadas)» do anexo ao DL 163/2006, para evitar uma referência errada. | X80: Pendente
A81: 77 | B81: 3 | C81: 3.13.5 | D81: 3.13.4 | E81: CORRIMÃO EM RAMPAS GU 05 | F81: INCOERÊNCIA | G81: MÉDIA | H81: Texto igual ao 3.13.4, mas a 60 €/ml contra 145 €/ml | I81: 3.13.5 | ml | 86 | 60,00 € | 5 160,00 €, com o texto da guarda de 1,10 m. O 3.13.4 tem o mesmo texto a 145,00 €/ml. | J81: 86 | K81: ml | L81: 60 | M81: 5160 | N81: Corrimão de rampa conforme a secção 2.5 do DL 163/2006 (ambos os lados e, quando aplicável, corrimão duplo), com descrição própria e PU coerente. | O81: 0 | P81: 7310 | Q81: =AVERAGE(O81:P81) -> 3655 | R81: Se o artigo for de facto a guarda descrita: (145−60)×86 = 7 310 €. Se for corrimão simples, o PU de 60 € é plausível e só há que corrigir o texto. | S81: Corrigir a descrição e harmonizar o PU com o 3.13.4. | T81: Projetista | U81: EXISTENTE | V81: MANTIDO | W81: Os textos do 3.13.4 e do 3.13.5 são idênticos e os PU são 145 € e 60 €. 86 × 60 = 5 160 € e (145−60)×86 = 7 310 € estão corretos. | X81: Pendente
A82: 78 | B82: 3 | C82: 3.13.8 | D82: 3.1.5; 3.1.6; 3.13.9 | E82: VEDAÇÃO EXISTENTE - CONSOLIDAÇÃO REFORÇO | F82: VERIFICAR | G82: MÉDIA | H82: Nova fundação da vedação reaplicada pode não estar orçada | I82: 3.1.5 | ml | 220 | 9,00 € (desmontagem «incluindo a demolição das fundações existentes que se encontrem degradadas»). 3.1.6 refere «trabalhos de consolidação da fundação da vedação existente». 3.13.8 | ml | 220 | 25,00 € | 5 500,00 € (vedação «devidamente consolidada e reforçada»). Só a vedação nova VED 01 (3.13.9, 20 ml) inclui lintel. | J82: 220 | K82: ml | L82: 25 | M82: 5500 | N82: Lintel ou fundação nova em betão armado para os troços demolidos, a ≈30–40 €/ml, explícito na descrição do 3.13.8 ou num artigo próprio. | O82: 0 | P82: 8800 | Q82: =AVERAGE(O82:P82) -> 4400 | R82: O 3.1.5 demole as fundações degradadas e nenhum artigo refere expressamente a nova fundação. A expressão «consolidada e reforçada» do 3.13.8 pode abranger a consolidação da fundação referida no 3.1.6, mas o PU de 25 €/ml dificilmente a cobre além da reaplicação e da pintura. Máximo: 220×40 = 8 800 €; mínimo de 0 € se as fundações estiverem em bom estado ou se o 3.13.8 já as incluir. | S82: Clarificar se o 3.13.8 inclui a fundação ou lintel dos troços demolidos ou criar um artigo próprio, estimando a extensão. | T82: Projetista | U82: NOVO | V82: CORRIGIDO | W82: Textos e valores confirmados (3.1.5 com 220 ml a 9 €; 3.1.6 com 208 m² a 30 €; 3.13.8 com 220 ml a 25 €; 3.13.9 com lintel). A omissão não está provada, porque «consolidada e reforçada» pode incluir a fundação. Tipo passa de FALHA/OMISSÃO para VERIFICAR e o título e a fundamentação foram ajustados. O intervalo 0–8 800 € mantém-se. | X82: Pendente
A83: 79 | B83: 3 | C83: 3.16.1.14 | D83: 3.16.1.14.1; 3.16.1.14.2 | E83: KIT MOB. CONDICIONADA | F83: PREÇO BAIXO | G83: MÉDIA | H83: Kit de barras de apoio a 62,10 €/conjunto | I83: 3.16.1.14.1 | UN | 6 | 62,10 € | 372,60 €; 3.16.1.14.2 | UN | 4 | 62,10 € | 248,40 €. | N83: Um conjunto conforme o DL 163/2006 (secção 2.9: barra rebatível + barra fixa na sanita; barras horizontal e vertical no duche) em inox tipo JNF custa 250–500 €. | O83: 1879 | P83: 4379 | Q83: =AVERAGE(O83:P83) -> 3129 | R83: (250−62,10)×10 = 1 879 €; (500−62,10)×10 = 4 379 €. O PU atual corresponde a uma só barra simples. | S83: Detalhar a composição do kit por local e rever o PU. | T83: Orçamentista | U83: EXISTENTE | V83: MANTIDO | W83: Valores confirmados (6 + 4 UN a 62,10 €; título «KIT» com «barras de apoio» no plural). Cálculo correto. Mesmo que a UN seja uma barra, o kit por local fica subavaliado. | X83: Pendente
A84: 80 | B84: 3 | C84: 3.16.1.18 | D84: 5.3.7 | E84: DRENAGEM LINEAR EM BALNEÁRIOS | F84: DUPLICAÇÃO | G84: MÉDIA | H84: Drenagem linear dos balneários paga também em 5.3.7 | I84: 3.16.1.18 | ml | 28 | 269,61 € | 7 549,08 € (ACO 64 inox). 5.3.7 CANAL COM GRELHA CHUVEIROS | m | 25,6 | 220,00 € | 5 632,00 €. | J84: 28 | K84: ml | L84: 269.61 | M84: 7549.08 | N84: Um só artigo para a drenagem de pavimento dos duches, com o material definido (inox em arquitetura, ferro fundido em 5.3.7). | O84: -5632 | P84: -7549.08 | Q84: =AVERAGE(O84:P84) -> -6590.54 | R84: Mesma função e comprimentos semelhantes (28 vs 25,6 m). Anular o 5.3.7 dá −5 632 €; anular o 3.16.1.18 dá −7 549,08 €. | S84: Eliminar um dos artigos e uniformizar o material. | T84: Projetista | U84: EXISTENTE | V84: MANTIDO | W84: Valores confirmados. O 5.3.7 chama-se «CANAL COM GRELHA CHUVEIROS» (ferro fundido, com sifão) e o 3.16.1.18 é drenagem linear ACO 64 inox nos balneários. Mesma função e comprimentos próximos. O 6.2.16 (ACO 64 inox, 87,4 m) é de águas pluviais e não entra nesta duplicação. [Consolidação: intervalo = retirar 5.3.7 (5.632,00 €) ou 3.16.1.18 (7.549,08 €).] | X84: Pendente
A85: 81 | B85: 3 | C85: 3.17.1 | D85: 3.17.9 | E85: BANCO PRÉBRICADO EM BETÃO | F85: DESCRIÇÃO | G85: MÉDIA | H85: Banco pré-fabricado de 38,9 k€ sem qualquer especificação técnica | I85: 3.17.1 | ml | 187 | 208,26 € | 38 943,75 €. Texto completo: «BANCO PRÉBRICADO EM BETÃO / Incluí: Todos os trabalhos e materiais necessários ... caderno de encargos.» Sem secção, dimensões, classe de betão, acabamento, armadura nem fixação. Também o 3.17.9 (CONSOLIDAÇÃO E REPOSIÇÃO DE GRELHA DE DRENAGEM, 65 ml × 50 € = 3 250 €) só tem o título. | J85: 187 | K85: ml | L85: 208.26 | M85: 38943.75 | N85: Descrição mínima: secção e comprimento das peças, betão e armadura (ou GRC), acabamento e tratamento de superfície, assentamento e fundação, juntas e remates, referência ao desenho de pormenor. | O85: 0 | P85: 0 | Q85: =AVERAGE(O85:P85) -> 0 | R85: Um artigo de 38 943,75 € (2,5 % do cap. 3) sem qualquer especificação não permite comparar propostas nem controlar a execução. Por 208,26 €/ml, a variação entre um banco simples e uma peça por medida com acabamento especial é grande, mas não é quantificável sem desenho. | S85: Completar a descrição do 3.17.1 (e do 3.17.9) com a especificação técnica e a remissão para o pormenor. | T85: Projetista | U85: NOVO | V85: MANTIDO | W85: Texto integral do 3.17.1 e do 3.17.9 lido em rows.json: só têm o título e a cláusula genérica 'Incluí'. Valores confirmados (187 ml × 208,26 € com custo de 38 943,75 € e 38 944,62 € pelo valor visível; 65 × 50 = 3 250 €). | X85: Pendente
A86: 82 | B86: 3 | C86: 3.17.7 | D86: 3.17.7.1 | E86: CORTINAS ÁREA DE JOGO | F86: PREÇO BAIXO | G86: MÉDIA | H86: Cortina divisória (PVC 4 m + rede) a 80 €/ml | I86: 3.17.7.1 | ml | 90 | 80,00 € | 7 200,00 €. Inclui tela PVC até 4 m, rede até à asna, sistema de correr e suspensão e planificação. | N86: 140–220 €/ml: ≈7 m² de tela e rede por ml (≈75–120 €), mais calha e suspensão (≈30–50 €) e montagem. | O86: 5400 | P86: 12600 | Q86: =AVERAGE(O86:P86) -> 9000 | R86: (140−80)×90 = 5 400 €; (220−80)×90 = 12 600 €. Só os materiais por ml excedem o PU. | S86: Rever o PU e definir se o acionamento é manual ou motorizado. | T86: Orçamentista | U86: NOVO | V86: MANTIDO | W86: Texto e valores confirmados (90 ml × 80 € = 7 200 €). Cálculo correto. Referência plausível para cortina divisória de pavilhão. | X86: Pendente
A87: 83 | B87: 4 | C87: 4.1.3 | D87: 5.1.3; 6.1.3; 2.1.3 | E87: ENCHIMENTO DE VALA | F87: PREÇO BAIXO | G87: MÉDIA | H87: Enchimento de valas com cirandagem a 5,50 €/m3, abaixo do aterro 2.1.3 | I87: 4.1.3: 30,61 m3 × 5,50 = 168,36 €; 5.1.3: 394,50 m3 × 5,50 = 2.169,75 €; 6.1.3: 537,682 m3 × 5,50 = 2.957,25 €. Total 962,792 m3 a 5,50 €/m3, 'incluindo cirandagem de terras para o envolvimento das tubagens e compactação'. | J87: 30.61 | K87: m3 | L87: 5.5 | M87: 168.36 | N87: No próprio MQT, 2.1.3 (aterro e compactação de terras, sem cirandagem) = 7,50 €/m3. Mercado para aterro de vala por camadas com cirandagem: 8–12 €/m3. | O87: 1925.58 | P87: 6258.15 | Q87: =AVERAGE(O87:P87) -> 4091.865 | R87: (7,50 − 5,50) × 962,792 = 1.925,58 €; (12 − 5,50) × 962,792 = 6.258,15 €. Um trabalho com cirandagem não pode custar menos do que o aterro simples do cap. 2. | S87: Rever o PU dos três artigos de enchimento (≥ 7,50 €/m3). | T87: Orçamentista | U87: NOVO | V87: CORRIGIDO | W87: Confirmei as três quantidades e totais e o 2.1.3 a 7,50 €/m3 ('aterro e compactação ... sendo ou não provenientes da escavação'). A soma é 962,792 m3. Corrigi o impacto máximo de 6.258,14 € para 6.258,15 € (6,5 × 962,792 = 6.258,148). A comparação interna sustenta o achado, embora 5,50 €/m3 esteja só no limite inferior do mercado. | X87: Pendente
A88: 84 | B88: 4 | C88: 4.2.2.8 | D88: 4.2.1.7; 4.2.2.7; 4.2.7.3 | E88: TUBAGEM EM MULTICAMADA PARA ÁGUA FRIA SUSPENSA – DN 90 | F88: VERIFICAR | G88: MÉDIA | H88: Multicamada DN90 a 178,38 €/m em 76,76 m: material pouco económico | I88: 4.2.2.8: 72,98 m × 178,38 €/m = 13.018,17 €; 4.2.1.7 (embutida): 3,78 m × 178,38 €/m = 674,28 €. Total DN90 = 76,76 m / 13.692,45 € (28% do subcap. 4.2, que soma 48.659,68 €). Salto de DN75 para DN90: 104,85 → 178,38 €/m (+70%). | J88: 72.98 | K88: m | L88: 178.38 | M88: 13018.17 | N88: Num coletor de água fria DN90 à vista, PP-R PN16/20 custa cerca de 60–90 €/m instalado. O inox prensado de 88,9 mm é mais caro (≈ 100–150 €/m) e pouco serve de alternativa económica. A multicamada DN90 (acessórios de grande diâmetro) explica o PU, mas não justifica a escolha. Referência interna, só indicativa por ser enterrada: PEAD DN90 (4.2.7.3) = 30,18 €/m. | O88: 0 | P88: -6784.05 | Q88: =AVERAGE(O88:P88) -> -3392.025 | R88: Cenário de troca para PP-R a 90 €/m: (90 − 178,38) × 76,76 = −6.784,05 €. Embutir tubo DN90 em roço (4.2.1.7, 'abertura e tapamento de roço') também é tecnicamente difícil em paredes correntes. | S88: O projetista deve confirmar o material e o diâmetro dos troços DN75–DN90 (alternativa PP-R) e eliminar a hipótese de DN90 embutida. | T88: Projetista | U88: EXISTENTE | V88: CORRIGIDO | W88: Todos os valores conferem com o dump (linhas 894 e 912). A soma de 4.2 é 48.659,68 € e o DN90 pesa 28,1%. 104,85 → 178,38 corresponde a +70,1%. Corrigi a referência: o inox prensado DN 88,9 não fica em 60–90 €/m instalado, por isso a alternativa económica é o PP-R. Ajustei o impacto máximo ao cêntimo (−6.784,05 €). O achado é de engenharia de valor (VERIFICAR) e não um erro comprovado. | X88: Pendente
A89: 85 | B89: 4 | C89: 4.3.10 | D89: 4.5.2; 4.2.7.1; cap. 13 | E89: CONTADOR REDE DE REGA | F89: INCOERÊNCIA | G89: MÉDIA | H89: Contador e ramal de rega sem rede de rega no MQT | I89: 4.3.10 Contador rede de rega: 1 UN × 900 €. 4.5.2 Ligação à rede de rega: 1 UN × 700 €. Total 1.600 €. O cap. 13 (Arquitetura Paisagista, 65.465 €) tem 3.190 m2 de prados (13.5), 80 árvores e cerca de 2.100 arbustos/trepadeiras, mas nenhum aspersor, gotejador, programador ou tubagem de rega (pesquisa 'rega' só devolve 4.3.10, 4.5.2 e textos de plantação). | J89: 1 | K89: UN | L89: 900 | M89: 900 | N89: Se há rega, é preciso medir a rede (gota-a-gota nas árvores/arbustos e aspersão nos prados): cerca de 3,5 €/m2 × 3.552 m2 (13.1.4) ≈ 12.400 €. Se não há rega, os artigos 4.3.10 e 4.5.2 sobram. | O89: 0 | P89: 0 | Q89: =AVERAGE(O89:P89) -> 0 | R89: O contador e o ramal de rega não servem nenhuma rede medida. 3,5 €/m2 × 3.552 m2 = 12.432 €. | S89: O Dono de Obra e o projetista de paisagismo devem decidir se há rega. Se sim, medir a rede de rega no cap. 13; se não, eliminar 4.3.10 e 4.5.2. | T89: Projetista | U89: NOVO | V89: MANTIDO | W89: Confirmei os valores 900 + 700 = 1.600 €. Cap. 13 = 65.465 €; prados 622 + 2.568 = 3.190 m2; árvores 15 + 15 + 1 + 10 + 5 + 13 + 7 + 14 = 80; arbustos e trepadeiras = 2.137; 13.1.4 = 3.552 m2. A pesquisa de 'aspers', 'gota' e 'programador' não devolve nada. 'rega' só aparece em 4.3.10, 4.5.2, 'primeira rega' (13.3.x) e 13.6.3 (drenos de cova 'para ... água de rega'), além de falsos positivos ('entrega'). A omissão é real e o sinal do impacto está coerente (−1.600 a +12.432 €). [Consolidação: impacto contabilizado em 13 (OMISSÃO) – rede de rega para não contar duas vezes.] | X89: Pendente
A90: 86 | B90: 4 | C90: 4.3.11 | D90: 4.2.6; 4.3.12; 4.3.15; 4.3.5; 4.3.6 | E90: CARRETEL | F90: VERIFICAR | G90: MÉDIA | H90: 10 carretéis sem reservatório nem grupo sobrepressor no MQT | I90: 4.3.11: 10 UN × 499,90 € = 4.999,00 €. RIA em aço galvanizado (4.2.6: 212,05 m, DN50–DN100) alimentada pelo contador próprio 4.3.15 (3.250,00 €). Não há qualquer artigo de reservatório de incêndio ou central de bombagem (pesquisa de 'reservat'/'sobrepress' sem resultados úteis). | J90: 10 | K90: UN | L90: 499.9 | M90: 4999 | N90: RT-SCIE (Portaria 1532/2008, na redação da Portaria 135/2020), art.os 164.º–165.º: a RIA de carretéis tem de garantir, no carretel mais desfavorável, pressão dinâmica ≥ 250 kPa e 1,5 l/s, com metade dos carretéis (máx. 4) em simultâneo. Se a rede pública não o garantir, é obrigatório um reservatório privativo com grupo sobrepressor (NP EN 12845). | O90: 0 | P90: 30000 | Q90: =AVERAGE(O90:P90) -> 15000 | R90: Os artigos 4.3.5 e 4.3.6 falam de 'reservatório', o que sugere que o projeto chegou a prevê-lo. Se a declaração de pressão/caudal da entidade gestora for insuficiente, um reservatório de 10–20 m3 com eletrobomba, jockey e quadro custa cerca de 20.000–30.000 €. | S90: Pedir à entidade gestora a declaração de pressão e caudal disponíveis. Se forem insuficientes, medir o reservatório e o grupo sobrepressor de incêndio. | T90: Projetista | U90: EXISTENTE | V90: MANTIDO | W90: Confirmei 4.3.11 (10 × 499,90 = 4.999 €), 4.2.6 (70,98 + 75,6 + 34,44 + 31,03 = 212,05 m, DN50–100) e 4.3.15 (3.250 €). Pesquisei o MQT completo: 'sobrepress' e 'hidropress' sem ocorrências, 'bombag' só nos desvios provisórios 5.4.2/5.4.3/6.3.2/6.3.3, 'reservat' só em 4.3.5/4.3.6. Ligar a RIA diretamente à rede pública é admissível se a pressão e o caudal chegarem, por isso o achado é condicional (VERIFICAR, mínimo 0 €), o que está corretamente refletido. | X90: Pendente
A91: 87 | B91: 4 | C91: 4.5.1 | D91: 4.5.1.1; 4.5.2; 4.3.9; 4.3.15; 4.3.16 | E91: LIGAÇÃO À REDE PÚBLICA – DN 110 | F91: PREÇO BAIXO | G91: MÉDIA | H91: Ramal DN110 com reposição de pavimentos a 750 €/un, sem taxas | I91: 4.5.1.1 DN110: 3 UN × 750,00 € = 2.250,00 €. Inclui tubagem PEAD, levantamento e reposição de pavimentos, vala e transporte a vazadouro. Não refere taxas nem orçamento da entidade gestora. | N91: Ramal DN110 em via pública com reposição de pavimento: 1.500–3.000 €/un. A estes valores juntam-se as tarifas de ligação da entidade gestora, que em muitos municípios executa ela própria o ramal. | O91: 2250 | P91: 6750 | Q91: =AVERAGE(O91:P91) -> 4500 | R91: (1.500 − 750) × 3 = 2.250 €; (3.000 − 750) × 3 = 6.750 €. | S91: Obter o orçamento ou tarifário da entidade gestora para os 3 ramais e ajustar o PU, ou passar as taxas para encargo do Dono de Obra. | T91: Orçamentista | U91: EXISTENTE | V91: MANTIDO | W91: Confirmei 3 × 750 = 2.250 € e que o texto inclui pavimentos, vala e vazadouro, sem taxas. Os 3 ramais correspondem aos 3 contadores (4.3.9, 4.3.15 e 4.3.16). Os cálculos estão certos. A referência é plausível, embora dependa do comprimento dos ramais, que o MQT não indica. | X91: Pendente
A92: 88 | B92: 5 | C92: 5.1.1 | D92: 5.1.3; 2.1.2; 2.1.5 | E92: ESCAVAÇÃO | F92: PREÇO BAIXO | G92: MÉDIA | H92: Vala com escoramento a 5,50 €/m3; diz 'incluindo enchimento' pago à parte | I92: 5.1.1: 448,52 m3 × 5,50 €/m3 = 2.466,86 €. Texto: 'com recurso a escoramento incluindo enchimento incluindo baldeação ...'. 5.1.3 (enchimento de vala): 394,50 m3 × 5,50 = 2.169,75 €, medido à parte. | J92: 448.52 | K92: m3 | L92: 5.5 | M92: 2466.86 | N92: 12–18 €/m3 (no próprio MQT, 2.1.2 + 2.1.5 = 16,50 €/m3 sem escoramento). Retirar 'incluindo enchimento' de 5.1.1, porque o enchimento está em 5.1.3. | O92: 2915.38 | P92: 5606.5 | Q92: =AVERAGE(O92:P92) -> 4260.94 | R92: (12 − 5,50) × 448,52 = 2.915,38 €; (18 − 5,50) × 448,52 = 5.606,50 €. O texto cria ambiguidade de pagamento em duplicado com 5.1.3. | S92: Rever o PU e corrigir a descrição de 5.1.1. | T92: Orçamentista | U92: EXISTENTE | V92: MANTIDO | W92: Confirmei no dump (linha 1070) 448,52 × 5,50 = 2.466,86 €, o texto 'incluindo enchimento' e 5.1.3 (394,5 × 5,5 = 2.169,75 €). O cálculo está certo. Nota: a regularização 5.1.2 está a 46,66 €/m3 (66,61 m3), o que compensa em parte o PU baixo, mas não chega para o justificar. | X92: Pendente
A93: 89 | B93: 5 | C93: 5.2.2 | D93: 5.2.3; 6.2.1; 6.2.4; 6.2.15; 5.2.4 | E93: RAMAIS DE DESCARGA SUSPENSOS | F93: INCOMPATIBILIDADE | G93: MÉDIA | H93: Descrições copiadas de habitação: isolamento acústico ambíguo e não orçado | I93: 5.2.2, 5.2.3, 6.2.1 e 6.2.4: 'As tubagens suspensas nos pisos habitacionais e comércio/serviço deverão ser envolvidas ... em lã de rocha [e=30mm] ... folha de alumínio ... duas camadas de membrana ... TECSOUND SY50' (em 6.2.4 aparece 'RECSOUND'). O 6.2.15 (bocas de limpeza) exige o mesmo envolvimento sem condição. PU de 13,50 a 33,18 €/m, iguais aos dos ramais embutidos (5.2.1.3 DN75 = 13,50 €/m) e não suspensos. Comprimento suspenso total: 202,66 m (5.255,98 €). O 5.2.3 e o 6.2.4 atribuem 'pressão nominal de 6 bar' a tubo EN 1329; o 5.2.4 'SN4/PN6' a tubo EN 1401, ambos de drenagem sem pressão. | N93: Um pavilhão escolar não tem pisos habitacionais nem de comércio/serviço. Ou se retira a exigência, ou se diz onde se aplica e se orça: o envolvimento acústico (lã de rocha + 2 × TECSOUND) custa cerca de 15–25 €/m. | O93: 0 | P93: 5066.5 | Q93: =AVERAGE(O93:P93) -> 2533.25 | R93: Se o envolvimento for exigido: 25 €/m × 202,66 m = 5.066,50 € não incluídos nos PU atuais (o PU do suspenso é igual ao do embutido). Se não for, o custo não muda, mas o texto dá azo a reclamação. | S93: Rever as descrições: retirar a referência a habitação/comércio ou definir os troços com isolamento acústico e orçá-los. Corrigir 'RECSOUND' e a referência a PN em tubos de drenagem. | T93: Projetista | U93: NOVO | V93: CORRIGIDO | W93: Confirmei a frase 'pisos habitacionais e comércio/serviço' em 5.2.2, 5.2.3, 6.2.1 e 6.2.4. Corrigi o no_mqt, porque o 6.2.15 não tem essa frase: exige o envolvimento em lã de rocha + TECSOUND sem condição. Confirmei 'RECSOUND' em 6.2.4, '6 bar' em 5.2.3/6.2.4 e 'SN4/PN6' em 5.2.4. Comprimentos: 9,98 + 18,48 + 25,41 + 148,79 = 202,66 m; custo 5.255,98 €. As igualdades de PU com os embutidos também conferem (13,50 e 16,32). | X93: Pendente
A94: 90 | B94: 5 | C94: 5.3.6.1 | D94: 6.2.12.1; 6.2.12.2; 6.2.12.3 | E94: CÂMARA DE VISITA CIRCULAR – DN1,00; 1,40<h<2,50 | F94: PREÇO BAIXO | G94: MÉDIA | H94: CV DN1000 até 2,5 m com escavação e D400 a 520,82 € | I94: 5.3.6.1: 5 UN × 520,82 € = 2.604,11 €. Inclui escavação, transporte, juntas, degraus e tampa FFD D400. O 6.2.12.1 (DN1,00, 1,00<h<1,50, sem escavação) custa o mesmo, 520,82 €; o 6.2.12.2 (DN1,00, 1,50<h<2,50) custa 570,42 €. | J94: 5 | K94: UN | L94: 520.82 | M94: 2604.11 | N94: Mínimo coerente com o próprio MQT: 570,42 € (6.2.12.2) mais escavação. Mercado PT para CV DN1000 com h ≈ 2 m e tampa D400 instalada: 820–1.220 €/un. | O94: 1495.9 | P94: 3495.9 | Q94: =AVERAGE(O94:P94) -> 2495.9 | R94: (820 − 520,82) × 5 = 1.495,90 €; (1.220 − 520,82) × 5 = 3.495,90 €. Uma câmara mais alta, com escavação e D400, não pode custar o mesmo que uma de 1,0–1,5 m sem escavação. | S94: Rever o PU (≥ 820 €/un) e escalonar por altura, como em 6.2.12. | T94: Orçamentista | U94: EXISTENTE | V94: MANTIDO | W94: Confirmei 5 × 520,82 €, com o total de custo de 2.604,11 € no MQT (o de venda é 2.604,10 €). O texto de 5.3.6 inclui escavação, vazadouro e D400. O 6.2.12 não inclui escavação nem fixa a classe D400, e os PU (520,82 € e 570,42 €) conferem. As contas estão certas. | X94: Pendente
A95: 91 | B95: 6 | C95: 6.2.5.7 | D95: 6.2.5.4; 6.2.5.5; 6.2.5.6 | E95: COLETORES ENTERRADOS EM PVC – DN 400 | F95: INCOERÊNCIA | G95: MÉDIA | H95: PVC DN400 a 45,24 €/m, mais barato que DN315 (63,38 €/m) | I95: 6.2.5.7 DN400: 48,30 m × 45,24 €/m = 2.185,09 €. 6.2.5.6 DN315: 185,97 m × 63,38 €/m = 11.786,78 €; 6.2.5.5 DN250: 39,75 €/m; 6.2.5.4 DN200: 25,32 €/m. | J95: 48.3 | K95: m | L95: 45.24 | M95: 2185.09 | N95: A progressão do próprio artigo (+57% a +59% por escalão: 25,32 → 39,75 → 63,38) aponta para DN400 ≈ 101 €/m. O mínimo lógico é o PU do DN315 (63,38 €/m). | O95: 876.16 | P95: 2712.91 | Q95: =AVERAGE(O95:P95) -> 1794.535 | R95: (63,38 − 45,24) × 48,30 = 876,16 €; (63,38 × 1,6 − 45,24) × 48,30 = (101,408 − 45,24) × 48,30 = 2.712,91 €. | S95: Corrigir o PU do DN400 (≈ 90–100 €/m). | T95: Orçamentista | U95: EXISTENTE | V95: CORRIGIDO | W95: Confirmei todos os PU e totais. Os rácios são 39,75 / 25,32 = 1,570 e 63,38 / 39,75 = 1,594. Recalculado, o impacto máximo dá 2.712,91 € e não 2.712,90 € (diferença de arredondamento). A incoerência é real. | X95: Pendente
A96: 92 | B96: 6 | C96: 6.2.9 | D96: 6.2.9.1; 6.2.8.2; 2.6.5 | E96: GEODRENO BANCOS – DN 160 | F96: PREÇO BAIXO | G96: MÉDIA | H96: Geodreno bancos DN160 a 7,65 €/m com brita, vala e pavimentos | I96: 6.2.9.1 DN160: 78,75 m × 7,65 €/m = 602,44 €. A descrição é a mesma de 6.2.8. | N96: 20,32 €/m (2.6.5, sem vala) a 32 €/m (mercado com vala e reposição). | O96: 997.76 | P96: 1917.56 | Q96: =AVERAGE(O96:P96) -> 1457.66 | R96: (20,32 − 7,65) × 78,75 = 997,76 €; (32 − 7,65) × 78,75 = 1.917,56 €. O impacto anterior (2.794–4.913 €) implicaria 43–70 €/m, o que não é coerente com 78,75 m. | S96: Rever o PU, alinhado com 6.2.8 e 2.6.5. | T96: Orçamentista | U96: EXISTENTE | V96: MANTIDO | W96: Confirmei 78,75 × 7,65 = 602,44 € e que o texto é idêntico ao de 6.2.8. As contas de impacto estão certas. Com menos de 2 k€, a gravidade MÉDIA é aceitável. | X96: Pendente
A97: 93 | B97: 7 | C97: 7 (OMISSÃO) | D97: 7.8.3 | E97: Sonorização do pavilhão | F97: FALHA/OMISSÃO | G97: MÉDIA | H97: Pavilhão sem qualquer sistema de sonorização | I97: Nenhum artigo de amplificação, altifalantes ou microfones em todo o MQT. 7.8.3 'Audiovisuais Sala Multiusos' só tem tomadas HDMI/USB e cabos (470,12 €) | N97: Sonorização de pavilhão (amplificação 240–480 W, 8–16 projetores de som, microfones, mesa): ≈ 6.000–15.000 €. Requisito funcional habitual, não regulamentar | O97: 6000 | P97: 15000 | Q97: =AVERAGE(O97:P97) -> 10500 | R97: Pesquisa por sonorização, altifalante, amplificador e áudio sem resultados (só isolamento acústico em 3.8.3 e 3.10.1). | S97: O Dono de Obra deve decidir a inclusão. Se a incluir, pedir projeto e artigos. | T97: Dono de Obra | U97: EXISTENTE | V97: MANTIDO | W97: Pesquisa refeita: 'sonoriz', 'altifal', 'amplific', 'áudio' com 0 resultados; 'audio' só em 7.8.3. Total 7.8.3 = 80,74 + 80,74 + 56,54 + 252,10 = 470,12 € (correto). Decisão de âmbito do Dono de Obra; impacto plausível se incluído. | X97: Pendente
A98: 94 | B98: 7 | C98: 7.1.1 | D98: 7.1.2.1; 7.3.7.1; 11.15; 11.16; 11.17 | E98: Intervenção no QG Existente | F98: VERIFICAR | G98: MÉDIA | H98: Intervenção no QG existente em verba global de conteúdo indefinido | I98: 7.1.1 'Intervenção no QG Existente' UN 1 × 1.313,81 € = 1.313,81 €. Nova entrada 7.1.2.1 'XV(0,6-1kV) - R4x1x185+G95' 165 m × 167,12 € = 27.574,80 € | J98: 1 | K98: UN | L98: 1313.81 | M98: 1313.81 | N98: Uma saída 4×185 mm² Cu (Iz ≈ 300 A) obriga a instalar no QG existente um disjuntor de caixa moldada de 250–315 A, a fazer a adaptação do barramento e a verificar a potência disponível. Valor de referência: ≈ 1.500–3.300 €. O eventual aumento da potência requisitada (E-Redes) é encargo do Dono de Obra e não está orçamentado | O98: 0 | P98: 1986.19 | Q98: =AVERAGE(O98:P98) -> 993.095 | R98: O artigo não diz o que inclui. O PU 1.313,81 € aparece igual em 7.3.7.1 (melhoria da rede de terra) e em 11.15/11.16/11.17 (AVAC), o que mostra um valor de verba e não uma estimativa. A potência do novo pavilhão (AVAC QEAC 8.989,77 €, ascensor 12.1, UPAC de cerca de 86–106 kWp) tem de ser confirmada face ao QG/PT existente. Impacto: (3.300 − 1.313,81) = 1.986,19 €. | S98: Fazer o balanço de potências e confirmar a potência disponível no QG/PT existente. Pedir à E-Redes aumento de potência, se necessário. Detalhar o âmbito de 7.1.1 (aparelho de saída, barramentos, adaptação). | T98: Dono de Obra | U98: EXISTENTE | V98: MANTIDO | W98: Valores confirmados (7.1.1 1 × 1.313,81; 7.1.2.1 165 m × 167,12 = 27.574,80). PU 1.313,81 confirmado em exatamente 5 artigos (7.1.1, 7.3.7.1, 11.15, 11.16, 11.17). Pesquisa por 'E-Redes', 'EDP', 'potência' sem artigo de aumento de potência. Cálculo do impacto correto. | X98: Pendente
A99: 95 | B99: 7 | C99: 7.2.3.1 | D99: 7.2.3.2; 7.2.3.3; 7.2.1.2; 7.2.1.3; 7.2.1.4; 7.2.2.1; 7.2.4.1 | E99: Caminho de cabos chapa aço macio (correntes fracas) 300/200/100x60 | F99: INCOERÊNCIA | G99: MÉDIA | H99: Caminho de cabos igual com preço 57–63 % mais caro | I99: Correntes fracas 7.2.3 (sem tampa): 300x60 5 m × 37,29 €; 200x60 110 m × 28,49 €; 100x60 200 m × 24,68 € (total 8.256,35 €). Elétricas 7.2.1 (mesmo material, sem tampa): 300x60 22,96 €; 200x60 18,18 €; 100x60 15,13 €. Com tampa (7.2.2.1/7.2.4.1): 200x60 29,20 € | J99: 5 | K99: m | L99: 37.29 | M99: 186.45 | N99: Mesmo produto, mesmo PU: alinhar 7.2.3 com 7.2.1 (mercado PT ≈ 12–25 €/m instalado para 100–200x60 galvanizado sendzimir) | O99: -3115.75 | P99: -3115.75 | Q99: =AVERAGE(O99:P99) -> -3115.75 | R99: Diferenças: +62,4 % (300x60), +56,7 % (200x60), +63,1 % (100x60). O 200x60 sem tampa de 7.2.3.2 (28,49 €) custa quase o mesmo que o 200x60 com tampa (29,20 €). Impacto: (22,96 − 37,29) × 5 + (18,18 − 28,49) × 110 + (15,13 − 24,68) × 200 = −3.115,75 €. | S99: Uniformizar os PU de 7.2.3 com 7.2.1, ou justificar a diferença na descrição (ex.: chapa com separador ou tampa). | T99: Orçamentista | U99: NOVO | V99: MANTIDO | W99: Todos os PU e quantidades conferidos no rows.json; total 7.2.3 = 186,45 + 3.133,90 + 4.936,00 = 8.256,35 €. Percentagens recalculadas (1,624; 1,567; 1,631). Impacto −71,65 − 1.134,10 − 1.910,00 = −3.115,75 € correto. As designações de 7.2.1 e 7.2.3 diferem só no uso (elétricas vs correntes fracas); a incoerência é objetiva. | X99: Pendente
A100: 96 | B100: 7 | C100: 7.3 (OMISSÃO) | D100: 7.3.1–7.3.7.1; 7.3.4 | E100: REDE TERRA – elétrodo de terra | F100: FALHA/OMISSÃO | G100: MÉDIA | H100: Rede de terra sem elétrodo próprio do novo edifício | I100: 7.3 (5.271,03 €) tem barras, caixas, cabos isolados e 7.3.4 'Piquet de terra, ligação equipotencial dos postes de iluminação' 16 UN × 46,45 € (= 4 postes P3 + 12 E1). Não há anel de fundação, cabo de cobre nu nem elétrodos para o edifício. 7.3.7.1 'Trabalhos de melhoria da rede de terra, medições, e outros se verifiquem necessários para um bom sistema terra…' é uma verba de 1.313,81 € | N100: RTIEBT secção 542: elétrodo de terra da instalação. Num edifício novo com fundações em betão armado, anel de fundação em cobre nu 35 mm² ou fita de aço, com ligações exotérmicas, ≈ 2.000–3.000 € | O100: 0 | P100: 3000 | Q100: =AVERAGE(O100:P100) -> 1500 | R100: Os 16 piquets correspondem exatamente aos postes (4 + 12), pelo que o edifício (demolido e reconstruído, a 165 m do QG existente) não tem elétrodo medido. Mínimo 0 se o elétrodo couber em 7.3.7.1 ou no capítulo de estruturas. | S100: Confirmar com o projetista o tipo de elétrodo e criar o artigo medido. Coordenar com estruturas a execução antes da betonagem. | T100: Projetista | U100: NOVO | V100: MANTIDO | W100: Pesquisa refeita em todo o rows.json: 'cobre' só em 8.4.1/8.5 (pares de cobre ITED); 'elétrodo/eléctrodo/electrodo', 'cobre nu', 'equipoten' (só 7.3.4), 'ligação à terra' sem artigo de elétrodo. Correspondência 16 = 4 + 12 postes confirmada. O texto de 7.3.7.1 é genérico e pode cobrir parte, o que justifica o mínimo 0. | X100: Pendente
A101: 97 | B101: 7 | C101: 7.4.1 | D101: 7.4.2; 7.4.3; 7.1.2.1 | E101: Q.G.P. | F101: PREÇO BAIXO | G101: MÉDIA | H101: QGP orçamentado abaixo de um dos quadros parciais que alimenta | I101: 7.4.1 'Q.G.P.' 1 UN × 2.648,86 €; 7.4.2 'Q.P.C.I.G.' 9.541,74 €; 7.4.3 'Q.P.Pav.' 2.733,80 €; 7.4.4 'Q.P.C.I.P.' 756,44 €; 7.4.5 'Q.PV.AC' 2.683,37 €; entrada 7.1.2.1 R4x1x185+G95 | J101: 1 | K101: UN | L101: 2648.86 | M101: 2648.86 | N101: QGP de 250–315 A com corte geral em caixa moldada, ~5–8 saídas (4 quadros parciais + reservas), descarregadores de sobretensões e analisador de energia, invólucro metálico: ≈ 4.000–7.000 € instalado | O101: 1351.14 | P101: 4351.14 | Q101: =AVERAGE(O101:P101) -> 2851.14 | R101: O QGP recebe 4×185 mm² e alimenta os 4 quadros parciais de 7.4, mas custa menos do que o Q.P.Pav. (2.733,80 €) e 27,8 % do Q.P.C.I.G. (9.541,74 €). Só o disjuntor de caixa moldada de 250 A com SPD e analisador ronda 1.500–2.500 €. Impacto: (4.000 − 2.648,86) = 1.351,14 €; (7.000 − 2.648,86) = 4.351,14 €. | S101: Pedir uma consulta a um quadrista com o esquema unifilar do QGP e rever o PU. | T101: Orçamentista | U101: EXISTENTE | V101: CORRIGIDO | W101: Valores do MQT conferidos (2.648,86 / 9.541,74 / 2.733,80; 2.648,86/9.541,74 = 27,8 %). O problema é plausível, mas a referência original (7.650–12.650 €, 'cerca de 30 saídas') não tem suporte nos dados: o QGP alimenta apenas 4 quadros parciais (7.4.2–7.4.5) e 4 colunas (7.6.1.1–7.6.1.4). Referência baixada para 4.000–7.000 €, impacto corrigido de 5.000–10.000 € para 1.351–4.351 € e gravidade de ALTA para MÉDIA. | X101: Pendente
...

Sheet CUSTO vs VENDA
A1: COMPARAÇÃO CUSTO × VENDA POR CAPÍTULO
A2: Custo e Venda copiados do MQT (azul). K e cenários = alavancas editáveis (amarelo). Impacto = soma dos achados por capítulo (folha MAPA COMPARATIVO).
A3: K pretendido (Venda/Custo): | C3: 1.2 | D3: ← alterar (ex.: 1,15 a 1,25 = estrutura + risco + lucro; definido pela empresa)
A5: Cap. | B5: Designação | C5: Custo MQT (€) | D5: Venda MQT (€) | E5: Venda − Custo (€) | F5: K atual | G5: Impacto achados A (€) | H5: Impacto achados B (€) | I5: Custo corrigido A (€) | J5: Custo corrigido B (€) | K5: Venda proposta A (€) | L5: Venda proposta B (€) | M5: % do custo
A6: 1 | B6: TRABALHOS PREPARATÓRIOS | C6: 312435 | D6: 312435 | E6: =D6-C6 -> 0 | F6: =IFERROR(D6/C6,0) -> 1 | G6: =SUMIFS('MAPA COMPARATIVO'!$O$5:$O$206,'MAPA COMPARATIVO'!$B$5:$B$206,A6,'MAPA COMPARATIVO'!$V$5:$V$206,"<>REJEITADO") -> 2000 | H6: =SUMIFS('MAPA COMPARATIVO'!$P$5:$P$206,'MAPA COMPARATIVO'!$B$5:$B$206,A6,'MAPA COMPARATIVO'!$V$5:$V$206,"<>REJEITADO") -> 21000 | I6: =C6+G6 -> 314435 | J6: =C6+H6 -> 333435 | K6: =I6*$C$3 -> 377322 | L6: =J6*$C$3 -> 400122 | M6: =IFERROR(C6/$C$21,0) -> 0.069435523
A7: 2 | B7: ESTABILIDADE | C7: 1651924.5 | D7: 1651922.7 | E7: =D7-C7 -> -1.85 | F7: =IFERROR(D7/C7,0) -> 0.99999888 | G7: =SUMIFS('MAPA COMPARATIVO'!$O$5:$O$206,'MAPA COMPARATIVO'!$B$5:$B$206,A7,'MAPA COMPARATIVO'!$V$5:$V$206,"<>REJEITADO") -> 322.83 | H7: =SUMIFS('MAPA COMPARATIVO'!$P$5:$P$206,'MAPA COMPARATIVO'!$B$5:$B$206,A7,'MAPA COMPARATIVO'!$V$5:$V$206,"<>REJEITADO") -> -143586.42 | I7: =C7+G7 -> 1652247.4 | J7: =C7+H7 -> 1508338.1 | K7: =I7*$C$3 -> 1982696.8 | L7: =J7*$C$3 -> 1810005.7 | M7: =IFERROR(C7/$C$21,0) -> 0.36712354
A8: 3 | B8: ARQUITETURA | C8: 1586732.2 | D8: 1586722.1 | E8: =D8-C8 -> -10.13 | F8: =IFERROR(D8/C8,0) -> 0.99999362 | G8: =SUMIFS('MAPA COMPARATIVO'!$O$5:$O$206,'MAPA COMPARATIVO'!$B$5:$B$206,A8,'MAPA COMPARATIVO'!$V$5:$V$206,"<>REJEITADO") -> 68532.89 | H8: =SUMIFS('MAPA COMPARATIVO'!$P$5:$P$206,'MAPA COMPARATIVO'!$B$5:$B$206,A8,'MAPA COMPARATIVO'!$V$5:$V$206,"<>REJEITADO") -> 297970.72 | I8: =C8+G8 -> 1655265.1 | J8: =C8+H8 -> 1884702.9 | K8: =I8*$C$3 -> 1986318.1 | L8: =J8*$C$3 -> 2261643.5 | M8: =IFERROR(C8/$C$21,0) -> 0.3526352
A9: 4 | B9: REDE DE ABASTECIMENTO DE ÁGUA | C9: 78339.7 | D9: 78339.7 | E9: =D9-C9 -> 0 | F9: =IFERROR(D9/C9,0) -> 1 | G9: =SUMIFS('MAPA COMPARATIVO'!$O$5:$O$206,'MAPA COMPARATIVO'!$B$5:$B$206,A9,'MAPA COMPARATIVO'!$V$5:$V$206,"<>REJEITADO") -> 4996.18 | H9: =SUMIFS('MAPA COMPARATIVO'!$P$5:$P$206,'MAPA COMPARATIVO'!$B$5:$B$206,A9,'MAPA COMPARATIVO'!$V$5:$V$206,"<>REJEITADO") -> 37769.6 | I9: =C9+G9 -> 83335.88 | J9: =C9+H9 -> 116109.3 | K9: =I9*$C$3 -> 100003.06 | L9: =J9*$C$3 -> 139331.16 | M9: =IFERROR(C9/$C$21,0) -> 0.017410207
A10: 5 | B10: REDE DE DRENAGEM DE ÁGUAS RESIDUAIS | C10: 40966.31 | D10: 40966.25 | E10: =D10-C10 -> -0.06 | F10: =IFERROR(D10/C10,0) -> 0.99999854 | G10: =SUMIFS('MAPA COMPARATIVO'!$O$5:$O$206,'MAPA COMPARATIVO'!$B$5:$B$206,A10,'MAPA COMPARATIVO'!$V$5:$V$206,"<>REJEITADO") -> 3832.03 | H10: =SUMIFS('MAPA COMPARATIVO'!$P$5:$P$206,'MAPA COMPARATIVO'!$B$5:$B$206,A10,'MAPA COMPARATIVO'!$V$5:$V$206,"<>REJEITADO") -> 14235.74 | I10: =C10+G10 -> 44798.34 | J10: =C10+H10 -> 55202.05 | K10: =I10*$C$3 -> 53758.008 | L10: =J10*$C$3 -> 66242.46 | M10: =IFERROR(C10/$C$21,0) -> 0.0091043486
A11: 6 | B11: REDE DE DRENAGEM DE ÁGUAS PLUVIAIS | C11: 128757.01 | D11: 128756.93 | E11: =D11-C11 -> -0.08 | F11: =IFERROR(D11/C11,0) -> 0.99999938 | G11: =SUMIFS('MAPA COMPARATIVO'!$O$5:$O$206,'MAPA COMPARATIVO'!$B$5:$B$206,A11,'MAPA COMPARATIVO'!$V$5:$V$206,"<>REJEITADO") -> 9387.53 | H11: =SUMIFS('MAPA COMPARATIVO'!$P$5:$P$206,'MAPA COMPARATIVO'!$B$5:$B$206,A11,'MAPA COMPARATIVO'!$V$5:$V$206,"<>REJEITADO") -> 28791.51 | I11: =C11+G11 -> 138144.54 | J11: =C11+H11 -> 157548.52 | K11: =I11*$C$3 -> 165773.45 | L11: =J11*$C$3 -> 189058.22 | M11: =IFERROR(C11/$C$21,0) -> 0.028614945
A12: 7 | B12: INSTALAÇÕES ELÉTRICAS | C12: 265980.37 | D12: 265980.37 | E12: =D12-C12 -> 0 | F12: =IFERROR(D12/C12,0) -> 1 | G12: =SUMIFS('MAPA COMPARATIVO'!$O$5:$O$206,'MAPA COMPARATIVO'!$B$5:$B$206,A12,'MAPA COMPARATIVO'!$V$5:$V$206,"<>REJEITADO") -> 13523.8 | H12: =SUMIFS('MAPA COMPARATIVO'!$P$5:$P$206,'MAPA COMPARATIVO'!$B$5:$B$206,A12,'MAPA COMPARATIVO'!$V$5:$V$206,"<>REJEITADO") -> 68197.32 | I12: =C12+G12 -> 279504.17 | J12: =C12+H12 -> 334177.69 | K12: =I12*$C$3 -> 335405 | L12: =J12*$C$3 -> 401013.23 | M12: =IFERROR(C12/$C$21,0) -> 0.05911145
A13: 8 | B13: INSTALAÇÕES DE TELECOMUNICAÇÕES | C13: 9863.68 | D13: 9863.68 | E13: =D13-C13 -> 0 | F13: =IFERROR(D13/C13,0) -> 1 | G13: =SUMIFS('MAPA COMPARATIVO'!$O$5:$O$206,'MAPA COMPARATIVO'!$B$5:$B$206,A13,'MAPA COMPARATIVO'!$V$5:$V$206,"<>REJEITADO") -> 2600 | H13: =SUMIFS('MAPA COMPARATIVO'!$P$5:$P$206,'MAPA COMPARATIVO'!$B$5:$B$206,A13,'MAPA COMPARATIVO'!$V$5:$V$206,"<>REJEITADO") -> 6300 | I13: =C13+G13 -> 12463.68 | J13: =C13+H13 -> 16163.68 | K13: =I13*$C$3 -> 14956.416 | L13: =J13*$C$3 -> 19396.416 | M13: =IFERROR(C13/$C$21,0) -> 0.0021921032
A14: 9 | B14: SEGURANÇA CONTRA INCÊNDIO | C14: 2885.06 | D14: 2885.06 | E14: =D14-C14 -> 0 | F14: =IFERROR(D14/C14,0) -> 1 | G14: =SUMIFS('MAPA COMPARATIVO'!$O$5:$O$206,'MAPA COMPARATIVO'!$B$5:$B$206,A14,'MAPA COMPARATIVO'!$V$5:$V$206,"<>REJEITADO") -> 641.36 | H14: =SUMIFS('MAPA COMPARATIVO'!$P$5:$P$206,'MAPA COMPARATIVO'!$B$5:$B$206,A14,'MAPA COMPARATIVO'!$V$5:$V$206,"<>REJEITADO") -> 1622.04 | I14: =C14+G14 -> 3526.42 | J14: =C14+H14 -> 4507.1 | K14: =I14*$C$3 -> 4231.704 | L14: =J14*$C$3 -> 5408.52 | M14: =IFERROR(C14/$C$21,0) -> 0.00064117544
A15: 10 | B15: SEGURANÇA ATIVA | C15: 17332.79 | D15: 17332.79 | E15: =D15-C15 -> 0 | F15: =IFERROR(D15/C15,0) -> 1 | G15: =SUMIFS('MAPA COMPARATIVO'!$O$5:$O$206,'MAPA COMPARATIVO'!$B$5:$B$206,A15,'MAPA COMPARATIVO'!$V$5:$V$206,"<>REJEITADO") -> 992.12 | H15: =SUMIFS('MAPA COMPARATIVO'!$P$5:$P$206,'MAPA COMPARATIVO'!$B$5:$B$206,A15,'MAPA COMPARATIVO'!$V$5:$V$206,"<>REJEITADO") -> 8247.73 | I15: =C15+G15 -> 18324.91 | J15: =C15+H15 -> 25580.52 | K15: =I15*$C$3 -> 21989.892 | L15: =J15*$C$3 -> 30696.624 | M15: =IFERROR(C15/$C$21,0) -> 0.0038520375
A16: 11 | B16: INSTALAÇÕES MECÂNICAS DE AVAC | C16: 271944.75 | D16: 271944.75 | E16: =D16-C16 -> 0 | F16: =IFERROR(D16/C16,0) -> 1 | G16: =SUMIFS('MAPA COMPARATIVO'!$O$5:$O$206,'MAPA COMPARATIVO'!$B$5:$B$206,A16,'MAPA COMPARATIVO'!$V$5:$V$206,"<>REJEITADO") -> -154.13 | H16: =SUMIFS('MAPA COMPARATIVO'!$P$5:$P$206,'MAPA COMPARATIVO'!$B$5:$B$206,A16,'MAPA COMPARATIVO'!$V$5:$V$206,"<>REJEITADO") -> -1281.75 | I16: =C16+G16 -> 271790.62 | J16: =C16+H16 -> 270663 | K16: =I16*$C$3 -> 326148.74 | L16: =J16*$C$3 -> 324795.6 | M16: =IFERROR(C16/$C$21,0) -> 0.060436974
A17: 12 | B17: INSTALAÇÕES ELETROMECÂNICAS | C17: 31350 | D17: 31350 | E17: =D17-C17 -> 0 | F17: =IFERROR(D17/C17,0) -> 1 | G17: =SUMIFS('MAPA COMPARATIVO'!$O$5:$O$206,'MAPA COMPARATIVO'!$B$5:$B$206,A17,'MAPA COMPARATIVO'!$V$5:$V$206,"<>REJEITADO") -> 0 | H17: =SUMIFS('MAPA COMPARATIVO'!$P$5:$P$206,'MAPA COMPARATIVO'!$B$5:$B$206,A17,'MAPA COMPARATIVO'!$V$5:$V$206,"<>REJEITADO") -> 2000 | I17: =C17+G17 -> 31350 | J17: =C17+H17 -> 33350 | K17: =I17*$C$3 -> 37620 | L17: =J17*$C$3 -> 40020 | M17: =IFERROR(C17/$C$21,0) -> 0.0069672208
... A19: 14 | B19: GESTÃO TÉCNICA CENTRALIZADA | C19: 35665.7 | D19: 35665.7 | E19: =D19-C19 -> 0 | F19: =IFERROR(D19/C19,0) -> 1 | G19: =SUMIFS('MAPA COMPARATIVO'!$O$5:$O$206,'MAPA COMPARATIVO'!$B$5:$B$206,A19,'MAPA COMPARATIVO'!$V$5:$V$206,"<>REJEITADO") -> -8398.6 | H19: =SUMIFS('MAPA COMPARATIVO'!$P$5:$P$206,'MAPA COMPARATIVO'!$B$5:$B$206,A19,'MAPA COMPARATIVO'!$V$5:$V$206,"<>REJEITADO") -> -1210.23 | I19: =C19+G19 -> 27267.1 | J19: =C19+H19 -> 34455.47 | K19: =I19*$C$3 -> 32720.52 | L19: =J19*$C$3 -> 41346.564 | M19: =IFERROR(C19/$C$21,0) -> 0.0079263416
A20: GERAL | B20: Achados transversais (sem capítulo) | G20: =SUMIFS('MAPA COMPARATIVO'!$O$5:$O$206,'MAPA COMPARATIVO'!$B$5:$B$206,"GERAL",'MAPA COMPARATIVO'!$V$5:$V$206,"<>REJEITADO") -> -12.12 | H20: =SUMIFS('MAPA COMPARATIVO'!$P$5:$P$206,'MAPA COMPARATIVO'!$B$5:$B$206,"GERAL",'MAPA COMPARATIVO'!$V$5:$V$206,"<>REJEITADO") -> -12.12 | I20: =G20 -> -12.12 | J20: =H20 -> -12.12 | K20: =I20*$C$3 -> -14.544 | L20: =J20*$C$3 -> -14.544 | M20: =IFERROR(C20/$C$21,0) -> 0
B21: TOTAL (sem IVA) | C21: =SUM(C6:C20) -> 4499642.1 | D21: =SUM(D6:D20) -> 4499630 | E21: =SUM(E6:E20) -> -12.12 | F21: =IFERROR(D21/C21,0) -> 0.99999731 | G21: =SUM(G6:G20) -> 115594.89 | H21: =SUM(H6:H20) -> 399725.14 | I21: =SUM(I6:I20) -> 4615237 | J21: =SUM(J6:J20) -> 4899367.2 | K21: =SUM(K6:K20) -> 5538284.4 | L21: =SUM(L6:L20) -> 5879240.7
B23: Variação do custo corrigido face ao MQT | I23: =IFERROR(I21/C21-1,0) -> 0.025689797 | J23: =IFERROR(J21/C21-1,0) -> 0.088834875
B24: Venda MQT − Custo MQT (prova de que não há margem) | E24: =E21 -> -12.12

Sheet MATRIZ CAP×TIPO
A1: MATRIZ DE COMPARAÇÃO – Nº DE ACHADOS POR CAPÍTULO × TIPO E GRAVIDADE
A2: Contagens e somas calculadas por fórmula sobre a folha MAPA COMPARATIVO (exclui achados REJEITADOS na verificação).
A4: Cap. | B4: Designação | C4: ERRO | D4: FALHA/OMISSÃO | E4: DUPLICAÇÃO | F4: PREÇO BAIXO | G4: PREÇO ALTO | H4: INCOERÊNCIA | I4: DESCRIÇÃO | J4: NORMA | K4: INCOMPATIBILIDADE | L4: EXTRA/FORA DE ÂMBITO | M4: VERIFICAR | N4: TOTAL | O4: CRÍTICA | P4: ALTA | Q4: MÉDIA | R4: BAIXA | S4: Impacto A – mín (€) | T4: Impacto B – máx (€)
A5: 1 | B5: TRABALHOS PREPARATÓRIOS | C5: =COUNTIFS('MAPA COMPARATIVO'!$B$5:$B$206,$A5,'MAPA COMPARATIVO'!$F$5:$F$206,"ERRO",'MAPA COMPARATIVO'!$V$5:$V$206,"<>REJEITADO") -> 0 | D5: =COUNTIFS('MAPA COMPARATIVO'!$B$5:$B$206,$A5,'MAPA COMPARATIVO'!$F$5:$F$206,"FALHA/OMISSÃO",'MAPA COMPARATIVO'!$V$5:$V$206,"<>REJEITADO") -> 1 | E5: =COUNTIFS('MAPA COMPARATIVO'!$B$5:$B$206,$A5,'MAPA COMPARATIVO'!$F$5:$F$206,"DUPLICAÇÃO",'MAPA COMPARATIVO'!$V$5:$V$206,"<>REJEITADO") -> 0 | F5: =COUNTIFS('MAPA COMPARATIVO'!$B$5:$B$206,$A5,'MAPA COMPARATIVO'!$F$5:$F$206,"PREÇO BAIXO",'MAPA COMPARATIVO'!$V$5:$V$206,"<>REJEITADO") -> 2 | G5: =COUNTIFS('MAPA COMPARATIVO'!$B$5:$B$206,$A5,'MAPA COMPARATIVO'!$F$5:$F$206,"PREÇO ALTO",'MAPA COMPARATIVO'!$V$5:$V$206,"<>REJEITADO") -> 0 | H5: =COUNTIFS('MAPA COMPARATIVO'!$B$5:$B$206,$A5,'MAPA COMPARATIVO'!$F$5:$F$206,"INCOERÊNCIA",'MAPA COMPARATIVO'!$V$5:$V$206,"<>REJEITADO") -> 0 | I5: =COUNTIFS('MAPA COMPARATIVO'!$B$5:$B$206,$A5,'MAPA COMPARATIVO'!$F$5:$F$206,"DESCRIÇÃO",'MAPA COMPARATIVO'!$V$5:$V$206,"<>REJEITADO") -> 1 | J5: =COUNTIFS('MAPA COMPARATIVO'!$B$5:$B$206,$A5,'MAPA COMPARATIVO'!$F$5:$F$206,"NORMA",'MAPA COMPARATIVO'!$V$5:$V$206,"<>REJEITADO") -> 0 | K5: =COUNTIFS('MAPA COMPARATIVO'!$B$5:$B$206,$A5,'MAPA COMPARATIVO'!$F$5:$F$206,"INCOMPATIBILIDADE",'MAPA COMPARATIVO'!$V$5:$V$206,"<>REJEITADO") -> 0 | L5: =COUNTIFS('MAPA COMPARATIVO'!$B$5:$B$206,$A5,'MAPA COMPARATIVO'!$F$5:$F$206,"EXTRA/FORA DE ÂMBITO",'MAPA COMPARATIVO'!$V$5:$V$206,"<>REJEITADO") -> 0 | M5: =COUNTIFS('MAPA COMPARATIVO'!$B$5:$B$206,$A5,'MAPA COMPARATIVO'!$F$5:$F$206,"VERIFICAR",'MAPA COMPARATIVO'!$V$5:$V$206,"<>REJEITADO") -> 1 | N5: =SUM(C5:M5) -> 5 | O5: =COUNTIFS('MAPA COMPARATIVO'!$B$5:$B$206,$A5,'MAPA COMPARATIVO'!$G$5:$G$206,"CRÍTICA",'MAPA COMPARATIVO'!$V$5:$V$206,"<>REJEITADO") -> 0 | P5: =COUNTIFS('MAPA COMPARATIVO'!$B$5:$B$206,$A5,'MAPA COMPARATIVO'!$G$5:$G$206,"ALTA",'MAPA COMPARATIVO'!$V$5:$V$206,"<>REJEITADO") -> 0 | Q5: =COUNTIFS('MAPA COMPARATIVO'!$B$5:$B$206,$A5,'MAPA COMPARATIVO'!$G$5:$G$206,"MÉDIA",'MAPA COMPARATIVO'!$V$5:$V$206,"<>REJEITADO") -> 3 | R5: =COUNTIFS('MAPA COMPARATIVO'!$B$5:$B$206,$A5,'MAPA COMPARATIVO'!$G$5:$G$206,"BAIXA",'MAPA COMPARATIVO'!$V$5:$V$206,"<>REJEITADO") -> 2 | S5: =SUMIFS('MAPA COMPARATIVO'!$O$5:$O$206,'MAPA COMPARATIVO'!$B$5:$B$206,$A5,'MAPA COMPARATIVO'!$V$5:$V$206,"<>REJEITADO") -> 2000 | T5: =SUMIFS('MAPA COMPARATIVO'!$P$5:$P$206,'MAPA COMPARATIVO'!$B$5:$B$206,$A5,'MAPA COMPARATIVO'!$V$5:$V$206,"<>REJEITADO") -> 21000
A6: 2 | B6: ESTABILIDADE | C6: =COUNTIFS('MAPA COMPARATIVO'!$B$5:$B$206,$A6,'MAPA COMPARATIVO'!$F$5:$F$206,"ERRO",'MAPA COMPARATIVO'!$V$5:$V$206,"<>REJEITADO") -> 3 | D6: =COUNTIFS('MAPA COMPARATIVO'!$B$5:$B$206,$A6,'MAPA COMPARATIVO'!$F$5:$F$206,"FALHA/OMISSÃO",'MAPA COMPARATIVO'!$V$5:$V$206,"<>REJEITADO") -> 4 | E6: =COUNTIFS('MAPA COMPARATIVO'!$B$5:$B$206,$A6,'MAPA COMPARATIVO'!$F$5:$F$206,"DUPLICAÇÃO",'MAPA COMPARATIVO'!$V$5:$V$206,"<>REJEITADO") -> 3 | F6: =COUNTIFS('MAPA COMPARATIVO'!$B$5:$B$206,$A6,'MAPA COMPARATIVO'!$F$5:$F$206,"PREÇO BAIXO",'MAPA COMPARATIVO'!$V$5:$V$206,"<>REJEITADO") -> 4 | G6: =COUNTIFS('MAPA COMPARATIVO'!$B$5:$B$206,$A6,'MAPA COMPARATIVO'!$F$5:$F$206,"PREÇO ALTO",'MAPA COMPARATIVO'!$V$5:$V$206,"<>REJEITADO") -> 0 | H6: =COUNTIFS('MAPA COMPARATIVO'!$B$5:$B$206,$A6,'MAPA COMPARATIVO'!$F$5:$F$206,"INCOERÊNCIA",'MAPA COMPARATIVO'!$V$5:$V$206,"<>REJEITADO") -> 3 | I6: =COUNTIFS('MAPA COMPARATIVO'!$B$5:$B$206,$A6,'MAPA COMPARATIVO'!$F$5:$F$206,"DESCRIÇÃO",'MAPA COMPARATIVO'!$V$5:$V$206,"<>REJEITADO") -> 6 | J6: =COUNTIFS('MAPA COMPARATIVO'!$B$5:$B$206,$A6,'MAPA COMPARATIVO'!$F$5:$F$206,"NORMA",'MAPA COMPARATIVO'!$V$5:$V$206,"<>REJEITADO") -> 5 | K6: =COUNTIFS('MAPA COMPARATIVO'!$B$5:$B$206,$A6,'MAPA COMPARATIVO'!$F$5:$F$206,"INCOMPATIBILIDADE",'MAPA COMPARATIVO'!$V$5:$V$206,"<>REJEITADO") -> 0 | L6: =COUNTIFS('MAPA COMPARATIVO'!$B$5:$B$206,$A6,'MAPA COMPARATIVO'!$F$5:$F$206,"EXTRA/FORA DE ÂMBITO",'MAPA COMPARATIVO'!$V$5:$V$206,"<>REJEITADO") -> 0 | M6: =COUNTIFS('MAPA COMPARATIVO'!$B$5:$B$206,$A6,'MAPA COMPARATIVO'!$F$5:$F$206,"VERIFICAR",'MAPA COMPARATIVO'!$V$5:$V$206,"<>REJEITADO") -> 7 | N6: =SUM(C6:M6) -> 35 | O6: =COUNTIFS('MAPA COMPARATIVO'!$B$5:$B$206,$A6,'MAPA COMPARATIVO'!$G$5:$G$206,"CRÍTICA",'MAPA COMPARATIVO'!$V$5:$V$206,"<>REJEITADO") -> 0 | P6: =COUNTIFS('MAPA COMPARATIVO'!$B$5:$B$206,$A6,'MAPA COMPARATIVO'!$G$5:$G$206,"ALTA",'MAPA COMPARATIVO'!$V$5:$V$206,"<>REJEITADO") -> 11 | Q6: =COUNTIFS('MAPA COMPARATIVO'!$B$5:$B$206,$A6,'MAPA COMPARATIVO'!$G$5:$G$206,"MÉDIA",'MAPA COMPARATIVO'!$V$5:$V$206,"<>REJEITADO") -> 16 | R6: =COUNTIFS('MAPA COMPARATIVO'!$B$5:$B$206,$A6,'MAPA COMPARATIVO'!$G$5:$G$206,"BAIXA",'MAPA COMPARATIVO'!$V$5:$V$206,"<>REJEITADO") -> 8 | S6: =SUMIFS('MAPA COMPARATIVO'!$O$5:$O$206,'MAPA COMPARATIVO'!$B$5:$B$206,$A6,'MAPA COMPARATIVO'!$V$5:$V$206,"<>REJEITADO") -> 322.83 | T6: =SUMIFS('MAPA COMPARATIVO'!$P$5:$P$206,'MAPA COMPARATIVO'!$B$5:$B$206,$A6,'MAPA COMPARATIVO'!$V$5:$V$206,"<>REJEITADO") -> -143586.42
A7: 3 | B7: ARQUITETURA | C7: =COUNTIFS('MAPA COMPARATIVO'!$B$5:$B$206,$A7,'MAPA COMPARATIVO'!$F$5:$F$206,"ERRO",'MAPA COMPARATIVO'!$V$5:$V$206,"<>REJEITADO") -> 4 | D7: =COUNTIFS('MAPA COMPARATIVO'!$B$5:$B$206,$A7,'MAPA COMPARATIVO'!$F$5:$F$206,"FALHA/OMISSÃO",'MAPA COMPARATIVO'!$V$5:$V$206,"<>REJEITADO") -> 11 | E7: =COUNTIFS('MAPA COMPARATIVO'!$B$5:$B$206,$A7,'MAPA COMPARATIVO'!$F$5:$F$206,"DUPLICAÇÃO",'MAPA COMPARATIVO'!$V$5:$V$206,"<>REJEITADO") -> 5 | F7: =COUNTIFS('MAPA COMPARATIVO'!$B$5:$B$206,$A7,'MAPA COMPARATIVO'!$F$5:$F$206,"PREÇO BAIXO",'MAPA COMPARATIVO'!$V$5:$V$206,"<>REJEITADO") -> 11 | G7: =COUNTIFS('MAPA COMPARATIVO'!$B$5:$B$206,$A7,'MAPA COMPARATIVO'!$F$5:$F$206,"PREÇO ALTO",'MAPA COMPARATIVO'!$V$5:$V$206,"<>REJEITADO") -> 1 | H7: =COUNTIFS('MAPA COMPARATIVO'!$B$5:$B$206,$A7,'MAPA COMPARATIVO'!$F$5:$F$206,"INCOERÊNCIA",'MAPA COMPARATIVO'!$V$5:$V$206,"<>REJEITADO") -> 12 | I7: =COUNTIFS('MAPA COMPARATIVO'!$B$5:$B$206,$A7,'MAPA COMPARATIVO'!$F$5:$F$206,"DESCRIÇÃO",'MAPA COMPARATIVO'!$V$5:$V$206,"<>REJEITADO") -> 6 | J7: =COUNTIFS('MAPA COMPARATIVO'!$B$5:$B$206,$A7,'MAPA COMPARATIVO'!$F$5:$F$206,"NORMA",'MAPA COMPARATIVO'!$V$5:$V$206,"<>REJEITADO") -> 4 | K7: =COUNTIFS('MAPA COMPARATIVO'!$B$5:$B$206,$A7,'MAPA COMPARATIVO'!$F$5:$F$206,"INCOMPATIBILIDADE",'MAPA COMPARATIVO'!$V$5:$V$206,"<>REJEITADO") -> 0 | L7: =COUNTIFS('MAPA COMPARATIVO'!$B$5:$B$206,$A7,'MAPA COMPARATIVO'!$F$5:$F$206,"EXTRA/FORA DE ÂMBITO",'MAPA COMPARATIVO'!$V$5:$V$206,"<>REJEITADO") -> 0 | M7: =COUNTIFS('MAPA COMPARATIVO'!$B$5:$B$206,$A7,'MAPA COMPARATIVO'!$F$5:$F$206,"VERIFICAR",'MAPA COMPARATIVO'!$V$5:$V$206,"<>REJEITADO") -> 5 | N7: =SUM(C7:M7) -> 59 | O7: =COUNTIFS('MAPA COMPARATIVO'!$B$5:$B$206,$A7,'MAPA COMPARATIVO'!$G$5:$G$206,"CRÍTICA",'MAPA COMPARATIVO'!$V$5:$V$206,"<>REJEITADO") -> 0 | P7: =COUNTIFS('MAPA COMPARATIVO'!$B$5:$B$206,$A7,'MAPA COMPARATIVO'!$G$5:$G$206,"ALTA",'MAPA COMPARATIVO'!$V$5:$V$206,"<>REJEITADO") -> 10 | Q7: =COUNTIFS('MAPA COMPARATIVO'!$B$5:$B$206,$A7,'MAPA COMPARATIVO'!$G$5:$G$206,"MÉDIA",'MAPA COMPARATIVO'!$V$5:$V$206,"<>REJEITADO") -> 26 | R7: =COUNTIFS('MAPA COMPARATIVO'!$B$5:$B$206,$A7,'MAPA COMPARATIVO'!$G$5:$G$206,"BAIXA",'MAPA COMPARATIVO'!$V$5:$V$206,"<>REJEITADO") -> 23 | S7: =SUMIFS('MAPA COMPARATIVO'!$O$5:$O$206,'MAPA COMPARATIVO'!$B$5:$B$206,$A7,'MAPA COMPARATIVO'!$V$5:$V$206,"<>REJEITADO") -> 68532.89 | T7: =SUMIFS('MAPA COMPARATIVO'!$P$5:$P$206,'MAPA COMPARATIVO'!$B$5:$B$206,$A7,'MAPA COMPARATIVO'!$V$5:$V$206,"<>REJEITADO") -> 297970.72
A8: 4 | B8: REDE DE ABASTECIMENTO DE ÁGUA | C8: =COUNTIFS('MAPA COMPARATIVO'!$B$5:$B$206,$A8,'MAPA COMPARATIVO'!$F$5:$F$206,"ERRO",'MAPA COMPARATIVO'!$V$5:$V$206,"<>REJEITADO") -> 0 | D8: =COUNTIFS('MAPA COMPARATIVO'!$B$5:$B$206,$A8,'MAPA COMPARATIVO'!$F$5:$F$206,"FALHA/OMISSÃO",'MAPA COMPARATIVO'!$V$5:$V$206,"<>REJEITADO") -> 0 | E8: =COUNTIFS('MAPA COMPARATIVO'!$B$5:$B$206,$A8,'MAPA COMPARATIVO'!$F$5:$F$206,"DUPLICAÇÃO",'MAPA COMPARATIVO'!$V$5:$V$206,"<>REJEITADO") -> 1 | F8: =COUNTIFS('MAPA COMPARATIVO'!$B$5:$B$206,$A8,'MAPA COMPARATIVO'!$F$5:$F$206,"PREÇO BAIXO",'MAPA COMPARATIVO'!$V$5:$V$206,"<>REJEITADO") -> 5 | G8: =COUNTIFS('MAPA COMPARATIVO'!$B$5:$B$206,$A8,'MAPA COMPARATIVO'!$F$5:$F$206,"PREÇO ALTO",'MAPA COMPARATIVO'!$V$5:$V$206,"<>REJEITADO") -> 1 | H8: =COUNTIFS('MAPA COMPARATIVO'!$B$5:$B$206,$A8,'MAPA COMPARATIVO'!$F$5:$F$206,"INCOERÊNCIA",'MAPA COMPARATIVO'!$V$5:$V$206,"<>REJEITADO") -> 1 | I8: =COUNTIFS('MAPA COMPARATIVO'!$B$5:$B$206,$A8,'MAPA COMPARATIVO'!$F$5:$F$206,"DESCRIÇÃO",'MAPA COMPARATIVO'!$V$5:$V$206,"<>REJEITADO") -> 0 | J8: =COUNTIFS('MAPA COMPARATIVO'!$B$5:$B$206,$A8,'MAPA COMPARATIVO'!$F$5:$F$206,"NORMA",'MAPA COMPARATIVO'!$V$5:$V$206,"<>REJEITADO") -> 1 | K8: =COUNTIFS('MAPA COMPARATIVO'!$B$5:$B$206,$A8,'MAPA COMPARATIVO'!$F$5:$F$206,"INCOMPATIBILIDADE",'MAPA COMPARATIVO'!$V$5:$V$206,"<>REJEITADO") -> 0 | L8: =COUNTIFS('MAPA COMPARATIVO'!$B$5:$B$206,$A8,'MAPA COMPARATIVO'!$F$5:$F$206,"EXTRA/FORA DE ÂMBITO",'MAPA COMPARATIVO'!$V$5:$V$206,"<>REJEITADO") -> 0 | M8: =COUNTIFS('MAPA COMPARATIVO'!$B$5:$B$206,$A8,'MAPA COMPARATIVO'!$F$5:$F$206,"VERIFICAR",'MAPA COMPARATIVO'!$V$5:$V$206,"<>REJEITADO") -> 4 | N8: =SUM(C8:M8) -> 13 | O8: =COUNTIFS('MAPA COMPARATIVO'!$B$5:$B$206,$A8,'MAPA COMPARATIVO'!$G$5:$G$206,"CRÍTICA",'MAPA COMPARATIVO'!$V$5:$V$206,"<>REJEITADO") -> 0 | P8: =COUNTIFS('MAPA COMPARATIVO'!$B$5:$B$206,$A8,'MAPA COMPARATIVO'!$G$5:$G$206,"ALTA",'MAPA COMPARATIVO'!$V$5:$V$206,"<>REJEITADO") -> 0 | Q8: =COUNTIFS('MAPA COMPARATIVO'!$B$5:$B$206,$A8,'MAPA COMPARATIVO'!$G$5:$G$206,"MÉDIA",'MAPA COMPARATIVO'!$V$5:$V$206,"<>REJEITADO") -> 5 | R8: =COUNTIFS('MAPA COMPARATIVO'!$B$5:$B$206,$A8,'MAPA COMPARATIVO'!$G$5:$G$206,"BAIXA",'MAPA COMPARATIVO'!$V$5:$V$206,"<>REJEITADO") -> 8 | S8: =SUMIFS('MAPA COMPARATIVO'!$O$5:$O$206,'MAPA COMPARATIVO'!$B$5:$B$206,$A8,'MAPA COMPARATIVO'!$V$5:$V$206,"<>REJEITADO") -> 4996.18 | T8: =SUMIFS('MAPA COMPARATIVO'!$P$5:$P$206,'MAPA COMPARATIVO'!$B$5:$B$206,$A8,'MAPA COMPARATIVO'!$V$5:$V$206,"<>REJEITADO") -> 37769.6
A9: 5 | B9: REDE DE DRENAGEM DE ÁGUAS RESIDUAIS | C9: =COUNTIFS('MAPA COMPARATIVO'!$B$5:$B$206,$A9,'MAPA COMPARATIVO'!$F$5:$F$206,"ERRO",'MAPA COMPARATIVO'!$V$5:$V$206,"<>REJEITADO") -> 0 | D9: =COUNTIFS('MAPA COMPARATIVO'!$B$5:$B$206,$A9,'MAPA COMPARATIVO'!$F$5:$F$206,"FALHA/OMISSÃO",'MAPA COMPARATIVO'!$V$5:$V$206,"<>REJEITADO") -> 0 | E9: =COUNTIFS('MAPA COMPARATIVO'!$B$5:$B$206,$A9,'MAPA COMPARATIVO'!$F$5:$F$206,"DUPLICAÇÃO",'MAPA COMPARATIVO'!$V$5:$V$206,"<>REJEITADO") -> 3 | F9: =COUNTIFS('MAPA COMPARATIVO'!$B$5:$B$206,$A9,'MAPA COMPARATIVO'!$F$5:$F$206,"PREÇO BAIXO",'MAPA COMPARATIVO'!$V$5:$V$206,"<>REJEITADO") -> 3 | G9: =COUNTIFS('MAPA COMPARATIVO'!$B$5:$B$206,$A9,'MAPA COMPARATIVO'!$F$5:$F$206,"PREÇO ALTO",'MAPA COMPARATIVO'!$V$5:$V$206,"<>REJEITADO") -> 0 | H9: =COUNTIFS('MAPA COMPARATIVO'!$B$5:$B$206,$A9,'MAPA COMPARATIVO'!$F$5:$F$206,"INCOERÊNCIA",'MAPA COMPARATIVO'!$V$5:$V$206,"<>REJEITADO") -> 1 | I9: =COUNTIFS('MAPA COMPARATIVO'!$B$5:$B$206,$A9,'MAPA COMPARATIVO'!$F$5:$F$206,"DESCRIÇÃO",'MAPA COMPARATIVO'!$V$5:$V$206,"<>REJEITADO") -> 1 | J9: =COUNTIFS('MAPA COMPARATIVO'!$B$5:$B$206,$A9,'MAPA COMPARATIVO'!$F$5:$F$206,"NORMA",'MAPA COMPARATIVO'!$V$5:$V$206,"<>REJEITADO") -> 0 | K9: =COUNTIFS('MAPA COMPARATIVO'!$B$5:$B$206,$A9,'MAPA COMPARATIVO'!$F$5:$F$206,"INCOMPATIBILIDADE",'MAPA COMPARATIVO'!$V$5:$V$206,"<>REJEITADO") -> 1 | L9: =COUNTIFS('MAPA COMPARATIVO'!$B$5:$B$206,$A9,'MAPA COMPARATIVO'!$F$5:$F$206,"EXTRA/FORA DE ÂMBITO",'MAPA COMPARATIVO'!$V$5:$V$206,"<>REJEITADO") -> 0 | M9: =COUNTIFS('MAPA COMPARATIVO'!$B$5:$B$206,$A9,'MAPA COMPARATIVO'!$F$5:$F$206,"VERIFICAR",'MAPA COMPARATIVO'!$V$5:$V$206,"<>REJEITADO") -> 0 | N9: =SUM(C9:M9) -> 9 | O9: =COUNTIFS('MAPA COMPARATIVO'!$B$5:$B$206,$A9,'MAPA COMPARATIVO'!$G$5:$G$206,"CRÍTICA",'MAPA COMPARATIVO'!$V$5:$V$206,"<>REJEITADO") -> 0 | P9: =COUNTIFS('MAPA COMPARATIVO'!$B$5:$B$206,$A9,'MAPA COMPARATIVO'!$G$5:$G$206,"ALTA",'MAPA COMPARATIVO'!$V$5:$V$206,"<>REJEITADO") -> 1 | Q9: =COUNTIFS('MAPA COMPARATIVO'!$B$5:$B$206,$A9,'MAPA COMPARATIVO'!$G$5:$G$206,"MÉDIA",'MAPA COMPARATIVO'!$V$5:$V$206,"<>REJEITADO") -> 3 | R9: =COUNTIFS('MAPA COMPARATIVO'!$B$5:$B$206,$A9,'MAPA COMPARATIVO'!$G$5:$G$206,"BAIXA",'MAPA COMPARATIVO'!$V$5:$V$206,"<>REJEITADO") -> 5 | S9: =SUMIFS('MAPA COMPARATIVO'!$O$5:$O$206,'MAPA COMPARATIVO'!$B$5:$B$206,$A9,'MAPA COMPARATIVO'!$V$5:$V$206,"<>REJEITADO") -> 3832.03 | T9: =SUMIFS('MAPA COMPARATIVO'!$P$5:$P$206,'MAPA COMPARATIVO'!$B$5:$B$206,$A9,'MAPA COMPARATIVO'!$V$5:$V$206,"<>REJEITADO") -> 14235.74
A10: 6 | B10: REDE DE DRENAGEM DE ÁGUAS PLUVIAIS | C10: =COUNTIFS('MAPA COMPARATIVO'!$B$5:$B$206,$A10,'MAPA COMPARATIVO'!$F$5:$F$206,"ERRO",'MAPA COMPARATIVO'!$V$5:$V$206,"<>REJEITADO") -> 0 | D10: =COUNTIFS('MAPA COMPARATIVO'!$B$5:$B$206,$A10,'MAPA COMPARATIVO'!$F$5:$F$206,"FALHA/OMISSÃO",'MAPA COMPARATIVO'!$V$5:$V$206,"<>REJEITADO") -> 0 | E10: =COUNTIFS('MAPA COMPARATIVO'!$B$5:$B$206,$A10,'MAPA COMPARATIVO'!$F$5:$F$206,"DUPLICAÇÃO",'MAPA COMPARATIVO'!$V$5:$V$206,"<>REJEITADO") -> 1 | F10: =COUNTIFS('MAPA COMPARATIVO'!$B$5:$B$206,$A10,'MAPA COMPARATIVO'!$F$5:$F$206,"PREÇO BAIXO",'MAPA COMPARATIVO'!$V$5:$V$206,"<>REJEITADO") -> 5 | G10: =COUNTIFS('MAPA COMPARATIVO'!$B$5:$B$206,$A10,'MAPA COMPARATIVO'!$F$5:$F$206,"PREÇO ALTO",'MAPA COMPARATIVO'!$V$5:$V$206,"<>REJEITADO") -> 0 | H10: =COUNTIFS('MAPA COMPARATIVO'!$B$5:$B$206,$A10,'MAPA COMPARATIVO'!$F$5:$F$206,"INCOERÊNCIA",'MAPA COMPARATIVO'!$V$5:$V$206,"<>REJEITADO") -> 2 | I10: =COUNTIFS('MAPA COMPARATIVO'!$B$5:$B$206,$A10,'MAPA COMPARATIVO'!$F$5:$F$206,"DESCRIÇÃO",'MAPA COMPARATIVO'!$V$5:$V$206,"<>REJEITADO") -> 3 | J10: =COUNTIFS('MAPA COMPARATIVO'!$B$5:$B$206,$A10,'MAPA COMPARATIVO'!$F$5:$F$206,"NORMA",'MAPA COMPARATIVO'!$V$5:$V$206,"<>REJEITADO") -> 0 | K10: =COUNTIFS('MAPA COMPARATIVO'!$B$5:$B$206,$A10,'MAPA COMPARATIVO'!$F$5:$F$206,"INCOMPATIBILIDADE",'MAPA COMPARATIVO'!$V$5:$V$206,"<>REJEITADO") -> 0 | L10: =COUNTIFS('MAPA COMPARATIVO'!$B$5:$B$206,$A10,'MAPA COMPARATIVO'!$F$5:$F$206,"EXTRA/FORA DE ÂMBITO",'MAPA COMPARATIVO'!$V$5:$V$206,"<>REJEITADO") -> 0 | M10: =COUNTIFS('MAPA COMPARATIVO'!$B$5:$B$206,$A10,'MAPA COMPARATIVO'!$F$5:$F$206,"VERIFICAR",'MAPA COMPARATIVO'!$V$5:$V$206,"<>REJEITADO") -> 0 | N10: =SUM(C10:M10) -> 11 | O10: =COUNTIFS('MAPA COMPARATIVO'!$B$5:$B$206,$A10,'MAPA COMPARATIVO'!$G$5:$G$206,"CRÍTICA",'MAPA COMPARATIVO'!$V$5:$V$206,"<>REJEITADO") -> 0 | P10: =COUNTIFS('MAPA COMPARATIVO'!$B$5:$B$206,$A10,'MAPA COMPARATIVO'!$G$5:$G$206,"ALTA",'MAPA COMPARATIVO'!$V$5:$V$206,"<>REJEITADO") -> 4 | Q10: =COUNTIFS('MAPA COMPARATIVO'!$B$5:$B$206,$A10,'MAPA COMPARATIVO'!$G$5:$G$206,"MÉDIA",'MAPA COMPARATIVO'!$V$5:$V$206,"<>REJEITADO") -> 2 | R10: =COUNTIFS('MAPA COMPARATIVO'!$B$5:$B$206,$A10,'MAPA COMPARATIVO'!$G$5:$G$206,"BAIXA",'MAPA COMPARATIVO'!$V$5:$V$206,"<>REJEITADO") -> 5 | S10: =SUMIFS('MAPA COMPARATIVO'!$O$5:$O$206,'MAPA COMPARATIVO'!$B$5:$B$206,$A10,'MAPA COMPARATIVO'!$V$5:$V$206,"<>REJEITADO") -> 9387.53 | T10: =SUMIFS('MAPA COMPARATIVO'!$P$5:$P$206,'MAPA COMPARATIVO'!$B$5:$B$206,$A10,'MAPA COMPARATIVO'!$V$5:$V$206,"<>REJEITADO") -> 28791.51
A11: 7 | B11: INSTALAÇÕES ELÉTRICAS | C11: =COUNTIFS('MAPA COMPARATIVO'!$B$5:$B$206,$A11,'MAPA COMPARATIVO'!$F$5:$F$206,"ERRO",'MAPA COMPARATIVO'!$V$5:$V$206,"<>REJEITADO") -> 2 | D11: =COUNTIFS('MAPA COMPARATIVO'!$B$5:$B$206,$A11,'MAPA COMPARATIVO'!$F$5:$F$206,"FALHA/OMISSÃO",'MAPA COMPARATIVO'!$V$5:$V$206,"<>REJEITADO") -> 6 | E11: =COUNTIFS('MAPA COMPARATIVO'!$B$5:$B$206,$A11,'MAPA COMPARATIVO'!$F$5:$F$206,"DUPLICAÇÃO",'MAPA COMPARATIVO'!$V$5:$V$206,"<>REJEITADO") -> 1 | F11: =COUNTIFS('MAPA COMPARATIVO'!$B$5:$B$206,$A11,'MAPA COMPARATIVO'!$F$5:$F$206,"PREÇO BAIXO",'MAPA COMPARATIVO'!$V$5:$V$206,"<>REJEITADO") -> 4 | G11: =COUNTIFS('MAPA COMPARATIVO'!$B$5:$B$206,$A11,'MAPA COMPARATIVO'!$F$5:$F$206,"PREÇO ALTO",'MAPA COMPARATIVO'!$V$5:$V$206,"<>REJEITADO") -> 0 | H11: =COUNTIFS('MAPA COMPARATIVO'!$B$5:$B$206,$A11,'MAPA COMPARATIVO'!$F$5:$F$206,"INCOERÊNCIA",'MAPA COMPARATIVO'!$V$5:$V$206,"<>REJEITADO") -> 1 | I11: =COUNTIFS('MAPA COMPARATIVO'!$B$5:$B$206,$A11,'MAPA COMPARATIVO'!$F$5:$F$206,"DESCRIÇÃO",'MAPA COMPARATIVO'!$V$5:$V$206,"<>REJEITADO") -> 3 | J11: =COUNTIFS('MAPA COMPARATIVO'!$B$5:$B$206,$A11,'MAPA COMPARATIVO'!$F$5:$F$206,"NORMA",'MAPA COMPARATIVO'!$V$5:$V$206,"<>REJEITADO") -> 0 | K11: =COUNTIFS('MAPA COMPARATIVO'!$B$5:$B$206,$A11,'MAPA COMPARATIVO'!$F$5:$F$206,"INCOMPATIBILIDADE",'MAPA COMPARATIVO'!$V$5:$V$206,"<>REJEITADO") -> 0 | L11: =COUNTIFS('MAPA COMPARATIVO'!$B$5:$B$206,$A11,'MAPA COMPARATIVO'!$F$5:$F$206,"EXTRA/FORA DE ÂMBITO",'MAPA COMPARATIVO'!$V$5:$V$206,"<>REJEITADO") -> 1 | M11: =COUNTIFS('MAPA COMPARATIVO'!$B$5:$B$206,$A11,'MAPA COMPARATIVO'!$F$5:$F$206,"VERIFICAR",'MAPA COMPARATIVO'!$V$5:$V$206,"<>REJEITADO") -> 5 | N11: =SUM(C11:M11) -> 23 | O11: =COUNTIFS('MAPA COMPARATIVO'!$B$5:$B$206,$A11,'MAPA COMPARATIVO'!$G$5:$G$206,"CRÍTICA",'MAPA COMPARATIVO'!$V$5:$V$206,"<>REJEITADO") -> 0 | P11: =COUNTIFS('MAPA COMPARATIVO'!$B$5:$B$206,$A11,'MAPA COMPARATIVO'!$G$5:$G$206,"ALTA",'MAPA COMPARATIVO'!$V$5:$V$206,"<>REJEITADO") -> 4 | Q11: =COUNTIFS('MAPA COMPARATIVO'!$B$5:$B$206,$A11,'MAPA COMPARATIVO'!$G$5:$G$206,"MÉDIA",'MAPA COMPARATIVO'!$V$5:$V$206,"<>REJEITADO") -> 11 | R11: =COUNTIFS('MAPA COMPARATIVO'!$B$5:$B$206,$A11,'MAPA COMPARATIVO'!$G$5:$G$206,"BAIXA",'MAPA COMPARATIVO'!$V$5:$V$206,"<>REJEITADO") -> 8 | S11: =SUMIFS('MAPA COMPARATIVO'!$O$5:$O$206,'MAPA COMPARATIVO'!$B$5:$B$206,$A11,'MAPA COMPARATIVO'!$V$5:$V$206,"<>REJEITADO") -> 13523.8 | T11: =SUMIFS('MAPA COMPARATIVO'!$P$5:$P$206,'MAPA COMPARATIVO'!$B$5:$B$206,$A11,'MAPA COMPARATIVO'!$V$5:$V$206,"<>REJEITADO") -> 68197.32
A12: 8 | B12: INSTALAÇÕES DE TELECOMUNICAÇÕES | C12: =COUNTIFS('MAPA COMPARATIVO'!$B$5:$B$206,$A12,'MAPA COMPARATIVO'!$F$5:$F$206,"ERRO",'MAPA COMPARATIVO'!$V$5:$V$206,"<>REJEITADO") -> 0 | D12: =COUNTIFS('MAPA COMPARATIVO'!$B$5:$B$206,$A12,'MAPA COMPARATIVO'!$F$5:$F$206,"FALHA/OMISSÃO",'MAPA COMPARATIVO'!$V$5:$V$206,"<>REJEITADO") -> 2 | E12: =COUNTIFS('MAPA COMPARATIVO'!$B$5:$B$206,$A12,'MAPA COMPARATIVO'!$F$5:$F$206,"DUPLICAÇÃO",'MAPA COMPARATIVO'!$V$5:$V$206,"<>REJEITADO") -> 0 | F12: =COUNTIFS('MAPA COMPARATIVO'!$B$5:$B$206,$A12,'MAPA COMPARATIVO'!$F$5:$F$206,"PREÇO BAIXO",'MAPA COMPARATIVO'!$V$5:$V$206,"<>REJEITADO") -> 0 | G12: =COUNTIFS('MAPA COMPARATIVO'!$B$5:$B$206,$A12,'MAPA COMPARATIVO'!$F$5:$F$206,"PREÇO ALTO",'MAPA COMPARATIVO'!$V$5:$V$206,"<>REJEITADO") -> 0 | H12: =COUNTIFS('MAPA COMPARATIVO'!$B$5:$B$206,$A12,'MAPA COMPARATIVO'!$F$5:$F$206,"INCOERÊNCIA",'MAPA COMPARATIVO'!$V$5:$V$206,"<>REJEITADO") -> 0 | I12: =COUNTIFS('MAPA COMPARATIVO'!$B$5:$B$206,$A12,'MAPA COMPARATIVO'!$F$5:$F$206,"DESCRIÇÃO",'MAPA COMPARATIVO'!$V$5:$V$206,"<>REJEITADO") -> 0 | J12: =COUNTIFS('MAPA COMPARATIVO'!$B$5:$B$206,$A12,'MAPA COMPARATIVO'!$F$5:$F$206,"NORMA",'MAPA COMPARATIVO'!$V$5:$V$206,"<>REJEITADO") -> 0 | K12: =COUNTIFS('MAPA COMPARATIVO'!$B$5:$B$206,$A12,'MAPA COMPARATIVO'!$F$5:$F$206,"INCOMPATIBILIDADE",'MAPA COMPARATIVO'!$V$5:$V$206,"<>REJEITADO") -> 0 | L12: =COUNTIFS('MAPA COMPARATIVO'!$B$5:$B$206,$A12,'MAPA COMPARATIVO'!$F$5:$F$206,"EXTRA/FORA DE ÂMBITO",'MAPA COMPARATIVO'!$V$5:$V$206,"<>REJEITADO") -> 0 | M12: =COUNTIFS('MAPA COMPARATIVO'!$B$5:$B$206,$A12,'MAPA COMPARATIVO'!$F$5:$F$206,"VERIFICAR",'MAPA COMPARATIVO'!$V$5:$V$206,"<>REJEITADO") -> 0 | N12: =SUM(C12:M12) -> 2 | O12: =COUNTIFS('MAPA COMPARATIVO'!$B$5:$B$206,$A12,'MAPA COMPARATIVO'!$G$5:$G$206,"CRÍTICA",'MAPA COMPARATIVO'!$V$5:$V$206,"<>REJEITADO") -> 0 | P12: =COUNTIFS('MAPA COMPARATIVO'!$B$5:$B$206,$A12,'MAPA COMPARATIVO'!$G$5:$G$206,"ALTA",'MAPA COMPARATIVO'!$V$5:$V$206,"<>REJEITADO") -> 0 | Q12: =COUNTIFS('MAPA COMPARATIVO'!$B$5:$B$206,$A12,'MAPA COMPARATIVO'!$G$5:$G$206,"MÉDIA",'MAPA COMPARATIVO'!$V$5:$V$206,"<>REJEITADO") -> 2 | R12: =COUNTIFS('MAPA COMPARATIVO'!$B$5:$B$206,$A12,'MAPA COMPARATIVO'!$G$5:$G$206,"BAIXA",'MAPA COMPARATIVO'!$V$5:$V$206,"<>REJEITADO") -> 0 | S12: =SUMIFS('MAPA COMPARATIVO'!$O$5:$O$206,'MAPA COMPARATIVO'!$B$5:$B$206,$A12,'MAPA COMPARATIVO'!$V$5:$V$206,"<>REJEITADO") -> 2600 | T12: =SUMIFS('MAPA COMPARATIVO'!$P$5:$P$206,'MAPA COMPARATIVO'!$B$5:$B$206,$A12,'MAPA COMPARATIVO'!$V$5:$V$206,"<>REJEITADO") -> 6300
A13: 9 | B13: SEGURANÇA CONTRA INCÊNDIO | C13: =COUNTIFS('MAPA COMPARATIVO'!$B$5:$B$206,$A13,'MAPA COMPARATIVO'!$F$5:$F$206,"ERRO",'MAPA COMPARATIVO'!$V$5:$V$206,"<>REJEITADO") -> 0 | D13: =COUNTIFS('MAPA COMPARATIVO'!$B$5:$B$206,$A13,'MAPA COMPARATIVO'!$F$5:$F$206,"FALHA/OMISSÃO",'MAPA COMPARATIVO'!$V$5:$V$206,"<>REJEITADO") -> 2 | E13: =COUNTIFS('MAPA COMPARATIVO'!$B$5:$B$206,$A13,'MAPA COMPARATIVO'!$F$5:$F$206,"DUPLICAÇÃO",'MAPA COMPARATIVO'!$V$5:$V$206,"<>REJEITADO") -> 0 | F13: =COUNTIFS('MAPA COMPARATIVO'!$B$5:$B$206,$A13,'MAPA COMPARATIVO'!$F$5:$F$206,"PREÇO BAIXO",'MAPA COMPARATIVO'!$V$5:$V$206,"<>REJEITADO") -> 0 | G13: =COUNTIFS('MAPA COMPARATIVO'!$B$5:$B$206,$A13,'MAPA COMPARATIVO'!$F$5:$F$206,"PREÇO ALTO",'MAPA COMPARATIVO'!$V$5:$V$206,"<>REJEITADO") -> 0 | H13: =COUNTIFS('MAPA COMPARATIVO'!$B$5:$B$206,$A13,'MAPA COMPARATIVO'!$F$5:$F$206,"INCOERÊNCIA",'MAPA COMPARATIVO'!$V$5:$V$206,"<>REJEITADO") -> 0 | I13: =COUNTIFS('MAPA COMPARATIVO'!$B$5:$B$206,$A13,'MAPA COMPARATIVO'!$F$5:$F$206,"DESCRIÇÃO",'MAPA COMPARATIVO'!$V$5:$V$206,"<>REJEITADO") -> 0 | J13: =COUNTIFS('MAPA COMPARATIVO'!$B$5:$B$206,$A13,'MAPA COMPARATIVO'!$F$5:$F$206,"NORMA",'MAPA COMPARATIVO'!$V$5:$V$206,"<>REJEITADO") -> 0 | K13: =COUNTIFS('MAPA COMPARATIVO'!$B$5:$B$206,$A13,'MAPA COMPARATIVO'!$F$5:$F$206,"INCOMPATIBILIDADE",'MAPA COMPARATIVO'!$V$5:$V$206,"<>REJEITADO") -> 0 | L13: =COUNTIFS('MAPA COMPARATIVO'!$B$5:$B$206,$A13,'MAPA COMPARATIVO'!$F$5:$F$206,"EXTRA/FORA DE ÂMBITO",'MAPA COMPARATIVO'!$V$5:$V$206,"<>REJEITADO") -> 0 | M13: =COUNTIFS('MAPA COMPARATIVO'!$B$5:$B$206,$A13,'MAPA COMPARATIVO'!$F$5:$F$206,"VERIFICAR",'MAPA COMPARATIVO'!$V$5:$V$206,"<>REJEITADO") -> 0 | N13: =SUM(C13:M13) -> 2 | O13: =COUNTIFS('MAPA COMPARATIVO'!$B$5:$B$206,$A13,'MAPA COMPARATIVO'!$G$5:$G$206,"CRÍTICA",'MAPA COMPARATIVO'!$V$5:$V$206,"<>REJEITADO") -> 0 | P13: =COUNTIFS('MAPA COMPARATIVO'!$B$5:$B$206,$A13,'MAPA COMPARATIVO'!$G$5:$G$206,"ALTA",'MAPA COMPARATIVO'!$V$5:$V$206,"<>REJEITADO") -> 0 | Q13: =COUNTIFS('MAPA COMPARATIVO'!$B$5:$B$206,$A13,'MAPA COMPARATIVO'!$G$5:$G$206,"MÉDIA",'MAPA COMPARATIVO'!$V$5:$V$206,"<>REJEITADO") -> 2 | R13: =COUNTIFS('MAPA COMPARATIVO'!$B$5:$B$206,$A13,'MAPA COMPARATIVO'!$G$5:$G$206,"BAIXA",'MAPA COMPARATIVO'!$V$5:$V$206,"<>REJEITADO") -> 0 | S13: =SUMIFS('MAPA COMPARATIVO'!$O$5:$O$206,'MAPA COMPARATIVO'!$B$5:$B$206,$A13,'MAPA COMPARATIVO'!$V$5:$V$206,"<>REJEITADO") -> 641.36 | T13: =SUMIFS('MAPA COMPARATIVO'!$P$5:$P$206,'MAPA COMPARATIVO'!$B$5:$B$206,$A13,'MAPA COMPARATIVO'!$V$5:$V$206,"<>REJEITADO") -> 1622.04
A14: 10 | B14: SEGURANÇA ATIVA | C14: =COUNTIFS('MAPA COMPARATIVO'!$B$5:$B$206,$A14,'MAPA COMPARATIVO'!$F$5:$F$206,"ERRO",'MAPA COMPARATIVO'!$V$5:$V$206,"<>REJEITADO") -> 1 | D14: =COUNTIFS('MAPA COMPARATIVO'!$B$5:$B$206,$A14,'MAPA COMPARATIVO'!$F$5:$F$206,"FALHA/OMISSÃO",'MAPA COMPARATIVO'!$V$5:$V$206,"<>REJEITADO") -> 0 | E14: =COUNTIFS('MAPA COMPARATIVO'!$B$5:$B$206,$A14,'MAPA COMPARATIVO'!$F$5:$F$206,"DUPLICAÇÃO",'MAPA COMPARATIVO'!$V$5:$V$206,"<>REJEITADO") -> 2 | F14: =COUNTIFS('MAPA COMPARATIVO'!$B$5:$B$206,$A14,'MAPA COMPARATIVO'!$F$5:$F$206,"PREÇO BAIXO",'MAPA COMPARATIVO'!$V$5:$V$206,"<>REJEITADO") -> 2 | G14: =COUNTIFS('MAPA COMPARATIVO'!$B$5:$B$206,$A14,'MAPA COMPARATIVO'!$F$5:$F$206,"PREÇO ALTO",'MAPA COMPARATIVO'!$V$5:$V$206,"<>REJEITADO") -> 0 | H14: =COUNTIFS('MAPA COMPARATIVO'!$B$5:$B$206,$A14,'MAPA COMPARATIVO'!$F$5:$F$206,"INCOERÊNCIA",'MAPA COMPARATIVO'!$V$5:$V$206,"<>REJEITADO") -> 1 | I14: =COUNTIFS('MAPA COMPARATIVO'!$B$5:$B$206,$A14,'MAPA COMPARATIVO'!$F$5:$F$206,"DESCRIÇÃO",'MAPA COMPARATIVO'!$V$5:$V$206,"<>REJEITADO") -> 0 | J14: =COUNTIFS('MAPA COMPARATIVO'!$B$5:$B$206,$A14,'MAPA COMPARATIVO'!$F$5:$F$206,"NORMA",'MAPA COMPARATIVO'!$V$5:$V$206,"<>REJEITADO") -> 0 | K14: =COUNTIFS('MAPA COMPARATIVO'!$B$5:$B$206,$A14,'MAPA COMPARATIVO'!$F$5:$F$206,"INCOMPATIBILIDADE",'MAPA COMPARATIVO'!$V$5:$V$206,"<>REJEITADO") -> 0 | L14: =COUNTIFS('MAPA COMPARATIVO'!$B$5:$B$206,$A14,'MAPA COMPARATIVO'!$F$5:$F$206,"EXTRA/FORA DE ÂMBITO",'MAPA COMPARATIVO'!$V$5:$V$206,"<>REJEITADO") -> 0 | M14: =COUNTIFS('MAPA COMPARATIVO'!$B$5:$B$206,$A14,'MAPA COMPARATIVO'!$F$5:$F$206,"VERIFICAR",'MAPA COMPARATIVO'!$V$5:$V$206,"<>REJEITADO") -> 5 | N14: =SUM(C14:M14) -> 11 | O14: =COUNTIFS('MAPA COMPARATIVO'!$B$5:$B$206,$A14,'MAPA COMPARATIVO'!$G$5:$G$206,"CRÍTICA",'MAPA COMPARATIVO'!$V$5:$V$206,"<>REJEITADO") -> 0 | P14: =COUNTIFS('MAPA COMPARATIVO'!$B$5:$B$206,$A14,'MAPA COMPARATIVO'!$G$5:$G$206,"ALTA",'MAPA COMPARATIVO'!$V$5:$V$206,"<>REJEITADO") -> 0 | Q14: =COUNTIFS('MAPA COMPARATIVO'!$B$5:$B$206,$A14,'MAPA COMPARATIVO'!$G$5:$G$206,"MÉDIA",'MAPA COMPARATIVO'!$V$5:$V$206,"<>REJEITADO") -> 4 | R14: =COUNTIFS('MAPA COMPARATIVO'!$B$5:$B$206,$A14,'MAPA COMPARATIVO'!$G$5:$G$206,"BAIXA",'MAPA COMPARATIVO'!$V$5:$V$206,"<>REJEITADO") -> 7 | S14: =SUMIFS('MAPA COMPARATIVO'!$O$5:$O$206,'MAPA COMPARATIVO'!$B$5:$B$206,$A14,'MAPA COMPARATIVO'!$V$5:$V$206,"<>REJEITADO") -> 992.12 | T14: =SUMIFS('MAPA COMPARATIVO'!$P$5:$P$206,'MAPA COMPARATIVO'!$B$5:$B$206,$A14,'MAPA COMPARATIVO'!$V$5:$V$206,"<>REJEITADO") -> 8247.73
A15: 11 | B15: INSTALAÇÕES MECÂNICAS DE AVAC | C15: =COUNTIFS('MAPA COMPARATIVO'!$B$5:$B$206,$A15,'MAPA COMPARATIVO'!$F$5:$F$206,"ERRO",'MAPA COMPARATIVO'!$V$5:$V$206,"<>REJEITADO") -> 8 | D15: =COUNTIFS('MAPA COMPARATIVO'!$B$5:$B$206,$A15,'MAPA COMPARATIVO'!$F$5:$F$206,"FALHA/OMISSÃO",'MAPA COMPARATIVO'!$V$5:$V$206,"<>REJEITADO") -> 1 | E15: =COUNTIFS('MAPA COMPARATIVO'!$B$5:$B$206,$A15,'MAPA COMPARATIVO'!$F$5:$F$206,"DUPLICAÇÃO",'MAPA COMPARATIVO'!$V$5:$V$206,"<>REJEITADO") -> 1 | F15: =COUNTIFS('MAPA COMPARATIVO'!$B$5:$B$206,$A15,'MAPA COMPARATIVO'!$F$5:$F$206,"PREÇO BAIXO",'MAPA COMPARATIVO'!$V$5:$V$206,"<>REJEITADO") -> 0 | G15: =COUNTIFS('MAPA COMPARATIVO'!$B$5:$B$206,$A15,'MAPA COMPARATIVO'!$F$5:$F$206,"PREÇO ALTO",'MAPA COMPARATIVO'!$V$5:$V$206,"<>REJEITADO") -> 0 | H15: =COUNTIFS('MAPA COMPARATIVO'!$B$5:$B$206,$A15,'MAPA COMPARATIVO'!$F$5:$F$206,"INCOERÊNCIA",'MAPA COMPARATIVO'!$V$5:$V$206,"<>REJEITADO") -> 1 | I15: =COUNTIFS('MAPA COMPARATIVO'!$B$5:$B$206,$A15,'MAPA COMPARATIVO'!$F$5:$F$206,"DESCRIÇÃO",'MAPA COMPARATIVO'!$V$5:$V$206,"<>REJEITADO") -> 2 | J15: =COUNTIFS('MAPA COMPARATIVO'!$B$5:$B$206,$A15,'MAPA COMPARATIVO'!$F$5:$F$206,"NORMA",'MAPA COMPARATIVO'!$V$5:$V$206,"<>REJEITADO") -> 0 | K15: =COUNTIFS('MAPA COMPARATIVO'!$B$5:$B$206,$A15,'MAPA COMPARATIVO'!$F$5:$F$206,"INCOMPATIBILIDADE",'MAPA COMPARATIVO'!$V$5:$V$206,"<>REJEITADO") -> 0 | L15: =COUNTIFS('MAPA COMPARATIVO'!$B$5:$B$206,$A15,'MAPA COMPARATIVO'!$F$5:$F$206,"EXTRA/FORA DE ÂMBITO",'MAPA COMPARATIVO'!$V$5:$V$206,"<>REJEITADO") -> 0 | M15: =COUNTIFS('MAPA COMPARATIVO'!$B$5:$B$206,$A15,'MAPA COMPARATIVO'!$F$5:$F$206,"VERIFICAR",'MAPA COMPARATIVO'!$V$5:$V$206,"<>REJEITADO") -> 1 | N15: =SUM(C15:M15) -> 14 | O15: =COUNTIFS('MAPA COMPARATIVO'!$B$5:$B$206,$A15,'MAPA COMPARATIVO'!$G$5:$G$206,"CRÍTICA",'MAPA COMPARATIVO'!$V$5:$V$206,"<>REJEITADO") -> 0 | P15: =COUNTIFS('MAPA COMPARATIVO'!$B$5:$B$206,$A15,'MAPA COMPARATIVO'!$G$5:$G$206,"ALTA",'MAPA COMPARATIVO'!$V$5:$V$206,"<>REJEITADO") -> 0 | Q15: =COUNTIFS('MAPA COMPARATIVO'!$B$5:$B$206,$A15,'MAPA COMPARATIVO'!$G$5:$G$206,"MÉDIA",'MAPA COMPARATIVO'!$V$5:$V$206,"<>REJEITADO") -> 2 | R15: =COUNTIFS('MAPA COMPARATIVO'!$B$5:$B$206,$A15,'MAPA COMPARATIVO'!$G$5:$G$206,"BAIXA",'MAPA COMPARATIVO'!$V$5:$V$206,"<>REJEITADO") -> 12 | S15: =SUMIFS('MAPA COMPARATIVO'!$O$5:$O$206,'MAPA COMPARATIVO'!$B$5:$B$206,$A15,'MAPA COMPARATIVO'!$V$5:$V$206,"<>REJEITADO") -> -154.13 | T15: =SUMIFS('MAPA COMPARATIVO'!$P$5:$P$206,'MAPA COMPARATIVO'!$B$5:$B$206,$A15,'MAPA COMPARATIVO'!$V$5:$V$206,"<>REJEITADO") -> -1281.75
A16: 12 | B16: INSTALAÇÕES ELETROMECÂNICAS | C16: =COUNTIFS('MAPA COMPARATIVO'!$B$5:$B$206,$A16,'MAPA COMPARATIVO'!$F$5:$F$206,"ERRO",'MAPA COMPARATIVO'!$V$5:$V$206,"<>REJEITADO") -> 0 | D16: =COUNTIFS('MAPA COMPARATIVO'!$B$5:$B$206,$A16,'MAPA COMPARATIVO'!$F$5:$F$206,"FALHA/OMISSÃO",'MAPA COMPARATIVO'!$V$5:$V$206,"<>REJEITADO") -> 0 | E16: =COUNTIFS('MAPA COMPARATIVO'!$B$5:$B$206,$A16,'MAPA COMPARATIVO'!$F$5:$F$206,"DUPLICAÇÃO",'MAPA COMPARATIVO'!$V$5:$V$206,"<>REJEITADO") -> 0 | F16: =COUNTIFS('MAPA COMPARATIVO'!$B$5:$B$206,$A16,'MAPA COMPARATIVO'!$F$5:$F$206,"PREÇO BAIXO",'MAPA COMPARATIVO'!$V$5:$V$206,"<>REJEITADO") -> 0 | G16: =COUNTIFS('MAPA COMPARATIVO'!$B$5:$B$206,$A16,'MAPA COMPARATIVO'!$F$5:$F$206,"PREÇO ALTO",'MAPA COMPARATIVO'!$V$5:$V$206,"<>REJEITADO") -> 0 | H16: =COUNTIFS('MAPA COMPARATIVO'!$B$5:$B$206,$A16,'MAPA COMPARATIVO'!$F$5:$F$206,"INCOERÊNCIA",'MAPA COMPARATIVO'!$V$5:$V$206,"<>REJEITADO") -> 0 | I16: =COUNTIFS('MAPA COMPARATIVO'!$B$5:$B$206,$A16,'MAPA COMPARATIVO'!$F$5:$F$206,"DESCRIÇÃO",'MAPA COMPARATIVO'!$V$5:$V$206,"<>REJEITADO") -> 0 | J16: =COUNTIFS('MAPA COMPARATIVO'!$B$5:$B$206,$A16,'MAPA COMPARATIVO'!$F$5:$F$206,"NORMA",'MAPA COMPARATIVO'!$V$5:$V$206,"<>REJEITADO") -> 0 | K16: =COUNTIFS('MAPA COMPARATIVO'!$B$5:$B$206,$A16,'MAPA COMPARATIVO'!$F$5:$F$206,"INCOMPATIBILIDADE",'MAPA COMPARATIVO'!$V$5:$V$206,"<>REJEITADO") -> 0 | L16: =COUNTIFS('MAPA COMPARATIVO'!$B$5:$B$206,$A16,'MAPA COMPARATIVO'!$F$5:$F$206,"EXTRA/FORA DE ÂMBITO",'MAPA COMPARATIVO'!$V$5:$V$206,"<>REJEITADO") -> 0 | M16: =COUNTIFS('MAPA COMPARATIVO'!$B$5:$B$206,$A16,'MAPA COMPARATIVO'!$F$5:$F$206,"VERIFICAR",'MAPA COMPARATIVO'!$V$5:$V$206,"<>REJEITADO") -> 1 | N16: =SUM(C16:M16) -> 1 | O16: =COUNTIFS('MAPA COMPARATIVO'!$B$5:$B$206,$A16,'MAPA COMPARATIVO'!$G$5:$G$206,"CRÍTICA",'MAPA COMPARATIVO'!$V$5:$V$206,"<>REJEITADO") -> 0 | P16: =COUNTIFS('MAPA COMPARATIVO'!$B$5:$B$206,$A16,'MAPA COMPARATIVO'!$G$5:$G$206,"ALTA",'MAPA COMPARATIVO'!$V$5:$V$206,"<>REJEITADO") -> 0 | Q16: =COUNTIFS('MAPA COMPARATIVO'!$B$5:$B$206,$A16,'MAPA COMPARATIVO'!$G$5:$G$206,"MÉDIA",'MAPA COMPARATIVO'!$V$5:$V$206,"<>REJEITADO") -> 0 | R16: =COUNTIFS('MAPA COMPARATIVO'!$B$5:$B$206,$A16,'MAPA COMPARATIVO'!$G$5:$G$206,"BAIXA",'MAPA COMPARATIVO'!$V$5:$V$206,"<>REJEITADO") -> 1 | S16: =SUMIFS('MAPA COMPARATIVO'!$O$5:$O$206,'MAPA COMPARATIVO'!$B$5:$B$206,$A16,'MAPA COMPARATIVO'!$V$5:$V$206,"<>REJEITADO") -> 0 | T16: =SUMIFS('MAPA COMPARATIVO'!$P$5:$P$206,'MAPA COMPARATIVO'!$B$5:$B$206,$A16,'MAPA COMPARATIVO'!$V$5:$V$206,"<>REJEITADO") -> 2000
... A19: GERAL | B19: Transversal / ficheiro | C19: =COUNTIFS('MAPA COMPARATIVO'!$B$5:$B$206,$A19,'MAPA COMPARATIVO'!$F$5:$F$206,"ERRO",'MAPA COMPARATIVO'!$V$5:$V$206,"<>REJEITADO") -> 3 | D19: =COUNTIFS('MAPA COMPARATIVO'!$B$5:$B$206,$A19,'MAPA COMPARATIVO'!$F$5:$F$206,"FALHA/OMISSÃO",'MAPA COMPARATIVO'!$V$5:$V$206,"<>REJEITADO") -> 1 | E19: =COUNTIFS('MAPA COMPARATIVO'!$B$5:$B$206,$A19,'MAPA COMPARATIVO'!$F$5:$F$206,"DUPLICAÇÃO",'MAPA COMPARATIVO'!$V$5:$V$206,"<>REJEITADO") -> 0 | F19: =COUNTIFS('MAPA COMPARATIVO'!$B$5:$B$206,$A19,'MAPA COMPARATIVO'!$F$5:$F$206,"PREÇO BAIXO",'MAPA COMPARATIVO'!$V$5:$V$206,"<>REJEITADO") -> 0 | G19: =COUNTIFS('MAPA COMPARATIVO'!$B$5:$B$206,$A19,'MAPA COMPARATIVO'!$F$5:$F$206,"PREÇO ALTO",'MAPA COMPARATIVO'!$V$5:$V$206,"<>REJEITADO") -> 0 | H19: =COUNTIFS('MAPA COMPARATIVO'!$B$5:$B$206,$A19,'MAPA COMPARATIVO'!$F$5:$F$206,"INCOERÊNCIA",'MAPA COMPARATIVO'!$V$5:$V$206,"<>REJEITADO") -> 0 | I19: =COUNTIFS('MAPA COMPARATIVO'!$B$5:$B$206,$A19,'MAPA COMPARATIVO'!$F$5:$F$206,"DESCRIÇÃO",'MAPA COMPARATIVO'!$V$5:$V$206,"<>REJEITADO") -> 0 | J19: =COUNTIFS('MAPA COMPARATIVO'!$B$5:$B$206,$A19,'MAPA COMPARATIVO'!$F$5:$F$206,"NORMA",'MAPA COMPARATIVO'!$V$5:$V$206,"<>REJEITADO") -> 0 | K19: =COUNTIFS('MAPA COMPARATIVO'!$B$5:$B$206,$A19,'MAPA COMPARATIVO'!$F$5:$F$206,"INCOMPATIBILIDADE",'MAPA COMPARATIVO'!$V$5:$V$206,"<>REJEITADO") -> 0 | L19: =COUNTIFS('MAPA COMPARATIVO'!$B$5:$B$206,$A19,'MAPA COMPARATIVO'!$F$5:$F$206,"EXTRA/FORA DE ÂMBITO",'MAPA COMPARATIVO'!$V$5:$V$206,"<>REJEITADO") -> 0 | M19: =COUNTIFS('MAPA COMPARATIVO'!$B$5:$B$206,$A19,'MAPA COMPARATIVO'!$F$5:$F$206,"VERIFICAR",'MAPA COMPARATIVO'!$V$5:$V$206,"<>REJEITADO") -> 1 | N19: =SUM(C19:M19) -> 5 | O19: =COUNTIFS('MAPA COMPARATIVO'!$B$5:$B$206,$A19,'MAPA COMPARATIVO'!$G$5:$G$206,"CRÍTICA",'MAPA COMPARATIVO'!$V$5:$V$206,"<>REJEITADO") -> 1 | P19: =COUNTIFS('MAPA COMPARATIVO'!$B$5:$B$206,$A19,'MAPA COMPARATIVO'!$G$5:$G$206,"ALTA",'MAPA COMPARATIVO'!$V$5:$V$206,"<>REJEITADO") -> 2 | Q19: =COUNTIFS('MAPA COMPARATIVO'!$B$5:$B$206,$A19,'MAPA COMPARATIVO'!$G$5:$G$206,"MÉDIA",'MAPA COMPARATIVO'!$V$5:$V$206,"<>REJEITADO") -> 2 | R19: =COUNTIFS('MAPA COMPARATIVO'!$B$5:$B$206,$A19,'MAPA COMPARATIVO'!$G$5:$G$206,"BAIXA",'MAPA COMPARATIVO'!$V$5:$V$206,"<>REJEITADO") -> 0 | S19: =SUMIFS('MAPA COMPARATIVO'!$O$5:$O$206,'MAPA COMPARATIVO'!$B$5:$B$206,$A19,'MAPA COMPARATIVO'!$V$5:$V$206,"<>REJEITADO") -> -12.12 | T19: =SUMIFS('MAPA COMPARATIVO'!$P$5:$P$206,'MAPA COMPARATIVO'!$B$5:$B$206,$A19,'MAPA COMPARATIVO'!$V$5:$V$206,"<>REJEITADO") -> -12.12
B20: TOTAL | C20: =SUM(C5:C19) -> 22 | D20: =SUM(D5:D19) -> 31 | E20: =SUM(E5:E19) -> 17 | F20: =SUM(F5:F19) -> 39 | G20: =SUM(G5:G19) -> 2 | H20: =SUM(H5:H19) -> 24 | I20: =SUM(I5:I19) -> 23 | J20: =SUM(J5:J19) -> 10 | ... T20: =SUM(T5:T19) -> 399725.14

Sheet DUPLICAÇÕES
A1: DUPLICAÇÕES
A2: Comparação lado a lado: o mesmo trabalho pago em dois artigos. Impacto = valor a retirar (negativo).
A4: Artigo A | B4: Descrição A (MQT) | C4: Qtd A | D4: Un | E4: Total A (€) | F4: Artigo B | G4: Descrição B (MQT) | H4: Qtd B | I4: Un | J4: Total B (€) | K4: Impacto A – mín (€) | L4: Impacto B – máx (€) | M4: Gravidade | N4: Problema | O4: Ação | P4: Verificação
A5: 2.2.2 | B5: MACIÇOS DE FUNDAÇÃO Execução de MACIÇO DE ENCABEÇAMENTO de estacas em betão armado normal cinzento , incluindo fornecimento, colocação, compactação e cura de be | C5: 63 | D5: m3 | E5: 19996.33 | F5: 2.3.3 | G5: MACIÇOS DE FUNDAÇÃO Execução de MACIÇO DE ENCABEÇAMENTO de estacas em betão armado normal cinzento , incluindo fornecimento, colocação, compactação e cura de be | H5: 63.11 | I5: m3 | J5: 20119.03 | K5: 0 | L5: -19996.33 | M5: ALTA | N5: Maciços de encabeçamento repetidos em 2.2.2 e 2.3.3 (63,00/63,11 m3) | O5: Confirmar nos desenhos de estabilidade. Se for duplicação, eliminar 2.2.2. Se não for, explicar na descrição a que microestacas se refere cada artigo. | P5: MANTIDO
A6: 2.3.3 | B6: MACIÇOS DE FUNDAÇÃO Execução de MACIÇO DE ENCABEÇAMENTO de estacas em betão armado normal cinzento , incluindo fornecimento, colocação, compactação e cura de be | C6: 63.11 | D6: m3 | E6: 20119.03 | F6: 2.2.2 | G6: MACIÇOS DE FUNDAÇÃO Execução de MACIÇO DE ENCABEÇAMENTO de estacas em betão armado normal cinzento , incluindo fornecimento, colocação, compactação e cura de be | H6: 63 | I6: m3 | J6: 19996.33 | K6: 0 | L6: 0 | M6: ALTA | N6: Par de 2.2.2 (63,11 vs 63,00 m3), com S4 em vez de S3 | O6: Ver 2.2.2. | P6: MANTIDO
A7: 3.9.2.3 | B7: SOLEIRAS EXT. Fornecimento e aplicação de Soleira em Betão Polimérico tipo Tubani ou equiv., a aplicar em vãos interiores como elemento de transição entre espaç | F7: 3.9.2.3.1 | G7: 400 mm de largura | H7: 112 | I7: ml | J7: 9520 | K7: -9940 | L7: -9940 | M7: ALTA | N7: Soleiras exteriores pagas em 3.9.2.3 e nos artigos dos vãos | O7: Retirar a soleira dos artigos de caixilharia (e reduzir os PU) ou anular o 3.9.2.3. Corrigir 'vãos interiores' para 'exteriores'. | P7: MANTIDO
A8: 5.3.7 | B8: CANAL COM GRELHA CHUVEIROS Fornecimento e assentamento de caleiras de pavimento em ferro fundido, com grelha em ferro fundido, incluindo o sinfão a instalar e | C8: 25.6 | D8: m | E8: 5632 | F8: 3.16.1.18 | G8: DRENAGEM LINEAR EM BALNEÁRIOS Fornecimento e instalação drenagem linear tipo ACO 64 em Aço Inox com grelha ranhurada. Conforme projeto de arquitetura. Incluí: | H8: 28 | I8: ml | J8: 7549.08 | K8: 0 | L8: 0 | M8: ALTA | N8: Drenagem linear dos balneários paga em 5.3.7 e 3.16.1.18 | O8: Eliminar 5.3.7, ou reduzi-lo à ligação à rede, e corrigir a referência a cozinhas. | P8: MANTIDO
A9: 6.2.18 | B9: CALEIRA Fornecimento e modelação de caleiras de recolha de águas de coberturas, em folha de zinco nº 12, incluindo quinagem, soldaduras a estanho, em conformida | F9: 6.2.18.1 | G9: 200x100 mm | H9: 196.6 | I9: m | J9: 7864 | K9: -7864 | L9: -7864 | M9: ALTA | N9: Caleiras de zinco já incluídas nos artigos de cobertura | O9: Eliminar 6.2.18, ou excluir as caleiras de 3.3.x e da nota 02 e confirmar a compatibilidade do zinco com o sistema FTB. | P9: MANTIDO
A10: 2.1.1 | B10: ESCAVAÇÃO GERAL Escavação em terreno de qualquer natureza para obtenção da cota de fundação definida em projeto, incluindo carga e transporte de material. | C10: 9861.9 | D10: m3 | E10: 54240.45 | F10: 2.1.5 | G10: TRANSPORTE A VAZADOURO Carga, transporte, descarga e colocação de terras provenientes de escavação, à distância média de 20km de acordo com as especificações do | H10: 8171.56 | I10: m3 | J10: 44943.58 | K10: 0 | L10: -8171.56 | M10: MÉDIA | N10: 'Carga e transporte' pagos em 2.1.1 e outra vez em 2.1.5 | O10: Retirar 'carga e transporte' de 2.1.1 e confirmar a natureza do terreno com o estudo geotécnico. Se houver rocha, criar um subartigo próprio. | P10: MANTIDO
A11: 3.16.1.18 | B11: DRENAGEM LINEAR EM BALNEÁRIOS Fornecimento e instalação drenagem linear tipo ACO 64 em Aço Inox com grelha ranhurada. Conforme projeto de arquitetura. Incluí: | C11: 28 | D11: ml | E11: 7549.08 | F11: 5.3.7 | G11: CANAL COM GRELHA CHUVEIROS Fornecimento e assentamento de caleiras de pavimento em ferro fundido, com grelha em ferro fundido, incluindo o sinfão a instalar e | H11: 25.6 | I11: m | J11: 5632 | K11: -5632 | L11: -7549.08 | M11: MÉDIA | N11: Drenagem linear dos balneários paga também em 5.3.7 | O11: Eliminar um dos artigos e uniformizar o material. | P11: MANTIDO
A12: 10.5.1 | B12: O fornecimento e montagem de toda a rede de caixas e tubagens necessária para a instalação dos equipamentos de segurança são para serem executados pela Empreita | C12: 1 | D12: UN | E12: 1632.31 | F12: 7.10 | G12: INFRAESTRUTURAS ELECTRICAS PARA INSTALAÇÕES DE SEGURANÇA ATIVA | J12: 513.7 | K12: -513.7 | L12: -1632.31 | M12: MÉDIA | N12: Tubagem de segurança paga no Cap. 10 e no Cap. 7 | O12: Eliminar 10.5.1 (ou 7.10) e consolidar a medição num único artigo. | P12: CORRIGIDO
A13: 3.11.2.19 | B13: Fornecimento e aplicação de porta CF metálica de 1 folha de batente, em chapa de aço eletrozincado tipo TRIA, série SISAF ES1, ou equivalente. Utilização do aro | F13: 10.1.9 | G13: Retentores Electromagnéticos | H13: 2 | I13: UN | J13: 155.26 | K13: 0 | L13: 0 | M13: BAIXA | N13: Retentores GEZE pagos na porta e de novo em 10.1.9 | O13: Manter o retentor num só artigo (o 10.1.9 limitado à ligação) e acertar a quantidade. | P13: MANTIDO
A14: 3.16.1.3 | B14: LAVATÓRIO SUSPENSO Fornecimento e instalação de Lavatório suspenso tipo SANINDUSA, série Sanlife, quadrangular com furo para torneira, 400x400x145, cor branco, | C14: 20 | D14: UN | E14: 3785.2 | F14: 5.3.1 | G14: SIFÕES LAVATÓRIOS Fornecimento e assentamento de sifões tipo garrafa, ou S de latão cromado a aplicar em lavatórios. Em conformidade com as peças desenhadas, in | K14: 0 | L14: 0 | M14: BAIXA | N14: Sifão dos 20 lavatórios pago aqui e em 5.3.1 | O14: Retirar o sifão do 3.16.1.3 ou reduzir o 5.3.1 para 4 UN. | P14: MANTIDO
A15: 3.16.1.4 | B15: URINOL Fornecimento e instalação de urinol, tipo SANINDUSA, série Forma com alimentação de água por cima ref. 108561004 com Kit de fixação 21 para colunas suspe | C15: 6 | D15: UN | E15: 1170.18 | F15: 5.3.2 | G15: SIFÕES MICTÓRIOS Fornecimento e assentamento de sifões a aplicar em mictórios. Em conformidade com as peças desenhadas, incluindo todos os acessórios e trabalho | K15: 0 | L15: 0 | M15: BAIXA | N15: Sifão dos urinóis pago duas vezes; 7 sifões para 6 | O15: Retirar o sifão de um dos artigos e acertar a quantidade. | P15: MANTIDO
A16: 4.5.5 | B16: PINTURA DA REDE DE INCÊNDIOS Pintura da rede de incêndio e acessórios com as cores normalizadas de sinalização (de acordo com a norma NP-182), com tintas baças | C16: 1 | D16: UN | E16: 250 | F16: 4.5.4 | G16: PINTURA DA REDE DE ABASTECIMENTO Pintura da rede á vista e acessórios de água quente e fria com as cores normalizadas de sinalização (de acordo com a norma NP - | H16: 1 | I16: UN | J16: 350 | K16: 0 | L16: -1000 | M16: BAIXA | N16: Pintura das redes paga nos artigos de tubagem e de pintura | O16: Retirar 'pintura a tinta adequada' dos artigos de tubagem, ou limitar 4.5.4/4.5.5/5.4.4 à identificação (setas e legendas). | P16: MANTIDO
A17: 5.3.1 | B17: SIFÕES LAVATÓRIOS Fornecimento e assentamento de sifões tipo garrafa, ou S de latão cromado a aplicar em lavatórios. Em conformidade com as peças desenhadas, in | F17: 5.3.1.1 | G17: DN 40 | H17: 24 | I17: UN | J17: 840 | K17: -700 | L17: -840 | M17: BAIXA | N17: Sifões de lavatório pagos duas vezes (5.3.1 e 3.16.1.3) | O17: Eliminar 5.3.1, ou retirar o sifão de 3.16.1.3 e manter um só artigo. | P17: MANTIDO
A18: 5.3.2 | B18: SIFÕES MICTÓRIOS Fornecimento e assentamento de sifões a aplicar em mictórios. Em conformidade com as peças desenhadas, incluindo todos os acessórios e trabalho | F18: 5.3.2.1 | G18: DN 50 | H18: 7 | I18: UN | J18: 245 | K18: -210 | L18: -245 | M18: BAIXA | N18: Sifões de urinol já incluídos e 7 sifões para 6 urinóis | O18: Eliminar 5.3.2. | P18: MANTIDO
A19: 7.2.8.4.1 | B19: PEADØ110 | C19: 155 | D19: m | E19: 699.05 | F19: 7.1.2.2 | G19: PEAD 110 | H19: 155 | I19: m | J19: 699.05 | K19: -699.05 | L19: -699.05 | M19: BAIXA | N19: Tubo PEAD Ø110 da entrada de energia medido duas vezes | O19: Eliminar 7.2.8.4.1, ou redescrevê-lo como tubo de reserva se o projeto o exigir. | P19: MANTIDO
A20: 10.1.9 | B20: Retentores Electromagnéticos | C20: 2 | D20: UN | E20: 155.26 | F20: 3.11.2.19 | G20: Fornecimento e aplicação de porta CF metálica de 1 folha de batente, em chapa de aço eletrozincado tipo TRIA, série SISAF ES1, ou equivalente. Utilização do aro | K20: -155.26 | L20: -155.26 | M20: BAIXA | N20: Retentores eletromagnéticos já incluídos nas portas corta-fogo | O20: Eliminar 10.1.9, ou redescrevê-lo como 'ligação dos retentores'. | P20: MANTIDO
A21: 11.2.1 | B21: . BC AQS 1 e 2: ENERGIE, AquaPura X60 HT Acessórios e válvulas: grupo hidraúlico de segurança, todas as válvulas e acessórios necessários, vaso de Expansão, vá | C21: 2 | D21: UN | E21: 29076.88 | F21: 4.3.6.1 | G21: DN 20 | H21: 1 | I21: UN | J21: 678 | K21: 0 | L21: 0 | M21: BAIXA | N21: Grupo de segurança AQS medido também em 4.3.8 e 11.3.3 | O21: Clarificar qual artigo inclui o grupo/válvula de segurança da produção de AQS e excluí-lo nos outros. Manter 4.3.6. | P21: MANTIDO

Sheet INCOERÊNCIAS DE PREÇO
A1: INCOERÊNCIAS DE PREÇO
A2: Mesmo trabalho (ou trabalho equivalente) com preços/quantidades diferentes entre artigos. Δ% = PU A / PU B − 1.
A4: Artigo A | B4: Descrição A | C4: Un | D4: PU A (€) | E4: Artigo B | F4: Descrição B | G4: Un | H4: PU B (€) | I4: Δ% A vs B | J4: Problema | K4: O que deveria estar | L4: Impacto A – mín (€) | M4: Impacto B – máx (€) | N4: Gravidade | O4: Verificação
A5: 2.2.1 | B5: MICROESTACAS Execução de microestaca para fundação, com um comprimento médio de 8,50 m, 200 mm de diâmetro nominal, composta de armadura tub | C5: ml | D5: 90.03 | E5: 2.3.1.1 | F5: 101.6x6.5 | G5: ml | H5: 134.17 | I5: =IF(AND(ISNUMBER(D5),ISNUMBER(H5),H5<>0),D5/H5-1,"") -> -0.32898562 | J5: Microestaca 101,6×6,5 a 90,03 €/ml e a 134,17 €/ml (+49%) | K5: Um só PU para a mesma microestaca: 90–105 €/ml (o PU de 2.2.1 já é um valor de mercado). | L5: -15320.67 | M5: -23183.21 | N5: ALTA | O5: MANTIDO
A6: 2.2.5 | B6: PERFIS SELADOS TUBULARES Execução de perfis selados, com um comprimento médio estimado de 9 a 10 m de comprimento, 200 mm de diâmetro nomina | C6: ml | D6: 74.57 | E6: 2.3.1.2 | F6: 88.9x6.5 | G6: ml | H6: 126.31 | I6: =IF(AND(ISNUMBER(D6),ISNUMBER(H6),H6<>0),D6/H6-1,"") -> -0.40962711 | J6: Microestaca 88,9×6,5 a 74,57 €/ml e a 126,31 €/ml (+69%) | K6: Um só PU para a mesma microestaca 88,9×6,5 N80 IRS: 75–90 €/ml. Um comprimento maior não encarece o metro. | L6: -20156.04 | M6: -28721.39 | N6: ALTA | O6: MANTIDO
A7: 2.6.5 | B7: DRENO TARDOZ PAREDES DE CONTENÇÃO E MUROS DE SUPORTE Fornecimento e colocação de dreno, no tardoz de muro de suporte e paredes de contenção, | C7: ml | D7: 20.32 | E7: 6.2.8.2 | F7: DN 160 | G7: m | H7: 7.65 | I7: =IF(AND(ISNUMBER(D7),ISNUMBER(H7),H7<>0),D7/H7-1,"") -> 1.6562092 | J7: O mesmo dreno DN160 a 20,32 €/ml (2.6.5) e a 7,65 €/m (6.2.8.2) | K7: Um PU coerente para o mesmo produto (cerca de 15–22 €/ml com secção drenante de 0,40×0,40) e a confirmação de que os 420 m de 6.2.8.2 não incluem os 244,57 ml do tardoz. | L7: 0 | M7: -4969.17 | N7: MÉDIA | O7: MANTIDO
A8: 3.6.1.2 | B8: Fornecimento e aplicação de sub-estrutura em perfis de aço galvanizado para a fixação da chapa ondulada em paredes exteriores. | C8: m2 | D8: 12.5 | E8: 3.6.1.1 | F8: Fornecimento e aplicação de chapa ondulada de 0.7mm de espessura tipo FTB ou equiv. | G8: m2 | H8: 25.44 | I8: =IF(AND(ISNUMBER(D8),ISNUMBER(H8),H8<>0),D8/H8-1,"") -> -0.5086478 | J8: Subestrutura de 320 m2 para 1 550 m2 de chapa ondulada | K8: Subestrutura medida na mesma área da chapa (1 550 m²), como o próprio MQT faz em 3.10.5, ou justificação das zonas onde a chapa não a precisa (por exemplo, sobre o painel sandwich do 3.5.1, que já inclui subestrutura). | L8: 0 | M8: 15375 | N8: MÉDIA | O8: CORRIGIDO
A9: 3.9.1.2 | B9: PAV I 02 Fornecimento e aplicação de Pavimento em Betão Armado tipo SECIL UNIPISO ( 10cm) ou equiv. Incluí: - Camada de betão leve de enchim | E9: 3.9.1.2.1 | F9: Piso 01 | G9: m2 | H9: 35 | I9: =IF(AND(ISNUMBER(D9),ISNUMBER(H9),H9<>0),D9/H9-1,"") | J9: Unipiso interior 10 cm mais caro que exterior 12 cm com brita | K9: O sistema exterior (12 cm + caixa de brita 20 cm + manta) deve ser mais caro do que o interior (10 cm + betão leve), com uma referência de 39–46 €/m². | L9: 0 | M9: 0 | N9: MÉDIA | O9: MANTIDO
A10: 3.11.2.9.1 | B10: VE.2.03 com 5,33x2,40 | C10: UN | D10: 7024.85 | E10: 3.11.2.8 | F10: VE.2.02 com 5,33x2,40 Fornecimento e aplicação de caixilharia em perfis de alumínio com 3 folha fixa tipo Navarra fachada cortina série 1520 | G10: UN | H10: 5547.92 | I10: =IF(AND(ISNUMBER(D10),ISNUMBER(H10),H10<>0),D10/H10-1,"") -> 0.26621328 | J10: Vão só com fixos mais caro que vãos iguais com basculante | K10: Um vão só com folhas fixas não deve custar mais do que vãos iguais com folhas móveis. Referência: ≤5 547,92 € (VE.2.02). | L10: 0 | M10: -4430.79 | N10: MÉDIA | O10: MANTIDO
